Workbook

Sheet Cover
A1: HOME FINANCE PLANNING WORKBOOK
A2: Loan affordability, repayment, investment growth, and a practical roadmap for the wider financial journey
A4: CONTENTS | B4: PURPOSE | C4: REVIEW STATUS
A5: Rent vs Buy | B5: Compares purchasing a home with renting and investing the avoided down payment and monthly savings. | C5: Reviewed by Ashwani
A6: Home Loan Analysis | B6: Evaluates home ownership against SIP investing under common long-term assumptions. | C6: Reviewed by Ashwani
A7: EMI Calculator | B7: Calculates EMI and provides a yearly principal-and-interest repayment schedule. | C7: Reviewed by Ashwani
A8: SIP Growth | B8: Projects yearly SIP growth, tax, inflation-adjusted value, and model assumptions. | C8: Reviewed by Ashwani
A9: Expense Ratio Impact | B9: Compares direct and regular mutual fund expense ratios and shows the long-term rupee cost over 5–30 years. | C9: Reviewed by Ashwani
A10: Loan Prepayment | B10: Models normal repayment, five lump sums, monthly extra payments, rate changes, and a combined scenario. | C10: Pending manual review
A11: Step-Up SIP Goal | B11: Calculates the starting SIP and annual step-up needed for an inflation-adjusted future goal after simplified tax. | C11: Pending manual review
A12: Retirement SWP | B12: Calculates the retirement corpus required, tests the current saving path, and models inflation-linked withdrawals for up to 40 years. | C12: Pending manual review
A13: Emergency Fund | B13: Builds a risk-adjusted emergency target from essential expenses and projects the month-by-month funding path. | C13: Pending manual review
A14: Net Worth & Cash Flow | B14: Tracks household net worth, savings rate, debt burden, liquidity, and monthly goal capacity. | C14: Pending manual review
A15: Term Insurance | B15: Estimates family protection from income replacement, loans, future goals, available assets, and existing cover. | C15: Pending manual review
... A18: Prepay vs Invest | B18: Compares investing surplus with two loan-prepayment strategies using post-tax wealth, risk, and liquidity. | C18: Pending manual review
A19: RECOMMENDED CALCULATOR ROADMAP
A20: Priority | B20: Calculator to create | C20: What it should answer
A21: 1 — Built | B21: Mutual Fund Expense-Ratio Impact | C21: How much wealth is lost over time because of fund expenses? Compare two expense ratios, direct vs regular plans, and show the rupee cost after 5–30 years.
A22: 2 — Built | B22: Home-Loan Part-Payment & Prepayment | C22: How much interest and tenure can be saved with one-time or annual prepayments? Choose Reduce EMI or Reduce Tenure and compare the outcome.
A23: 3 — Built | B23: Step-Up SIP Goal Planner | C23: What starting SIP and annual increase are needed for a future goal after inflation and simplified tax? Includes a 30-year funding schedule.
A24: 4 — Built | B24: Prepay Loan vs Invest | C24: Should surplus cash be used to prepay the loan or invested? Compare guaranteed interest savings with uncertain post-tax investment returns.
A25: 5 — Built | B25: Retirement Corpus & SWP | C25: How large a retirement corpus is required, and how long could it last under inflation, returns, taxes, and monthly withdrawals?
A26: 6 — Built | B26: Emergency-Fund Calculator | C26: How many months of essential expenses should be held, and how long will it take to build the target?
A27: 7 — Built | B27: Net-Worth & Monthly Cash-Flow Tracker | C27: What is the household’s current net worth, savings rate, debt burden, and monthly surplus available for goals?
A28: 8 — Built | B28: Term-Insurance Need Calculator | C28: How much life cover may be needed after considering dependants, debts, future goals, existing assets, and current insurance?
A29: 9 — Built | B29: Asset-Allocation & Rebalancing Tool | C29: What equity, debt, gold, and cash mix matches the goal horizon and risk comfort, and what trades restore the target allocation?
A30: 10 — Built | B30: Goal-Based Investment Dashboard | C30: Track several goals together, show funded percentage, monthly gap, required SIP, and priority when cash is limited.
A32: ARTICLE & LEARNING ROADMAP
A33: Status / journey stage | B33: Article to write | C33: Simple-language focus
A34: Covered in calculator — Safety | B34: How to Build an Emergency Fund | C34: What counts as an emergency, where to keep the money, and why emergency savings come before aggressive investing.
A35: Pending — Start here | B35: Needs, Wants, Savings and Debt | C35: A simple monthly-money system, savings rate, debt priorities, and how to avoid investing money needed soon.
A36: Covered in calculator — Mutual funds | B36: How Expense Ratio Quietly Reduces Wealth | C36: Explain TER, daily NAV deduction, compounding drag, and why a small annual percentage can create a large long-term rupee difference.
A37: Pending — Mutual funds | B37: How to Choose a Mutual Fund Without Technical Jargon | C37: Start with the goal and horizon, select a suitable category, check the SEBI Riskometer, understand costs, compare consistency, and avoid chasing last year’s winner.
A38: Pending — Mutual funds | B38: Direct vs Regular Mutual Funds | C38: Same portfolio but different costs and support: who may prefer DIY direct plans and who may value professional guidance.
A39: Covered in calculators — Mutual funds | B39: SIP, Lumpsum and Step-Up SIP | C39: When each method may fit, how cash-flow timing changes results, and why discipline matters more than predicting the market.
A40: Covered in calculator — Home loans | B40: How Part-Payment Reduces Home-Loan Interest | C40: Why early prepayments save more interest, the difference between reducing EMI and tenure, and what to confirm with the lender.
A41: Pending — Home loans | B41: Prepay Loan or Invest Surplus? A Decision Framework | C41: Compare certainty, liquidity, tax, risk, return assumptions, and the emotional benefit of becoming debt-free.
A42: Built article — Retirement | B42: Nominal Wealth vs Real Wealth | C42: Show why inflation changes purchasing power and why retirement and long-term goals must be planned in today’s rupees.
A43: Pending — Retirement | B43: Sequence-of-Returns Risk in Retirement | C43: Explain why poor returns early in retirement can be damaging even when the long-term average return looks acceptable.
A44: Pending — Protection | B44: Term Insurance and Health Insurance Basics | C44: Explain what each policy protects, common exclusions, adequate cover, and why insurance is not an investment return product.
A45: Pending — Behaviour | B45: Common Investor Mistakes | C45: Chasing returns, panic selling, over-diversifying, ignoring costs and tax, borrowing to invest, and changing plans too often.
A47: CURRENT WORKBOOK STATUS
A48: Item | B48: Status | C48: Detail
A49: Visible financial tools | B49: 14 built; 5 reviewed | C49: All 14 visible financial tools are available; 5 are reviewed and 9 remain pending manual review.
A50: Roadmap calculators | B50: 10 built / 0 pending | C50: Priorities 1–10 are complete; the calculator roadmap is finished and ready for manual review.
A51: Full educational articles | B51: 1 built | C51: Nominal Wealth vs Real Wealth is included in SIP Growth.
A52: Embedded learning guides | B52: 13 covered | C52: All calculators except Home Loan Analysis include embedded explanations, coaching guidance, or assumptions.
A53: Hidden calculation support | B53: 2 built | C53: Prepayment Engine and PVI Engine support the loan calculators and remain hidden.
A54: Mutual Fund Selection Guide | B54: Pending | C54: Still the highest-priority standalone article for beginner investors.
A55: Workbook status | B55: Calculator roadmap complete; 5 reviewed / 9 pending | C55: Nine calculators await manual review; the separate educational article roadmap remains open.
A56: NEXT RECOMMENDED WORK
A58: Order | B58: Build / review | C58: Why it comes next
A59: 1 | B59: Manual review of 9 pending calculators | C59: Validate assumptions, formulas, labels, and coaching across the calculators still marked pending manual review.
A60: 2 | B60: Needs, Wants, Savings and Debt | C60: Adds a beginner-friendly monthly money system to complement the cash-flow tracker.
A61: 3 | B61: Mutual Fund Selection Guide | C61: Explains category fit, Riskometer, costs, consistency, and avoiding performance chasing.
A62: 4 | B62: Direct vs Regular Mutual Funds | C62: Clarifies the cost-versus-advice trade-off without implying one choice suits everyone.
A63: 5 | B63: Sequence-of-Returns Risk | C63: Deepens the retirement planner with a plain-language explanation of early-retirement risk.
A65: WRITING PRINCIPLES FOR EVERY ARTICLE
A66: Use one relatable rupee example, distinguish assumptions from facts, show both benefits and risks, explain tax and inflation separately, avoid promising returns, and end with a short checklist the reader can act on.

Sheet Common Assumptions
A1: COMMON ASSUMPTIONS — MODEL CONTROL
A2: Edit the blue cells only. Linked calculators update automatically; scenario-specific exceptions are listed below.
A4: PARAMETER | B4: DEFAULT | C4: UNIT | D4: APPLIES TO
A5: General inflation | B5: 6 | C5: % p.a. | D5: Real-value and future-cost calculations
A6: Illustrative investment return | B6: 12 | C6: % p.a. | D6: Long-term SIP / equity illustrations
A7: Home / general loan rate | B7: 7.5 | C7: % p.a. | D7: Home-loan and loan-comparison calculators
A8: Property appreciation | B8: 10 | C8: % p.a. | D8: Property comparison models
A9: Property maintenance | B9: 1 | C9: % p.a. | D9: Property comparison models
A10: Direct-plan / investment cost | B10: 0.5 | C10: % p.a. | D10: Investment cost assumptions
A11: Regular-plan expense ratio | B11: 1.5 | C11: % p.a. | D11: Expense-ratio comparison only
A12: LTCG tax rate | B12: 12.5 | C12: % | D12: Simplified investment tax illustrations
A13: LTCG exemption | B13: 125000 | C13: ₹ | D13: Simplified investment tax illustrations
A14: Annual rent increase | B14: 10 | C14: % p.a. | D14: Rent vs Buy only
A15: Annual SIP step-up | B15: 10 | C15: % p.a. | D15: Step-Up SIP Goal only
A16: Post-retirement gross return | B16: 8 | C16: % p.a. | D16: Retirement withdrawal phase only
A17: Liquid savings return | B17: 4 | C17: % p.a. | D17: Emergency-fund savings only
A19: SCENARIO-SPECIFIC EXCEPTIONS
A20: Loan reset rate | B20: Linked to common loan rate by default | D20: Overwrite only to test a lender reset scenario
A21: Goal-level return | B21: 12% for ordinary goals; 4% for emergency fund | D21: Separates long-term investment from liquid savings
A22: Post-retirement tax/cost drag | B22: Kept in scenario sheet | D22: Distinct from pre-retirement investment cost
A23: LTV loan-size threshold 1 | B23: 3000000 | C23: ₹ loan amount | D23: Home Loan Analysis; Rent vs Buy — RBI Master Circular – Housing Finance (rbi.org.in)
A24: LTV loan-size threshold 2 | B24: 7500000 | C24: ₹ loan amount | D24: Home Loan Analysis; Rent vs Buy — RBI Master Circular – Housing Finance (rbi.org.in)
A25: Maximum LTV — band 1 | B25: 90 | C25: % | D25: Home Loan Analysis; Rent vs Buy — RBI Master Circular – Housing Finance (rbi.org.in)
A26: Maximum LTV — band 2 | B26: 80 | C26: % | D26: Home Loan Analysis; Rent vs Buy — RBI Master Circular – Housing Finance (rbi.org.in)
A27: Maximum LTV — band 3 | B27: 75 | C27: % | D27: Home Loan Analysis; Rent vs Buy — RBI Master Circular – Housing Finance (rbi.org.in)
A28: Tax rate on property sale gain | B28: 12.5 | C28: % | D28: Property comparisons — Income Tax Department capital gains page; applies to property bought on or after 23 July 2024
A29: Selling cost | B29: 0 | C29: % of sale value | D29: Property comparisons

Sheet Rent vs Buy
A1: RENT VS BUY — LONG-TERM WEALTH COMPARISON
A2: Buying means living in the ready-possession home and repaying the loan over the selected tenure; renting means investing the avoided down payment plus EMI and maintenance saved after paying rent.
A4: MODEL INPUTS | D4: DECISION SUMMARY | G4: HOW TO READ THE RESULT | M4: RETURN SENSITIVITY
A5: Property Price (₹) | B5: 10000000 | D5: Monthly EMI | E5: =-PMT($B$7/1200,$B$8*12,$B$6) -> 60419.49 | G5: ="1. After "&TEXT($B$8,"0")&" years, buying creates real net wealth of ₹"&TEXT($E$9,"##,##,##0")&" versus ₹"&TEXT($E$10,"##,##,##0")&" from renting and investing." -> 1. After 20 years, buying creates real net wealth of ₹1,87,44,336 versus ₹1,26,30,239 from renting and investing. | M5: Return | N5: Leader | O5: Lead (Real)
A6: Loan Amount (₹) | B6: 7500000 | D6: First-Year Maintenance | E6: =$B$5*$B$9/100 -> 100000 | G6: ="2. "&IF($E$11>=0,"Buying leads by ₹","Renting and investing leads by ₹")&TEXT(ABS($E$11),"##,##,##0")&" in today’s rupees under the selected assumptions." -> 2. Buying leads by ₹61,14,097 in today’s rupees under the selected assumptions. | M6: 8 | N6: =IF('Rent Buy Sensitivity'!L21>=0,"Buy","Rent + Invest") -> Buy | O6: =ABS('Rent Buy Sensitivity'!L21) -> 13253943
A7: Loan Interest (% p.a.) | B7: ='Common Assumptions'!$B$7 -> 7.5 | D7: Buyer Total Cash Outlay | E7: =$B$5-$B$6+$E$5*$B$8*12+$E$6*$B$8 -> 19000677 | G7: ="3. The renter starts by investing the avoided down payment of ₹"&TEXT($B$5-$B$6,"##,##,##0")&" and then invests EMI plus maintenance less rent each month." -> 3. The renter starts by investing the avoided down payment of ₹25,00,000 and then invests EMI plus maintenance less rent each month. | M7: 10 | N7: =IF('Rent Buy Sensitivity'!L41>=0,"Buy","Rent + Invest") -> Buy | O7: =ABS('Rent Buy Sensitivity'!L41) -> 10347581
A8: Tenure (years) | B8: 20 | D8: Total Rent Paid | E8: =$B$13*12*IF($B$14=0,$B$8,((1+$B$14/100)^$B$8-1)/($B$14/100)) -> 17182500 | G8: ="4. Starting rent is ₹"&TEXT($B$13,"##,##,##0")&" per month, rising "&TEXT($B$14/100,"0.0%")&" yearly; investment returns are assumed at "&TEXT($B$12/100,"0.0%")&" nominally." -> 4. Starting rent is ₹25,000 per month, rising 10.0% yearly; investment returns are assumed at 12.0% nominally. | M8: 12 | N8: =IF('Rent Buy Sensitivity'!L61>=0,"Buy","Rent + Invest") -> Buy | O8: =ABS('Rent Buy Sensitivity'!L61) -> 6114096.8
A9: Maintenance (% p.a.) | B9: ='Common Assumptions'!$B$9 -> 1 | D9: Buy Net Wealth (Real) | E9: {=INDEX($H$21:$H$40,$B$8)} -> 18744336 | M9: 14 | N9: =IF('Rent Buy Sensitivity'!L81>=0,"Buy","Rent + Invest") -> Rent + Invest | O9: =ABS('Rent Buy Sensitivity'!L81) -> 47883.548
A10: Property Appreciation (% p.a.) | B10: ='Common Assumptions'!$B$8 -> 10 | D10: Rent + Invest Wealth (Real) | E10: {=INDEX($K$21:$K$40,$B$8)} -> 12630239 | G10: KEY ASSUMPTIONS & LIMITATIONS | M10: 16 | N10: =IF('Rent Buy Sensitivity'!L101>=0,"Buy","Rent + Invest") -> Rent + Invest | O10: =ABS('Rent Buy Sensitivity'!L101) -> 9013194.6
A11: Inflation (% p.a.) | B11: ='Common Assumptions'!$B$5 -> 6 | D11: Buy Advantage / (Rent Advantage) | E11: =E9-E10 -> 6114096.8 | G11: 1. Buyer wealth equals property value less outstanding loan; both are inflation-adjusted for the real comparison.
A12: Illustrative Investment Return (% p.a.) | B12: ='Common Assumptions'!$B$6 -> 12 | D12: Current Decision | E12: =IF(E11>=0,"BUY LEADS","RENT + INVEST LEADS") -> BUY LEADS | G12: 2. The buyer pays EMI and flat annual maintenance. The renter invests the monthly difference; if rent exceeds ownership cost, the model treats the difference as a portfolio withdrawal. | M12: Illustrative scenarios, not forecasts or guarantees. All other inputs remain unchanged.
A13: Starting Monthly Rent (₹) | B13: 25000 | G13: 3. Renter tax assumes a full year-end redemption and qualifying Section 112A LTCG above the exemption. Recent SIP instalments, cess, surcharge, and tax harvesting are excluded.
A14: Annual Rent Increase (%) | B14: ='Common Assumptions'!$B$14 -> 10 | G14: 4. Stamp duty, registration, property tax, insurance, loan tax benefits, rent deposits, moving costs, investment fees, and liquidity or risk differences are excluded. Selling cost and sale-gain tax use the shared illustrative assumptions.
A15: LTCG Tax Rate (%) | B15: ='Common Assumptions'!$B$12 -> 12.5 | G15: 5. Returns, appreciation, inflation, rent escalation, and interest rates are constant assumptions—not forecasts or guarantees.
A16: LTCG Exemption (₹) | B16: ='Common Assumptions'!$B$13 -> 125000 | G16: 6. Net contributions after any modeled withdrawals are used as a simplified tax cost basis; actual tax-lot calculations may differ.
A17: Loan-to-Value Ratio | B17: =$B$6/$B$5 -> 0.75 | D17: LTV Check | E17: =IF(OR('Common Assumptions'!$B$23="",'Common Assumptions'!$B$24="",'Common Assumptions'!$B$25="",'Common Assumptions'!$B$26="",'Common Assumptions'!$B$27=""),"",IF(B17>IF($B$6<='Common Assumptions'!$B$23,'Common Assumptions'!$B$25/100,IF($B$6<='Common Assumptions'!$B$24,'Common Assumptions'!$B$26/100,'Common Assumptions'!$B$27/100)),"Above regulatory LTV limit for this loan size: verify with your lender","Within configured LTV limit")) -> Within configured LTV limit
A19: YEARLY RENT VS BUY WEALTH SCHEDULE
A20: Year | B20: Annual Rent | C20: Monthly Invest Difference | D20: Renter Net Contributions | E20: Property Value | F20: Loan Balance | G20: Buy Net Wealth | H20: Buy Net Wealth (Real) | I20: Renter Portfolio | J20: Estimated Tax | K20: Renter Post-Tax Wealth (Real)
A21: =1 -> 1 | B21: =$B$13*12*(1+$B$14/100)^(A21-1) -> 300000 | C21: =$E$5+$E$6/12-$B$13*(1+$B$14/100)^(A21-1) -> 43752.823 | D21: =$B$5-$B$6+C21*12 -> 3025033.9 | E21: =$B$5*(1+$B$10/100)^A21 -> 11000000 | F21: =IF(A21>=$B$8,0,MAX(0,-FV($B$7/1200,A21*12,-$E$5,$B$6))) -> 7331761 | G21: =E21-E21*'Common Assumptions'!$B$29/100-MAX(0,E21-$B$5-E21*'Common Assumptions'!$B$29/100)*'Common Assumptions'!$B$28/100-F21 -> 3543239 | H21: =G21/(1+$B$11/100)^A21 -> 3342678.3 | I21: =($B$5-$B$6)*(1+$B$12/1200)^12+FV($B$12/1200,12,-C21,0,0) -> 3371957.9 | J21: =MAX(0,I21-D21-$B$16)*$B$15/100 -> 27740.501 | K21: =(I21-J21)/(1+$B$11/100)^A21 -> 3154922.1
A22: =A21+1 -> 2 | B22: =$B$13*12*(1+$B$14/100)^(A22-1) -> 330000 | C22: =$E$5+$E$6/12-$B$13*(1+$B$14/100)^(A22-1) -> 41252.823 | D22: =D21+C22*12 -> 3520067.7 | E22: =$B$5*(1+$B$10/100)^A22 -> 12100000 | F22: =IF(A22>=$B$8,0,MAX(0,-FV($B$7/1200,A22*12,-$E$5,$B$6))) -> 7150461.1 | G22: =E22-E22*'Common Assumptions'!$B$29/100-MAX(0,E22-$B$5-E22*'Common Assumptions'!$B$29/100)*'Common Assumptions'!$B$28/100-F22 -> 4687038.9 | H22: =G22/(1+$B$11/100)^A22 -> 4171447.9 | I22: =I21*(1+$B$12/1200)^12+FV($B$12/1200,12,-C22,0,0) -> 4322795.6 | J22: =MAX(0,I22-D22-$B$16)*$B$15/100 -> 84715.981 | K22: =(I22-J22)/(1+$B$11/100)^A22 -> 3771875.8
A23: =A22+1 -> 3 | B23: =$B$13*12*(1+$B$14/100)^(A23-1) -> 363000 | C23: =$E$5+$E$6/12-$B$13*(1+$B$14/100)^(A23-1) -> 38502.823 | D23: =D22+C23*12 -> 3982101.6 | E23: =$B$5*(1+$B$10/100)^A23 -> 13310000 | F23: =IF(A23>=$B$8,0,MAX(0,-FV($B$7/1200,A23*12,-$E$5,$B$6))) -> 6955086.5 | G23: =E23-E23*'Common Assumptions'!$B$29/100-MAX(0,E23-$B$5-E23*'Common Assumptions'!$B$29/100)*'Common Assumptions'!$B$28/100-F23 -> 5941163.5 | H23: =G23/(1+$B$11/100)^A23 -> 4988315.5 | I23: =I22*(1+$B$12/1200)^12+FV($B$12/1200,12,-C23,0,0) -> 5359346.4 | J23: =MAX(0,I23-D23-$B$16)*$B$15/100 -> 156530.6 | K23: =(I23-J23)/(1+$B$11/100)^A23 -> 4368384.5
A24: =A23+1 -> 4 | B24: =$B$13*12*(1+$B$14/100)^(A24-1) -> 399300 | C24: =$E$5+$E$6/12-$B$13*(1+$B$14/100)^(A24-1) -> 35477.823 | D24: =D23+C24*12 -> 4407835.5 | E24: =$B$5*(1+$B$10/100)^A24 -> 14641000 | F24: =IF(A24>=$B$8,0,MAX(0,-FV($B$7/1200,A24*12,-$E$5,$B$6))) -> 6744544.4 | G24: =E24-E24*'Common Assumptions'!$B$29/100-MAX(0,E24-$B$5-E24*'Common Assumptions'!$B$29/100)*'Common Assumptions'!$B$28/100-F24 -> 7316330.6 | H24: =G24/(1+$B$11/100)^A24 -> 5795219.1 | I24: =I23*(1+$B$12/1200)^12+FV($B$12/1200,12,-C24,0,0) -> 6488993.3 | J24: =MAX(0,I24-D24-$B$16)*$B$15/100 -> 244519.73 | K24: =(I24-J24)/(1+$B$11/100)^A24 -> 4946208
A25: =A24+1 -> 5 | B25: =$B$13*12*(1+$B$14/100)^(A25-1) -> 439230 | C25: =$E$5+$E$6/12-$B$13*(1+$B$14/100)^(A25-1) -> 32150.323 | D25: =D24+C25*12 -> 4793639.4 | E25: =$B$5*(1+$B$10/100)^A25 -> 16105100 | F25: =IF(A25>=$B$8,0,MAX(0,-FV($B$7/1200,A25*12,-$E$5,$B$6))) -> 6517657.4 | G25: =E25-E25*'Common Assumptions'!$B$29/100-MAX(0,E25-$B$5-E25*'Common Assumptions'!$B$29/100)*'Common Assumptions'!$B$28/100-F25 -> 8824305.1 | H25: =G25/(1+$B$11/100)^A25 -> 6594034.1 | I25: =I24*(1+$B$12/1200)^12+FV($B$12/1200,12,-C25,0,0) -> 7719706.6 | J25: =MAX(0,I25-D25-$B$16)*$B$15/100 -> 350133.41 | K25: =(I25-J25)/(1+$B$11/100)^A25 -> 5506973.8
A26: =A25+1 -> 6 | B26: =$B$13*12*(1+$B$14/100)^(A26-1) -> 483153 | C26: =$E$5+$E$6/12-$B$13*(1+$B$14/100)^(A26-1) -> 28490.073 | D26: =D25+C26*12 -> 5135520.2 | E26: =$B$5*(1+$B$10/100)^A26 -> 17715610 | F26: =IF(A26>=$B$8,0,MAX(0,-FV($B$7/1200,A26*12,-$E$5,$B$6))) -> 6273156.5 | G26: =E26-E26*'Common Assumptions'!$B$29/100-MAX(0,E26-$B$5-E26*'Common Assumptions'!$B$29/100)*'Common Assumptions'!$B$28/100-F26 -> 10478002 | H26: =G26/(1+$B$11/100)^A26 -> 7386578.1 | I26: =I25*(1+$B$12/1200)^12+FV($B$12/1200,12,-C26,0,0) -> 9060084.1 | J26: =MAX(0,I26-D26-$B$16)*$B$15/100 -> 474945.48 | K26: =(I26-J26)/(1+$B$11/100)^A26 -> 6052184
A27: =A26+1 -> 7 | B27: =$B$13*12*(1+$B$14/100)^(A27-1) -> 531468.3 | C27: =$E$5+$E$6/12-$B$13*(1+$B$14/100)^(A27-1) -> 24463.798 | D27: =D26+C27*12 -> 5429085.8 | E27: =$B$5*(1+$B$10/100)^A27 -> 19487171 | F27: =IF(A27>=$B$8,0,MAX(0,-FV($B$7/1200,A27*12,-$E$5,$B$6))) -> 6009674.5 | G27: =E27-E27*'Common Assumptions'!$B$29/100-MAX(0,E27-$B$5-E27*'Common Assumptions'!$B$29/100)*'Common Assumptions'!$B$28/100-F27 -> 12291600 | H27: =G27/(1+$B$11/100)^A27 -> 8174616.1 | I27: =I26*(1+$B$12/1200)^12+FV($B$12/1200,12,-C27,0,0) -> 10519392 | J27: =MAX(0,I27-D27-$B$16)*$B$15/100 -> 620663.24 | K27: =(I27-J27)/(1+$B$11/100)^A27 -> 6583219.8
A28: =A27+1 -> 8 | B28: =$B$13*12*(1+$B$14/100)^(A28-1) -> 584615.13 | C28: =$E$5+$E$6/12-$B$13*(1+$B$14/100)^(A28-1) -> 20034.895 | D28: =D27+C28*12 -> 5669504.6 | E28: =$B$5*(1+$B$10/100)^A28 -> 21435888 | F28: =IF(A28>=$B$8,0,MAX(0,-FV($B$7/1200,A28*12,-$E$5,$B$6))) -> 5725737.6 | G28: =E28-E28*'Common Assumptions'!$B$29/100-MAX(0,E28-$B$5-E28*'Common Assumptions'!$B$29/100)*'Common Assumptions'!$B$28/100-F28 -> 14280664 | H28: =G28/(1+$B$11/100)^A28 -> 8959865.6 | I28: =I27*(1+$B$12/1200)^12+FV($B$12/1200,12,-C28,0,0) -> 12107607 | J28: =MAX(0,I28-D28-$B$16)*$B$15/100 -> 789137.75 | K28: =(I28-J28)/(1+$B$11/100)^A28 -> 7101347.3
A29: =A28+1 -> 9 | B29: =$B$13*12*(1+$B$14/100)^(A29-1) -> 643076.64 | C29: =$E$5+$E$6/12-$B$13*(1+$B$14/100)^(A29-1) -> 15163.103 | D29: =D28+C29*12 -> 5851461.8 | E29: =$B$5*(1+$B$10/100)^A29 -> 23579477 | F29: =IF(A29>=$B$8,0,MAX(0,-FV($B$7/1200,A29*12,-$E$5,$B$6))) -> 5419758 | G29: =E29-E29*'Common Assumptions'!$B$29/100-MAX(0,E29-$B$5-E29*'Common Assumptions'!$B$29/100)*'Common Assumptions'!$B$28/100-F29 -> 16462284 | H29: =G29/(1+$B$11/100)^A29 -> 9744000.8 | I29: =I28*(1+$B$12/1200)^12+FV($B$12/1200,12,-C29,0,0) -> 13835460 | J29: =MAX(0,I29-D29-$B$16)*$B$15/100 -> 982374.8 | K29: =(I29-J29)/(1+$B$11/100)^A29 -> 7607721.5
A30: =A29+1 -> 10 | B30: =$B$13*12*(1+$B$14/100)^(A30-1) -> 707384.31 | C30: =$E$5+$E$6/12-$B$13*(1+$B$14/100)^(A30-1) -> 9804.1306 | D30: =D29+C30*12 -> 5969111.4 | E30: =$B$5*(1+$B$10/100)^A30 -> 25937425 | F30: =IF(A30>=$B$8,0,MAX(0,-FV($B$7/1200,A30*12,-$E$5,$B$6))) -> 5090024.3 | G30: =E30-E30*'Common Assumptions'!$B$29/100-MAX(0,E30-$B$5-E30*'Common Assumptions'!$B$29/100)*'Common Assumptions'!$B$28/100-F30 -> 18855222 | H30: =G30/(1+$B$11/100)^A30 -> 10528658 | I30: =I29*(1+$B$12/1200)^12+FV($B$12/1200,12,-C30,0,0) -> 15714484 | J30: =MAX(0,I30-D30-$B$16)*$B$15/100 -> 1202546.6 | K30: =(I30-J30)/(1+$B$11/100)^A30 -> 8103389.9
A31: =A30+1 -> 11 | B31: =$B$13*12*(1+$B$14/100)^(A31-1) -> 778122.74 | C31: =$E$5+$E$6/12-$B$13*(1+$B$14/100)^(A31-1) -> 3909.2613 | D31: =D30+C31*12 -> 6016022.5 | E31: =$B$5*(1+$B$10/100)^A31 -> 28531167 | F31: =IF(A31>=$B$8,0,MAX(0,-FV($B$7/1200,A31*12,-$E$5,$B$6))) -> 4734692.6 | G31: =E31-E31*'Common Assumptions'!$B$29/100-MAX(0,E31-$B$5-E31*'Common Assumptions'!$B$29/100)*'Common Assumptions'!$B$28/100-F31 -> 21480079 | H31: =G31/(1+$B$11/100)^A31 -> 11315437 | I31: =I30*(1+$B$12/1200)^12+FV($B$12/1200,12,-C31,0,0) -> 17757053 | J31: =MAX(0,I31-D31-$B$16)*$B$15/100 -> 1452003.8 | K31: =(I31-J31)/(1+$B$11/100)^A31 -> 8589296.5
A32: =A31+1 -> 12 | B32: =$B$13*12*(1+$B$14/100)^(A32-1) -> 855935.01 | C32: =$E$5+$E$6/12-$B$13*(1+$B$14/100)^(A32-1) -> -2575.0948 | D32: =D31+C32*12 -> 5985121.4 | E32: =$B$5*(1+$B$10/100)^A32 -> 31384284 | F32: =IF(A32>=$B$8,0,MAX(0,-FV($B$7/1200,A32*12,-$E$5,$B$6))) -> 4351775.6 | G32: =E32-E32*'Common Assumptions'!$B$29/100-MAX(0,E32-$B$5-E32*'Common Assumptions'!$B$29/100)*'Common Assumptions'!$B$28/100-F32 -> 24359473 | H32: =G32/(1+$B$11/100)^A32 -> 12105912 | I32: =I31*(1+$B$12/1200)^12+FV($B$12/1200,12,-C32,0,0) -> 19976433 | J32: =MAX(0,I32-D32-$B$16)*$B$15/100 -> 1733289 | K32: =(I32-J32)/(1+$B$11/100)^A32 -> 9066283.7
A33: =A32+1 -> 13 | B33: =$B$13*12*(1+$B$14/100)^(A33-1) -> 941528.51 | C33: =$E$5+$E$6/12-$B$13*(1+$B$14/100)^(A33-1) -> -9707.8866 | D33: =D32+C33*12 -> 5868626.7 | E33: =$B$5*(1+$B$10/100)^A33 -> 34522712 | F33: =IF(A33>=$B$8,0,MAX(0,-FV($B$7/1200,A33*12,-$E$5,$B$6))) -> 3939131.8 | G33: =E33-E33*'Common Assumptions'!$B$29/100-MAX(0,E33-$B$5-E33*'Common Assumptions'!$B$29/100)*'Common Assumptions'!$B$28/100-F33 -> 27518241 | H33: =G33/(1+$B$11/100)^A33 -> 12901625 | I33: =I32*(1+$B$12/1200)^12+FV($B$12/1200,12,-C33,0,0) -> 22386824 | J33: =MAX(0,I33-D33-$B$16)*$B$15/100 -> 2049149.7 | K33: =(I33-J33)/(1+$B$11/100)^A33 -> 9535095.5
... A40: =A39+1 -> 20 | B40: =$B$13*12*(1+$B$14/100)^(A40-1) -> 1834772.7 | C40: =$E$5+$E$6/12-$B$13*(1+$B$14/100)^(A40-1) -> -84144.903 | D40: =D39+C40*12 -> 1818177.6 | E40: =$B$5*(1+$B$10/100)^A40 -> 67274999 | F40: =IF(A40>=$B$8,0,MAX(0,-FV($B$7/1200,A40*12,-$E$5,$B$6))) -> 0 | G40: =E40-E40*'Common Assumptions'!$B$29/100-MAX(0,E40-$B$5-E40*'Common Assumptions'!$B$29/100)*'Common Assumptions'!$B$28/100-F40 -> 60115625 | H40: =G40/(1+$B$11/100)^A40 -> 18744336 | I40: =I39*(1+$B$12/1200)^12+FV($B$12/1200,12,-C40,0,0) -> 46015989 | J40: =MAX(0,I40-D40-$B$16)*$B$15/100 -> 5509101.5 | K40: =(I40-J40)/(1+$B$11/100)^A40 -> 12630239

Sheet Home Loan Analysis
A1: Property Price (₹) | B1: 10000000 | C1: Purchase price used as the starting value of the property.
A2: Loan Amount (₹) | B2: 7500000 | C2: Principal financed through the home loan.
A3: Loan Interest (% per year) | B3: ='Common Assumptions'!$B$7 -> 7.5 | C3: Annual nominal loan rate; the EMI calculation uses a monthly rate.
A4: Tenure (years) | B4: 20 | C4: Loan and investment comparison period in years.
A5: Maintenance (% per year) | B5: ='Common Assumptions'!$B$9 -> 1 | C5: Annual maintenance assumption; this model keeps the first-year rupee amount flat.
A6: Property Appreciation (% per year) | B6: ='Common Assumptions'!$B$8 -> 10 | C6: Expected annual compound growth rate of the property value.
A7: Inflation (% per year) | B7: ='Common Assumptions'!$B$5 -> 6 | C7: Annual rate used to convert future amounts into today’s purchasing power.
A8: SIP Return (% per year) | B8: ='Common Assumptions'!$B$6 -> 12 | C8: Expected annual SIP return; monthly contributions are compounded monthly.
A10: EMI & PROPERTY SUMMARY
A11: Down Payment | B11: =B1-B2 -> 2500000 | C11: Property price less the loan amount; also used as the SIP lump sum.
A12: Monthly EMI | B12: =PMT(B3/1200,B4*12,-B2) -> 60419.49 | C12: Fixed monthly loan payment of principal and interest.
A13: Total EMI Paid | B13: =B12*B4*12 -> 14500677 | C13: Monthly EMI multiplied by the full number of loan months.
A14: Net Interest Paid | B14: =B13-B2 -> 7000677.5 | C14: Total EMI paid less the original loan principal.
A15: Loan-to-Value Ratio | B15: =B2/B1 -> 0.75 | C15: =IF(OR('Common Assumptions'!$B$23="",'Common Assumptions'!$B$24="",'Common Assumptions'!$B$25="",'Common Assumptions'!$B$26="",'Common Assumptions'!$B$27=""),"",IF(B15>IF($B$2<='Common Assumptions'!$B$23,'Common Assumptions'!$B$25/100,IF($B$2<='Common Assumptions'!$B$24,'Common Assumptions'!$B$26/100,'Common Assumptions'!$B$27/100)),"Above regulatory LTV limit for this loan size: verify with your lender","Within configured LTV limit")) -> Within configured LTV limit
A16: First-Year Maintenance | B16: =B1*B5/100 -> 100000 | C16: Property price multiplied by the annual maintenance rate.
A17: Total Maintenance (20 Years) | B17: =B16*B4 -> 2000000 | C17: First-year maintenance multiplied by tenure; no annual escalation is modeled.
A18: Property Future Value (Gross Nominal) | B18: =B1*(1+B6/100)^B4 -> 67274999 | C18: Estimated property value at the end of the tenure before inflation adjustment.
A19: Property Future Value (Gross Real) | B19: =B18/(1+B7/100)^B4 -> 20976663 | C19: Gross future property value expressed in today’s rupees.
A20: Net Property Gain (After Maintenance & Interest) | B20: =B18-B1-B17-B14-(B18*'Common Assumptions'!$B$29/100)-(MAX(0,B18-B1-(B18*'Common Assumptions'!$B$29/100)) * 'Common Assumptions'!$B$28/100) -> 41114947 | C20: Nominal property sale value less purchase price, maintenance, loan interest, modeled selling cost, and modeled tax on sale gain.
A21: Real Property Gain (After Financing & Maintenance) | B21: =(B18-(B18*'Common Assumptions'!$B$29/100)-(MAX(0,B18-B1-(B18*'Common Assumptions'!$B$29/100)) * 'Common Assumptions'!$B$28/100))/(1+B7/100)^B4-B11-B12*12*IF(B7=0,B4,(1-(1+B7/100)^(-B4))/(B7/100))-IF(B7=0,B16*B4,B16*(1-(1+B7/100)^(-B4))/(B7/100)) -> 6781262.4 | C21: Net property sale proceeds in today's rupees less the down payment and present values of monthly EMIs and maintenance.
A23: SIP INVESTMENT SUMMARY
A24: Lump Sum Investment | B24: =B11 -> 2500000 | C24: One-time investment equal to the house down payment.
A25: Monthly SIP | B25: =B12 -> 60419.49 | C25: Monthly investment equal to the home-loan EMI.
A26: Total Amount Invested | B26: =B24+B25*B4*12 -> 17000677 | C26: Lump sum plus all monthly SIP contributions; returns are excluded.
A27: SIP Future Value (Nominal) | B27: =B24*(1+B8/1200)^(B4*12)+FV(B8/1200,B4*12,-B25,0,0) -> 87001688 | C27: Future value of the lump sum and monthly SIP contributions using monthly compounding before tax and inflation.
A28: Inflation-Adjusted SIP Value | B28: =B27/(1+B7/100)^B4 -> 27127538 | C28: Nominal SIP future value expressed in today’s rupees.
A29: Investment Gain (Nominal) | B29: =B27-B26 -> 70001011 | C29: SIP future value less total contributions, before tax.
A30: ="LTCG Tax ("&TEXT('Common Assumptions'!$B$12/100,"0.0%")&", ₹"&TEXT('Common Assumptions'!$B$13/100000,"0.00")&"L Exemption)" -> LTCG Tax (12.5%, ₹1.25L Exemption) | B30: =MAX(0,B29-'Common Assumptions'!$B$13)*'Common Assumptions'!$B$12/100 -> 8734501.4 | C30: ="Tax on the nominal investment gain above ₹"&TEXT('Common Assumptions'!$B$13,"##,##,##0")&", using the shared illustrative LTCG rate." -> Tax on the nominal investment gain above ₹1,25,000, using the shared illustrative LTCG rate.
A31: Post-Tax Investment Gain (Nominal) | B31: =B29-B30 -> 61266509 | C31: Nominal investment gain remaining after deducting the modeled LTCG tax.
A32: Post-Tax Future Value (Nominal) | B32: =B26+B31 -> 78267187 | C32: Total amount invested plus the post-tax nominal investment gain; this is the post-tax corpus after 20 years.
A33: Post-Tax Future Value (Real) | B33: =B32/(1+B7/100)^B4 -> 24404079 | C33: Post-tax future value after adjusting the full corpus for inflation; this is the value after 20 years in today’s rupees.
A34: Real Gain After LTCG & Inflation | B34: =B33-B35 -> 13587997 | C34: Inflation-adjusted post-tax future value less the present value of all SIP contributions, discounted consistently with the house-side cost methodology.
A35: Present Value of SIP Contributions (Real) | B35: =B24+B25*12*IF(B7=0,B4,(1-(1+B7/100)^(-B4))/(B7/100)) -> 10816081 | C35: Lump sum paid today plus each monthly SIP contribution discounted to present value using the same year-by-year inflation convention applied to home-loan interest.
A36: HOUSE VS SIP — DECISION ANALYSIS
A37: Comparison uses the assumptions above over the same 20-year horizon.
A39: Metric | B39: House | C39: SIP
A40: Total modeled cash outlay | B40: =B11+B13+B17 -> 19000677 | C40: =B26 -> 17000677
A41: Nominal future value | B41: =B18-(B18*'Common Assumptions'!$B$29/100)-(MAX(0,B18-B1-(B18*'Common Assumptions'!$B$29/100)) * 'Common Assumptions'!$B$28/100) -> 60115625 | C41: =B32 -> 78267187
A42: Inflation-adjusted future value | B42: =B41/(1+B7/100)^B4 -> 18744336 | C42: =B33 -> 24404079
A43: Real gain after modeled costs / tax | B43: =B21 -> 6781262.4 | C43: =B34 -> 13587997
A44: House advantage / (SIP advantage) | B44: =B43-C43 -> -6806735.1 | C44: =IF(B44>=0,"House leads","SIP leads") -> SIP leads
A45: =IF(B44>=0,"CONCLUSION: Buying the house is better under the current assumptions by ₹"&TEXT(ABS(B44),"##,##,##0")&" of real gain.","CONCLUSION: SIP investing is better under the current assumptions by ₹"&TEXT(ABS(B44),"##,##,##0")&" of real gain.") -> CONCLUSION: SIP investing is better under the current assumptions by ₹68,06,735 of real gain.
A46: Meaning: Nominal future value shows the property after modeled selling cost and tax on sale gain and SIP after modeled LTCG tax. Inflation-adjusted future value expresses both post-cost, post-tax values in today's rupees.
A47: ="1. Real outcome: House real gain is ₹"&TEXT(B43,"##,##,##0")&" versus SIP real gain of ₹"&TEXT(C43,"##,##,##0")&" after modeled costs and tax." -> 1. Real outcome: House real gain is ₹67,81,262 versus SIP real gain of ₹1,35,87,997 after modeled costs and tax.
A48: ="2. Portfolio size: SIP reaches "&_xlfn.UNICHAR(8377)&TEXT(C41,"##,##,##0")&" nominally versus the property's "&_xlfn.UNICHAR(8377)&TEXT(B41,"##,##,##0")&", with both values after modeled costs and tax." -> 2. Portfolio size: SIP reaches ₹7,82,67,187 nominally versus the property's ₹6,01,15,625, with both values after modeled costs and tax.
A49: ="3. Cash commitment: The house requires ₹"&TEXT(ABS(B40-C40),"##,##,##0")&IF(B40>=C40," more"," less")&" modeled cash outlay, mainly because maintenance is not invested in the SIP scenario." -> 3. Cash commitment: The house requires ₹20,00,000 more modeled cash outlay, mainly because maintenance is not invested in the SIP scenario.
A51: Decision caveat: This model compares taking a loan to buy an additional property against investing the same EMI and down payment amount in a SIP, assuming you already have a home to live in — it is not a rent-vs-buy comparison for your primary residence. It assumes the SIP is an equity-oriented investment eligible for Section 112A and is redeemed once at the end of the horizon. Property selling cost and sale-gain tax use the shared illustrative assumptions. It excludes rental income the second property might generate, rent increases, moving costs, stamp duty and registration, property taxes, insurance, home-loan tax benefits, SIP expense ratios, surcharge/cess, liquidity, and differences in risk. Include these before making a final personal decision.

Sheet EMI Calculator
A1: EMI CALCULATOR & YEARLY REPAYMENT SCHEDULE
A2: Edit the loan inputs below; the summary and annual amortization schedule recalculate automatically.
A4: LOAN INPUTS | D4: LOAN SUMMARY
A5: Loan Amount (₹) | B5: 2000000 | D5: Monthly EMI | E5: =-PMT($B$6/1200,$B$7*12,$B$5) -> 16111.864
A6: Interest Rate (% per year) | B6: ='Common Assumptions'!$B$7 -> 7.5 | D6: Total Payment | E6: =E5*$B$7*12 -> 3866847.3
A7: Tenure (years) | B7: 20 | D7: Total Interest | E7: =E6-$B$5 -> 1866847.3
D8: Total Principal | E8: =$B$5 -> 2000000
A10: YEARLY PAYMENT SCHEDULE
A11: Year | B11: Opening Balance | C11: EMI Paid | D11: Principal Paid | E11: Interest Paid | F11: Closing Balance
A12: =1 -> 1 | B12: =$B$5 -> 2000000 | C12: =$E$5*12 -> 193342.37 | D12: =-CUMPRINC($B$6/1200,$B$7*12,$B$5,1,12,0) -> 44863.741 | E12: =-CUMIPMT($B$6/1200,$B$7*12,$B$5,1,12,0) -> 148478.63 | F12: =MAX(0,B12-D12) -> 1955136.3
A13: =A12+1 -> 2 | B13: =F12 -> 1955136.3 | C13: =$E$5*12 -> 193342.37 | D13: =-CUMPRINC($B$6/1200,$B$7*12,$B$5,(A13-1)*12+1,A13*12,0) -> 48346.629 | E13: =-CUMIPMT($B$6/1200,$B$7*12,$B$5,(A13-1)*12+1,A13*12,0) -> 144995.74 | F13: =MAX(0,B13-D13) -> 1906789.6
A14: =A13+1 -> 3 | B14: =F13 -> 1906789.6 | C14: =$E$5*12 -> 193342.37 | D14: =-CUMPRINC($B$6/1200,$B$7*12,$B$5,(A14-1)*12+1,A14*12,0) -> 52099.904 | E14: =-CUMIPMT($B$6/1200,$B$7*12,$B$5,(A14-1)*12+1,A14*12,0) -> 141242.46 | F14: =MAX(0,B14-D14) -> 1854689.7
A15: =A14+1 -> 4 | B15: =F14 -> 1854689.7 | C15: =$E$5*12 -> 193342.37 | D15: =-CUMPRINC($B$6/1200,$B$7*12,$B$5,(A15-1)*12+1,A15*12,0) -> 56144.555 | E15: =-CUMIPMT($B$6/1200,$B$7*12,$B$5,(A15-1)*12+1,A15*12,0) -> 137197.81 | F15: =MAX(0,B15-D15) -> 1798545.2
A16: =A15+1 -> 5 | B16: =F15 -> 1798545.2 | C16: =$E$5*12 -> 193342.37 | D16: =-CUMPRINC($B$6/1200,$B$7*12,$B$5,(A16-1)*12+1,A16*12,0) -> 60503.203 | E16: =-CUMIPMT($B$6/1200,$B$7*12,$B$5,(A16-1)*12+1,A16*12,0) -> 132839.16 | F16: =MAX(0,B16-D16) -> 1738042
A17: =A16+1 -> 6 | B17: =F16 -> 1738042 | C17: =$E$5*12 -> 193342.37 | D17: =-CUMPRINC($B$6/1200,$B$7*12,$B$5,(A17-1)*12+1,A17*12,0) -> 65200.223 | E17: =-CUMIPMT($B$6/1200,$B$7*12,$B$5,(A17-1)*12+1,A17*12,0) -> 128142.14 | F17: =MAX(0,B17-D17) -> 1672841.7
A18: =A17+1 -> 7 | B18: =F17 -> 1672841.7 | C18: =$E$5*12 -> 193342.37 | D18: =-CUMPRINC($B$6/1200,$B$7*12,$B$5,(A18-1)*12+1,A18*12,0) -> 70261.886 | E18: =-CUMIPMT($B$6/1200,$B$7*12,$B$5,(A18-1)*12+1,A18*12,0) -> 123080.48 | F18: =MAX(0,B18-D18) -> 1602579.9
A19: =A18+1 -> 8 | B19: =F18 -> 1602579.9 | C19: =$E$5*12 -> 193342.37 | D19: =-CUMPRINC($B$6/1200,$B$7*12,$B$5,(A19-1)*12+1,A19*12,0) -> 75716.499 | E19: =-CUMIPMT($B$6/1200,$B$7*12,$B$5,(A19-1)*12+1,A19*12,0) -> 117625.87 | F19: =MAX(0,B19-D19) -> 1526863.4
A20: =A19+1 -> 9 | B20: =F19 -> 1526863.4 | C20: =$E$5*12 -> 193342.37 | D20: =-CUMPRINC($B$6/1200,$B$7*12,$B$5,(A20-1)*12+1,A20*12,0) -> 81594.568 | E20: =-CUMIPMT($B$6/1200,$B$7*12,$B$5,(A20-1)*12+1,A20*12,0) -> 111747.8 | F20: =MAX(0,B20-D20) -> 1445268.8
A21: =A20+1 -> 10 | B21: =F20 -> 1445268.8 | C21: =$E$5*12 -> 193342.37 | D21: =-CUMPRINC($B$6/1200,$B$7*12,$B$5,(A21-1)*12+1,A21*12,0) -> 87928.966 | E21: =-CUMIPMT($B$6/1200,$B$7*12,$B$5,(A21-1)*12+1,A21*12,0) -> 105413.4 | F21: =MAX(0,B21-D21) -> 1357339.8
A22: =A21+1 -> 11 | B22: =F21 -> 1357339.8 | C22: =$E$5*12 -> 193342.37 | D22: =-CUMPRINC($B$6/1200,$B$7*12,$B$5,(A22-1)*12+1,A22*12,0) -> 94755.12 | E22: =-CUMIPMT($B$6/1200,$B$7*12,$B$5,(A22-1)*12+1,A22*12,0) -> 98587.246 | F22: =MAX(0,B22-D22) -> 1262584.7
A23: =A22+1 -> 12 | B23: =F22 -> 1262584.7 | C23: =$E$5*12 -> 193342.37 | D23: =-CUMPRINC($B$6/1200,$B$7*12,$B$5,(A23-1)*12+1,A23*12,0) -> 102111.21 | E23: =-CUMIPMT($B$6/1200,$B$7*12,$B$5,(A23-1)*12+1,A23*12,0) -> 91231.16 | F23: =MAX(0,B23-D23) -> 1160473.5
A24: =A23+1 -> 13 | B24: =F23 -> 1160473.5 | C24: =$E$5*12 -> 193342.37 | D24: =-CUMPRINC($B$6/1200,$B$7*12,$B$5,(A24-1)*12+1,A24*12,0) -> 110038.36 | E24: =-CUMIPMT($B$6/1200,$B$7*12,$B$5,(A24-1)*12+1,A24*12,0) -> 83304.002 | F24: =MAX(0,B24-D24) -> 1050435.1
... A31: =A30+1 -> 20 | B31: =F30 -> 185711.66 | C31: =$E$5*12 -> 193342.37 | D31: =-CUMPRINC($B$6/1200,$B$7*12,$B$5,(A31-1)*12+1,A31*12,0) -> 185711.66 | E31: =-CUMIPMT($B$6/1200,$B$7*12,$B$5,(A31-1)*12+1,A31*12,0) -> 7630.7069 | F31: =MAX(0,B31-D31) -> 0
A33: HOW TO READ THE RESULTS
A34: ="1. A loan of ₹"&TEXT($B$5,"##,##,##0")&" at "&TEXT($B$6/100,"0.00%")&" for "&TEXT($B$7,"0")&" years requires a monthly EMI of ₹"&TEXT($E$5,"##,##,##0")&"." -> 1. A loan of ₹20,00,000 at 7.50% for 20 years requires a monthly EMI of ₹16,112.
A35: ="2. Total repayment over "&TEXT($B$7,"0")&" years is ₹"&TEXT($E$6,"##,##,##0")&", consisting of ₹"&TEXT($E$8,"##,##,##0")&" principal and ₹"&TEXT($E$7,"##,##,##0")&" interest." -> 2. Total repayment over 20 years is ₹38,66,847, consisting of ₹20,00,000 principal and ₹18,66,847 interest.
A36: ="3. Interest represents "&TEXT($E$7/$E$6,"0.0%")&" of total repayments; the remaining "&TEXT($E$8/$E$6,"0.0%")&" repays principal." -> 3. Interest represents 48.3% of total repayments; the remaining 51.7% repays principal.
A37: ="4. In year 1, ₹"&TEXT($D$12,"##,##,##0")&" of payments reduces principal and ₹"&TEXT($E$12,"##,##,##0")&" pays interest; this mix shifts toward principal over time." -> 4. In year 1, ₹44,864 of payments reduces principal and ₹1,48,479 pays interest; this mix shifts toward principal over time.
A39: INPUT GUIDE
A40: Input | C40: How it affects the model | F40: Current value
A41: Loan amount | C41: Principal borrowed. A larger amount increases the EMI, total repayment, and total interest proportionally. | F41: =B5 -> 2000000
A42: Annual interest rate | C42: Nominal annual borrowing rate divided by 12 for the monthly EMI and amortization calculations. | F42: =B6 -> 7.5
A43: Tenure | C43: Repayment period in years. A longer tenure usually lowers EMI but increases total interest. | F43: =B7 -> 20
A45: OUTPUT & CALCULATION FLOW
A46: Output | C46: Meaning / calculation flow
A47: Monthly EMI | C47: Fixed monthly payment calculated using the loan amount, monthly interest rate, and total number of monthly payments.
A48: Total payment | C48: Monthly EMI × 12 × tenure. This is the total cash paid to the lender if the rate and schedule remain unchanged.
A49: Total interest | C49: Total payment less the original loan amount. It is the modeled cost of borrowing before fees, taxes, or benefits.
A50: Opening balance | C50: Outstanding principal at the beginning of each year.
A51: Principal paid | C51: The part of that year’s EMIs that reduces the outstanding loan balance.
A52: Interest paid | C52: The part of that year’s EMIs charged as borrowing cost; it generally declines as the balance falls.
A53: Closing balance | C53: Opening balance less principal paid. It becomes the next year’s opening balance and reaches zero at maturity.
A56: ASSUMPTIONS & LIMITATIONS
A57: 1. The interest rate is fixed for the full tenure and interest is calculated monthly on the reducing principal balance.
A58: 2. EMIs are paid at each month-end, on time, with no missed payments, prepayments, part-payments, moratorium, or refinancing.
A59: 3. The schedule excludes processing fees, insurance, legal charges, penalties, taxes, and other lender costs.
A60: 4. Home-loan tax deductions or subsidies are excluded; actual after-tax borrowing cost depends on eligibility and tax rules.
A61: 5. Values are rounded for display, so displayed yearly figures may differ slightly from exact underlying formulas.
A62: 6. This is an illustration of a standard amortizing loan; the lender’s actual schedule may differ because of payment dates, day-count conventions, or rate resets.

Sheet SIP Growth
A1: SIP GROWTH & YEARLY VALUE SCHEDULE
A2: Edit the assumptions below; the summary and yearly schedule recalculate automatically.
A4: INVESTMENT INPUTS | D4: INVESTMENT SUMMARY
A5: Lumpsum at start | B5: 0 | D5: Total Amount Invested | E5: =$B$5+$B$6*$B$8*12 -> 4800000
A6: Monthly SIP Amount (₹) | B6: 20000 | D6: Future Value (Nominal) | E6: =$B$5*(1+$B$7/1200)^($B$8*12)+FV($B$7/1200,$B$8*12,-$B$6,0,0) -> 19785107
A7: Expected Return (% per year) | B7: ='Common Assumptions'!$B$6 -> 12 | D7: Investment Gain (Nominal) | E7: =E6-E5 -> 14985107
A8: Tenure (years) | B8: 20 | D8: Estimated LTCG Tax | E8: =MAX(0,E7-$B$11)*$B$10/100 -> 1857513.4
A9: Inflation (% per year) | B9: ='Common Assumptions'!$B$5 -> 6 | D9: Post-Tax Value (Nominal) | E9: =E6-E8 -> 17927594
A10: LTCG Tax Rate (%) | B10: ='Common Assumptions'!$B$12 -> 12.5 | D10: Post-Tax Value (Real) | E10: =E9/(1+$B$9/100)^$B$8 -> 5589908.5
A11: LTCG Exemption (₹) | B11: ='Common Assumptions'!$B$13 -> 125000 | D11: Real Gain vs Contributions (contributions in today's rupees) | E11: =E10-($B$5+IF($B$9=0,$B$6*12*$B$8,$B$6*12*(1-(1+$B$9/100)^(-$B$8))/($B$9/100))) -> 2837127.4
A13: Tax assumption: each row estimates tax if the full portfolio were redeemed at that year-end and all gains qualified for Section 112A LTCG. It excludes cess, surcharge, expense ratios, and the short-term status of recent SIP instalments.
A15: YEARLY SIP GROWTH SCHEDULE
A16: Year | B16: Opening Value | C16: Annual SIP | D16: Total Invested | E16: Nominal Value | F16: Nominal Gain | G16: Estimated LTCG Tax | H16: Post-Tax Value | I16: Post-Tax Real Value
A17: =IF(ROW()-16<=$B$8,ROW()-16,"") -> 1 | B17: =IF($A17="","",$B$5) -> 0 | C17: =IF($A17="","",$B$6*12) -> 240000 | D17: =IF($A17="","",$B$5+C17) -> 240000 | E17: =IF($A17="","",$B$5*(1+$B$7/1200)^12+FV($B$7/1200,12,-$B$6,0,0)) -> 253650.06 | F17: =IF($A17="","",E17-D17) -> 13650.06 | G17: =IF($A17="","",MAX(0,F17-$B$11)*$B$10/100) -> 0 | H17: =IF($A17="","",E17-G17) -> 253650.06 | I17: =IF($A17="","",H17/(1+$B$9/100)^A17) -> 239292.51
A18: =IF(ROW()-16<=$B$8,ROW()-16,"") -> 2 | B18: =IF($A18="","",E17) -> 253650.06 | C18: =IF($A18="","",$B$6*12) -> 240000 | D18: =IF($A18="","",D17+C18) -> 480000 | E18: =IF($A18="","",E17*(1+$B$7/1200)^12+FV($B$7/1200,12,-$B$6,0,0)) -> 539469.3 | F18: =IF($A18="","",E18-D18) -> 59469.297 | G18: =IF($A18="","",MAX(0,F18-$B$11)*$B$10/100) -> 0 | H18: =IF($A18="","",E18-G18) -> 539469.3 | I18: =IF($A18="","",H18/(1+$B$9/100)^A18) -> 480125.75
A19: =IF(ROW()-16<=$B$8,ROW()-16,"") -> 3 | B19: =IF($A19="","",E18) -> 539469.3 | C19: =IF($A19="","",$B$6*12) -> 240000 | D19: =IF($A19="","",D18+C19) -> 720000 | E19: =IF($A19="","",E18*(1+$B$7/1200)^12+FV($B$7/1200,12,-$B$6,0,0)) -> 861537.57 | F19: =IF($A19="","",E19-D19) -> 141537.57 | G19: =IF($A19="","",MAX(0,F19-$B$11)*$B$10/100) -> 2067.1959 | H19: =IF($A19="","",E19-G19) -> 859470.37 | I19: =IF($A19="","",H19/(1+$B$9/100)^A19) -> 721627.9
A20: =IF(ROW()-16<=$B$8,ROW()-16,"") -> 4 | B20: =IF($A20="","",E19) -> 861537.57 | C20: =IF($A20="","",$B$6*12) -> 240000 | D20: =IF($A20="","",D19+C20) -> 960000 | E20: =IF($A20="","",E19*(1+$B$7/1200)^12+FV($B$7/1200,12,-$B$6,0,0)) -> 1224452.2 | F20: =IF($A20="","",E20-D20) -> 264452.16 | G20: =IF($A20="","",MAX(0,F20-$B$11)*$B$10/100) -> 17431.519 | H20: =IF($A20="","",E20-G20) -> 1207020.6 | I20: =IF($A20="","",H20/(1+$B$9/100)^A20) -> 956073.4
A21: =IF(ROW()-16<=$B$8,ROW()-16,"") -> 5 | B21: =IF($A21="","",E20) -> 1224452.2 | C21: =IF($A21="","",$B$6*12) -> 240000 | D21: =IF($A21="","",D20+C21) -> 1200000 | E21: =IF($A21="","",E20*(1+$B$7/1200)^12+FV($B$7/1200,12,-$B$6,0,0)) -> 1633393.4 | F21: =IF($A21="","",E21-D21) -> 433393.4 | G21: =IF($A21="","",MAX(0,F21-$B$11)*$B$10/100) -> 38549.175 | H21: =IF($A21="","",E21-G21) -> 1594844.2 | I21: =IF($A21="","",H21/(1+$B$9/100)^A21) -> 1191760.4
A22: =IF(ROW()-16<=$B$8,ROW()-16,"") -> 6 | B22: =IF($A22="","",E21) -> 1633393.4 | C22: =IF($A22="","",$B$6*12) -> 240000 | D22: =IF($A22="","",D21+C22) -> 1440000 | E22: =IF($A22="","",E21*(1+$B$7/1200)^12+FV($B$7/1200,12,-$B$6,0,0)) -> 2094198.6 | F22: =IF($A22="","",E22-D22) -> 654198.62 | G22: =IF($A22="","",MAX(0,F22-$B$11)*$B$10/100) -> 66149.828 | H22: =IF($A22="","",E22-G22) -> 2028048.8 | I22: =IF($A22="","",H22/(1+$B$9/100)^A22) -> 1429694.4
A23: =IF(ROW()-16<=$B$8,ROW()-16,"") -> 7 | B23: =IF($A23="","",E22) -> 2094198.6 | C23: =IF($A23="","",$B$6*12) -> 240000 | D23: =IF($A23="","",D22+C23) -> 1680000 | E23: =IF($A23="","",E22*(1+$B$7/1200)^12+FV($B$7/1200,12,-$B$6,0,0)) -> 2613445.5 | F23: =IF($A23="","",E23-D23) -> 933445.49 | G23: =IF($A23="","",MAX(0,F23-$B$11)*$B$10/100) -> 101055.69 | H23: =IF($A23="","",E23-G23) -> 2512389.8 | I23: =IF($A23="","",H23/(1+$B$9/100)^A23) -> 1670882.7
A24: =IF(ROW()-16<=$B$8,ROW()-16,"") -> 8 | B24: =IF($A24="","",E23) -> 2613445.5 | C24: =IF($A24="","",$B$6*12) -> 240000 | D24: =IF($A24="","",D23+C24) -> 1920000 | E24: =IF($A24="","",E23*(1+$B$7/1200)^12+FV($B$7/1200,12,-$B$6,0,0)) -> 3198545.9 | F24: =IF($A24="","",E24-D24) -> 1278545.9 | G24: =IF($A24="","",MAX(0,F24-$B$11)*$B$10/100) -> 144193.23 | H24: =IF($A24="","",E24-G24) -> 3054352.6 | I24: =IF($A24="","",H24/(1+$B$9/100)^A24) -> 1916338.6
A25: =IF(ROW()-16<=$B$8,ROW()-16,"") -> 9 | B25: =IF($A25="","",E24) -> 3198545.9 | C25: =IF($A25="","",$B$6*12) -> 240000 | D25: =IF($A25="","",D24+C25) -> 2160000 | E25: =IF($A25="","",E24*(1+$B$7/1200)^12+FV($B$7/1200,12,-$B$6,0,0)) -> 3857851.6 | F25: =IF($A25="","",E25-D25) -> 1697851.6 | G25: =IF($A25="","",MAX(0,F25-$B$11)*$B$10/100) -> 196606.45 | H25: =IF($A25="","",E25-G25) -> 3661245.1 | I25: =IF($A25="","",H25/(1+$B$9/100)^A25) -> 2167085.4
A26: =IF(ROW()-16<=$B$8,ROW()-16,"") -> 10 | B26: =IF($A26="","",E25) -> 3857851.6 | C26: =IF($A26="","",$B$6*12) -> 240000 | D26: =IF($A26="","",D25+C26) -> 2400000 | E26: =IF($A26="","",E25*(1+$B$7/1200)^12+FV($B$7/1200,12,-$B$6,0,0)) -> 4600773.8 | F26: =IF($A26="","",E26-D26) -> 2200773.8 | G26: =IF($A26="","",MAX(0,F26-$B$11)*$B$10/100) -> 259471.72 | H26: =IF($A26="","",E26-G26) -> 4341302.1 | I26: =IF($A26="","",H26/(1+$B$9/100)^A26) -> 2424160.4
A27: =IF(ROW()-16<=$B$8,ROW()-16,"") -> 11 | B27: =IF($A27="","",E26) -> 4600773.8 | C27: =IF($A27="","",$B$6*12) -> 240000 | D27: =IF($A27="","",D26+C27) -> 2640000 | E27: =IF($A27="","",E26*(1+$B$7/1200)^12+FV($B$7/1200,12,-$B$6,0,0)) -> 5437917.1 | F27: =IF($A27="","",E27-D27) -> 2797917.1 | G27: =IF($A27="","",MAX(0,F27-$B$11)*$B$10/100) -> 334114.64 | H27: =IF($A27="","",E27-G27) -> 5103802.5 | I27: =IF($A27="","",H27/(1+$B$9/100)^A27) -> 2688619.5
A28: =IF(ROW()-16<=$B$8,ROW()-16,"") -> 12 | B28: =IF($A28="","",E27) -> 5437917.1 | C28: =IF($A28="","",$B$6*12) -> 240000 | D28: =IF($A28="","",D27+C28) -> 2880000 | E28: =IF($A28="","",E27*(1+$B$7/1200)^12+FV($B$7/1200,12,-$B$6,0,0)) -> 6381231.2 | F28: =IF($A28="","",E28-D28) -> 3501231.2 | G28: =IF($A28="","",MAX(0,F28-$B$11)*$B$10/100) -> 422028.9 | H28: =IF($A28="","",E28-G28) -> 5959202.3 | I28: =IF($A28="","",H28/(1+$B$9/100)^A28) -> 2961541
A29: =IF(ROW()-16<=$B$8,ROW()-16,"") -> 13 | B29: =IF($A29="","",E28) -> 6381231.2 | C29: =IF($A29="","",$B$6*12) -> 240000 | D29: =IF($A29="","",D28+C29) -> 3120000 | E29: =IF($A29="","",E28*(1+$B$7/1200)^12+FV($B$7/1200,12,-$B$6,0,0)) -> 7444181.1 | F29: =IF($A29="","",E29-D29) -> 4324181.1 | G29: =IF($A29="","",MAX(0,F29-$B$11)*$B$10/100) -> 524897.64 | H29: =IF($A29="","",E29-G29) -> 6919283.4 | I29: =IF($A29="","",H29/(1+$B$9/100)^A29) -> 3244030.1
... A56: =IF(ROW()-16<=$B$8,ROW()-16,"") | B56: =IF($A56="","",E55) | C56: =IF($A56="","",$B$6*12) | D56: =IF($A56="","",D55+C56) | E56: =IF($A56="","",E55*(1+$B$7/1200)^12+FV($B$7/1200,12,-$B$6,0,0)) | F56: =IF($A56="","",E56-D56) | G56: =IF($A56="","",MAX(0,F56-$B$11)*$B$10/100) | H56: =IF($A56="","",E56-G56) | I56: =IF($A56="","",H56/(1+$B$9/100)^A56)
A58: HOW TO READ THE RESULTS
A59: ="1. Over "&TEXT($B$8,"0")&" years, total contributions are ₹"&TEXT($E$5,"##,##,##0")&" and the projected nominal portfolio is ₹"&TEXT($E$6,"##,##,##0")&"." -> 1. Over 20 years, total contributions are ₹48,00,000 and the projected nominal portfolio is ₹1,97,85,107.
A60: ="2. The projected nominal gain is ₹"&TEXT($E$7,"##,##,##0")&"; estimated tax on a full final redemption is ₹"&TEXT($E$8,"##,##,##0")&", leaving ₹"&TEXT($E$9,"##,##,##0")&" nominally." -> 2. The projected nominal gain is ₹1,49,85,107; estimated tax on a full final redemption is ₹18,57,513, leaving ₹1,79,27,594 nominally.
A61: ="3. After adjusting the post-tax corpus for "&TEXT($B$9/100,"0.0%")&" annual inflation, its value in today’s rupees is ₹"&TEXT($E$10,"##,##,##0")&"." -> 3. After adjusting the post-tax corpus for 6.0% annual inflation, its value in today’s rupees is ₹55,89,909.
A62: ="4. Contributions are brought to today's rupees year by year (each year's twelve instalments divided by (1 + inflation) for that year). The real gain of ₹" & TEXT($E$11,"##,##,##0") & " compares the post-tax real value with those contributions." -> 4. Contributions are brought to today's rupees year by year (each year's twelve instalments divided by (1 + inflation) for that year). The real gain of ₹28,37,127 compares the post-tax real value with those contributions.
A64: INPUT GUIDE
A65: Input | C65: How it affects the model | G65: Current value
A66: Lumpsum at start | C66: One-time amount invested immediately; it compounds for the entire selected tenure. | G66: =B5 -> 0
A67: Monthly SIP amount | C67: Contribution made at the end of every month; annual contribution shown in the table equals 12 monthly SIPs. | G67: =B6 -> 20000
A68: Expected annual return | C68: Nominal annual return divided by 12 for monthly compounding; it is an assumption, not a guaranteed return. | G68: =B7 -> 12
A69: Tenure | C69: Number of years projected and the number of yearly rows generated in the schedule. | G69: =B8 -> 20
A70: Inflation | C70: Used to discount each year’s post-tax nominal value into today’s purchasing power. | G70: =B9 -> 6
A71: LTCG tax rate | C71: Tax percentage applied to estimated qualifying gains above the exemption on a full redemption. | G71: =B10 -> 12.5
A72: LTCG exemption | C72: Amount of qualifying long-term capital gain excluded from the simplified tax calculation. | G72: =B11 -> 125000
A74: OUTPUT & CALCULATION FLOW
A75: Output | D75: Meaning / calculation flow
A76: Total amount invested | D76: Lumpsum + monthly SIP × 12 × tenure. This is contributed capital, excluding returns.
A77: Future value (nominal) | D77: Lumpsum growth plus the future value of all month-end SIP contributions before tax and inflation.
A78: Investment gain (nominal) | D78: Nominal future value less total amount invested.
A79: Estimated LTCG tax | D79: Maximum of zero and (nominal gain − exemption), multiplied by the LTCG tax rate.
A80: Post-tax value (nominal) | D80: Nominal future value less estimated LTCG tax.
A81: Post-tax value (real) | D81: Post-tax nominal value divided by (1 + inflation rate) raised to the elapsed years.
A82: Real gain vs contributions | D82: Post-tax real value less contributions brought to today's rupees year by year; both sides are in today's rupees.
A84: ASSUMPTIONS & LIMITATIONS
A85: 1. Returns are constant and compounded monthly; actual market returns will vary and may include losses.
A86: 2. Monthly SIPs are assumed to occur at each month-end, with no missed payments, step-up SIP, withdrawals, or rebalancing.
A87: 3. Tax is estimated as if the full portfolio were redeemed at each year-end and all gains qualified for Section 112A LTCG. Recent SIP instalments may actually be short-term; cess, surcharge, grandfathering, loss set-off, and tax harvesting are excluded.
A88: 4. Expense ratios, exit loads, transaction costs, tracking error, and advisory fees are excluded, so actual net values may be lower.
A89: 5. Inflation is assumed constant. “Real value” means purchasing power in today’s rupees, not the amount visible in the future account statement.
A90: 6. This is an illustration for scenario comparison, not a return guarantee, tax filing computation, or personalized investment recommendation.
A92: NOMINAL VS REAL WEALTH — A SIMPLE GUIDE
A93: Why a large future amount may not buy as much as it appears to—and how inflation-adjusted values improve financial decisions.
A95: 1. THE BASIC IDEA
A96: Nominal wealth is the amount of money shown in your future account statement. It is measured in future rupees and does not adjust for rising prices. If your portfolio becomes ₹1 crore after 20 years, ₹1 crore is its nominal value.
A97: Real wealth expresses that future money in today’s purchasing power. It answers a more practical question: “What would this future amount be able to buy compared with what money can buy today?”
... A100: 2. NOMINAL AND REAL WEALTH COMPARED
A101: Term | D101: Simple meaning
A102: Nominal wealth | D102: The future rupee amount before adjusting for inflation. This is the balance you expect to see in the account.
A103: Real wealth | D103: The inflation-adjusted value of that future balance, expressed in today’s rupees.
A104: Nominal return | D104: The stated investment growth rate before removing inflation.
A105: Real return | D105: The increase in purchasing power after accounting for inflation.
A106: Purchasing power | D106: The quantity of goods and services that money can buy. Inflation reduces it over time.
A108: 3. HOW REAL WEALTH IS CALCULATED
A109: A future amount is converted into today’s money by dividing it by the inflation growth factor: Real Value = Nominal Value ÷ (1 + Inflation Rate) ^ Number of Years.
A110: ="Using this sheet: ₹"&TEXT($E$9,"##,##,##0")&" of post-tax nominal wealth after "&TEXT($B$8,"0")&" years becomes ₹"&TEXT($E$10,"##,##,##0")&" in today’s rupees when inflation is "&TEXT($B$9/100,"0.0%")&" per year." -> Using this sheet: ₹1,79,27,594 of post-tax nominal wealth after 20 years becomes ₹55,89,909 in today’s rupees when inflation is 6.0% per year.
A111: ="In other words, the nominal account balance is about "&TEXT($E$9/$E$10,"0.00")&" times the real value because prices are assumed to rise throughout the period." -> In other words, the nominal account balance is about 3.21 times the real value because prices are assumed to rise throughout the period.
A113: 4. NOMINAL RETURN IS NOT THE SAME AS REAL RETURN
A114: A quick estimate of real return is nominal return minus inflation. For example, a 12% return with 6% inflation is roughly a 6% real return. This shortcut is useful, but it is not exact.
A115: ="The exact real return for the current assumptions is "&TEXT((1+$B$7/100)/(1+$B$9/100)-1,"0.00%")&", calculated as (1 + nominal return) ÷ (1 + inflation) − 1." -> The exact real return for the current assumptions is 5.66%, calculated as (1 + nominal return) ÷ (1 + inflation) − 1.
A116: Taxes, fees, and investment costs reduce the return further. Therefore, post-tax real return is usually the most useful measure when planning future spending.
A118: 5. WHY THIS MATTERS FOR FINANCIAL PLANNING
A119: 1. Retirement: A future corpus may look large, but retirement expenses will also be higher. Plan using inflation-adjusted spending needs.
A120: 2. Education and healthcare: These costs may rise faster than general inflation, so a single inflation assumption may understate the required amount.
A121: 3. Comparing investments: Compare alternatives using the same time period, inflation assumption, tax treatment, and risk level.
A122: 4. Goals: Set goals in today’s rupees first, then inflate them to estimate the future nominal amount required.
A123: 5. Decisions: Use nominal values for expected account balances and real values for understanding lifestyle and purchasing power.
A125: 6. COMMON MISTAKES TO AVOID
A126: Do not compare a future nominal portfolio directly with today’s expenses. Do not treat expected returns as guaranteed. Do not ignore taxes and fees. Also, do not subtract inflation from the final corpus as a simple percentage—the adjustment compounds over every year.
A128: 7. BOTTOM LINE
A129: Nominal wealth tells you how many future rupees you may have. Real wealth tells you what those rupees may actually be worth. Both figures are useful, but real wealth is usually better for judging whether your future money can support the lifestyle or goal you are planning for.
A130: Remember: real wealth is still an estimate because future returns, inflation, taxes, and costs are uncertain. Use several scenarios rather than relying on one forecast.

Sheet Expense Ratio Impact
A1: MUTUAL FUND EXPENSE-RATIO IMPACT CALCULATOR
A2: Compare direct and regular plans using the same gross return; the difference shows how annual fund expenses compound into a long-term rupee cost.
A4: MODEL INPUTS | D4: SELECTED-HORIZON SUMMARY | H4: HOW TO READ THE RESULT
A5: Lumpsum at Start (₹) | B5: 0 | D5: Direct Net Return | E5: =B7-B8 -> 11.5 | H5: ="1. At year "&TEXT($B$10,"0")&", the higher expense ratio reduces pre-tax wealth by "&TEXT($E$10,"₹#,##0")&"." -> 1. At year 20, the higher expense ratio reduces pre-tax wealth by ₹22,91,924.
A6: Monthly SIP Amount (₹) | B6: 20000 | D6: Regular Net Return | E6: =B7-B9 -> 10.5 | H6: ="2. In today’s rupees after simplified tax, the wealth gap is "&TEXT($E$13,"₹#,##0")&"." -> 2. In today’s rupees after simplified tax, the wealth gap is ₹6,25,304.
A7: Gross Return Before Expenses (% p.a.) | B7: ='Common Assumptions'!$B$6 -> 12 | D7: Total Amount Invested | E7: =B5+B6*12*B10 -> 4800000 | H7: ="3. The annual TER difference is "&TEXT($B$9-$B$8,"0.00")&" percentage points; the cost accelerates as the portfolio grows." -> 3. The annual TER difference is 1.00 percentage points; the cost accelerates as the portfolio grows.
A8: Direct Plan Expense Ratio (% p.a.) | B8: ='Common Assumptions'!$B$10 -> 0.5 | D8: Direct Value Before Tax | E8: {=INDEX(C27:C56,B10)} -> 18502021 | H8: 4. Both plans are assumed to earn the same gross return before expenses; only the expense ratio differs.
A9: Regular Plan Expense Ratio (% p.a.) | B9: ='Common Assumptions'!$B$11 -> 1.5 | D9: Regular Value Before Tax | E9: {=INDEX(G27:G56,B10)} -> 16210098 | H9: 5. Tax is estimated as if the full portfolio were redeemed at each year-end and all gains qualified for the selected LTCG treatment.
A10: Selected Horizon (5–30 years) | B10: 20 | D10: Wealth Lost Before Tax | E10: =E8-E9 -> 2291923.7 | H10: 6. Returns, inflation, expenses, and tax inputs are assumptions—not forecasts or guarantees.
A11: Inflation (% p.a.) | B11: ='Common Assumptions'!$B$5 -> 6 | D11: Direct Post-Tax Value (Real) | E11: {=INDEX(F27:F56,B10)} -> 5239845.2
A12: LTCG Tax Rate (%) | B12: ='Common Assumptions'!$B$12 -> 12.5 | D12: Regular Post-Tax Value (Real) | E12: {=INDEX(J27:J56,B10)} -> 4614541.7
A13: LTCG Exemption (₹) | B13: ='Common Assumptions'!$B$13 -> 125000 | D13: Real Wealth Lost to Higher TER | E13: =E11-E12 -> 625303.56
A16: 5–30 YEAR MILESTONE COMPARISON
A17: Year | B17: Total Invested | C17: Direct Value Before Tax | D17: Regular Value Before Tax | E17: Pre-Tax Wealth Lost | F17: Direct Post-Tax Real | G17: Regular Post-Tax Real | H17: Real Wealth Lost
A18: 5 | B18: {=INDEX($B$27:$B$56,$A18)} -> 1200000 | C18: {=INDEX($C$27:$C$56,$A18)} -> 1611697.8 | D18: {=INDEX($G$27:$G$56,$A18)} -> 1569378.2 | E18: =C18-D18 -> 42319.582 | F18: {=INDEX($F$27:$F$56,$A18)} -> 1177574.7 | G18: {=INDEX($J$27:$J$56,$A18)} -> 1149904 | H18: =F18-G18 -> 27670.697
A19: 10 | B19: {=INDEX($B$27:$B$56,$A19)} -> 2400000 | C19: {=INDEX($C$27:$C$56,$A19)} -> 4468064.6 | D19: {=INDEX($G$27:$G$56,$A19)} -> 4216296.3 | E19: =C19-D19 -> 251768.28 | F19: {=INDEX($F$27:$F$56,$A19)} -> 2359319.3 | G19: {=INDEX($J$27:$J$56,$A19)} -> 2236306.4 | H19: =F19-G19 -> 123012.83
A20: 15 | B20: {=INDEX($B$27:$B$56,$A20)} -> 3600000 | C20: {=INDEX($C$27:$C$56,$A20)} -> 9530323 | D20: {=INDEX($G$27:$G$56,$A20)} -> 8680596.1 | E20: =C20-D20 -> 849726.87 | F20: {=INDEX($F$27:$F$56,$A20)} -> 3673876 | G20: {=INDEX($J$27:$J$56,$A20)} -> 3363634.8 | H20: =F20-G20 -> 310241.17
A21: 20 | B21: {=INDEX($B$27:$B$56,$A21)} -> 4800000 | C21: {=INDEX($C$27:$C$56,$A21)} -> 18502021 | D21: {=INDEX($G$27:$G$56,$A21)} -> 16210098 | E21: =C21-D21 -> 2291923.7 | F21: {=INDEX($F$27:$F$56,$A21)} -> 5239845.2 | G21: {=INDEX($J$27:$J$56,$A21)} -> 4614541.7 | H21: =F21-G21 -> 625303.56
A22: 25 | B22: {=INDEX($B$27:$B$56,$A22)} -> 6000000 | C22: {=INDEX($C$27:$C$56,$A22)} -> 34402310 | D22: {=INDEX($G$27:$G$56,$A22)} -> 28909377 | E22: =C22-D22 -> 5492932.6 | F22: {=INDEX($F$27:$F$56,$A22)} -> 7192119.2 | G22: {=INDEX($J$27:$J$56,$A22)} -> 6072254.2 | H22: =F22-G22 -> 1119865
A23: 30 | B23: {=INDEX($B$27:$B$56,$A23)} -> 7200000 | C23: {=INDEX($C$27:$C$56,$A23)} -> 62581944 | D23: {=INDEX($G$27:$G$56,$A23)} -> 50328020 | E23: =C23-D23 -> 12253924 | F23: {=INDEX($F$27:$F$56,$A23)} -> 9693551.2 | G23: {=INDEX($J$27:$J$56,$A23)} -> 7826710.4 | H23: =F23-G23 -> 1866840.7
A25: YEARLY EXPENSE-RATIO IMPACT SCHEDULE
A26: Year | B26: Total Invested | C26: Direct Value Before Tax | D26: Direct LTCG Tax | E26: Direct Post-Tax Value | F26: Direct Post-Tax Real | G26: Regular Value Before Tax | H26: Regular LTCG Tax | I26: Regular Post-Tax Value | J26: Regular Post-Tax Real | K26: Pre-Tax Wealth Lost | L26: Real Wealth Lost
A27: =ROW()-26 -> 1 | B27: =$B$5+$B$6*12*A27 -> 240000 | C27: =$B$5*(1+($B$7-$B$8)/1200)^(12*A27)+FV(($B$7-$B$8)/1200,12*A27,-$B$6,0,0) -> 253062.95 | D27: =MAX(0,C27-B27-$B$13)*$B$12/100 -> 0 | E27: =C27-D27 -> 253062.95 | F27: =E27/(1+$B$11/100)^A27 -> 238738.63 | G27: =$B$5*(1+($B$7-$B$9)/1200)^(12*A27)+FV(($B$7-$B$9)/1200,12*A27,-$B$6,0,0) -> 251893.6 | H27: =MAX(0,G27-B27-$B$13)*$B$12/100 -> 0 | I27: =G27-H27 -> 251893.6 | J27: =I27/(1+$B$11/100)^A27 -> 237635.47 | K27: =C27-G27 -> 1169.3446 | L27: =F27-J27 -> 1103.1553
A28: =ROW()-26 -> 2 | B28: =$B$5+$B$6*12*A28 -> 480000 | C28: =$B$5*(1+($B$7-$B$8)/1200)^(12*A28)+FV(($B$7-$B$8)/1200,12*A28,-$B$6,0,0) -> 536812.13 | D28: =MAX(0,C28-B28-$B$13)*$B$12/100 -> 0 | E28: =C28-D28 -> 536812.13 | F28: =E28/(1+$B$11/100)^A28 -> 477760.89 | G28: =$B$5*(1+($B$7-$B$9)/1200)^(12*A28)+FV(($B$7-$B$9)/1200,12*A28,-$B$6,0,0) -> 531546.75 | H28: =MAX(0,G28-B28-$B$13)*$B$12/100 -> 0 | I28: =G28-H28 -> 531546.75 | J28: =I28/(1+$B$11/100)^A28 -> 473074.71 | K28: =C28-G28 -> 5265.3881 | L28: =F28-J28 -> 4686.1766
A29: =ROW()-26 -> 3 | B29: =$B$5+$B$6*12*A29 -> 720000 | C29: =$B$5*(1+($B$7-$B$8)/1200)^(12*A29)+FV(($B$7-$B$8)/1200,12*A29,-$B$6,0,0) -> 854968.56 | D29: =MAX(0,C29-B29-$B$13)*$B$12/100 -> 1246.0698 | E29: =C29-D29 -> 853722.49 | F29: =E29/(1+$B$11/100)^A29 -> 716801.86 | G29: =$B$5*(1+($B$7-$B$9)/1200)^(12*A29)+FV(($B$7-$B$9)/1200,12*A29,-$B$6,0,0) -> 842018.63 | H29: =MAX(0,G29-B29-$B$13)*$B$12/100 -> 0 | I29: =G29-H29 -> 842018.63 | J29: =I29/(1+$B$11/100)^A29 -> 706975.08 | K29: =C29-G29 -> 12949.926 | L29: =F29-J29 -> 9826.7833
A30: =ROW()-26 -> 4 | B30: =$B$5+$B$6*12*A30 -> 960000 | C30: =$B$5*(1+($B$7-$B$8)/1200)^(12*A30)+FV(($B$7-$B$8)/1200,12*A30,-$B$6,0,0) -> 1211704.4 | D30: =MAX(0,C30-B30-$B$13)*$B$12/100 -> 15838.052 | E30: =C30-D30 -> 1195866.4 | F30: =E30/(1+$B$11/100)^A30 -> 947238.17 | G30: =$B$5*(1+($B$7-$B$9)/1200)^(12*A30)+FV(($B$7-$B$9)/1200,12*A30,-$B$6,0,0) -> 1186705.6 | H30: =MAX(0,G30-B30-$B$13)*$B$12/100 -> 12713.199 | I30: =G30-H30 -> 1173992.4 | J30: =I30/(1+$B$11/100)^A30 -> 929911.94 | K30: =C30-G30 -> 24998.825 | L30: =F30-J30 -> 17326.234
A31: =ROW()-26 -> 5 | B31: =$B$5+$B$6*12*A31 -> 1200000 | C31: =$B$5*(1+($B$7-$B$8)/1200)^(12*A31)+FV(($B$7-$B$8)/1200,12*A31,-$B$6,0,0) -> 1611697.8 | D31: =MAX(0,C31-B31-$B$13)*$B$12/100 -> 35837.228 | E31: =C31-D31 -> 1575860.6 | F31: =E31/(1+$B$11/100)^A31 -> 1177574.7 | G31: =$B$5*(1+($B$7-$B$9)/1200)^(12*A31)+FV(($B$7-$B$9)/1200,12*A31,-$B$6,0,0) -> 1569378.2 | H31: =MAX(0,G31-B31-$B$13)*$B$12/100 -> 30547.281 | I31: =G31-H31 -> 1538831 | J31: =I31/(1+$B$11/100)^A31 -> 1149904 | K31: =C31-G31 -> 42319.582 | L31: =F31-J31 -> 27670.697
A32: =ROW()-26 -> 6 | B32: =$B$5+$B$6*12*A32 -> 1440000 | C32: =$B$5*(1+($B$7-$B$8)/1200)^(12*A32)+FV(($B$7-$B$8)/1200,12*A32,-$B$6,0,0) -> 2060194.2 | D32: =MAX(0,C32-B32-$B$13)*$B$12/100 -> 61899.271 | E32: =C32-D32 -> 1998294.9 | F32: =E32/(1+$B$11/100)^A32 -> 1408719.1 | G32: =$B$5*(1+($B$7-$B$9)/1200)^(12*A32)+FV(($B$7-$B$9)/1200,12*A32,-$B$6,0,0) -> 1994222.7 | H32: =MAX(0,G32-B32-$B$13)*$B$12/100 -> 53652.843 | I32: =G32-H32 -> 1940569.9 | J32: =I32/(1+$B$11/100)^A32 -> 1368025.2 | K32: =C32-G32 -> 65971.425 | L32: =F32-J32 -> 40693.845
A33: =ROW()-26 -> 7 | B33: =$B$5+$B$6*12*A33 -> 1680000 | C33: =$B$5*(1+($B$7-$B$8)/1200)^(12*A33)+FV(($B$7-$B$8)/1200,12*A33,-$B$6,0,0) -> 2563074.9 | D33: =MAX(0,C33-B33-$B$13)*$B$12/100 -> 94759.359 | E33: =C33-D33 -> 2468315.5 | F33: =E33/(1+$B$11/100)^A33 -> 1641570.8 | G33: =$B$5*(1+($B$7-$B$9)/1200)^(12*A33)+FV(($B$7-$B$9)/1200,12*A33,-$B$6,0,0) -> 2465886.6 | H33: =MAX(0,G33-B33-$B$13)*$B$12/100 -> 82610.821 | I33: =G33-H33 -> 2383275.7 | J33: =I33/(1+$B$11/100)^A33 -> 1585014.5 | K33: =C33-G33 -> 97188.303 | L33: =F33-J33 -> 56556.301
A34: =ROW()-26 -> 8 | B34: =$B$5+$B$6*12*A34 -> 1920000 | C34: =$B$5*(1+($B$7-$B$8)/1200)^(12*A34)+FV(($B$7-$B$8)/1200,12*A34,-$B$6,0,0) -> 3126934.6 | D34: =MAX(0,C34-B34-$B$13)*$B$12/100 -> 135241.82 | E34: =C34-D34 -> 2991692.7 | F34: =E34/(1+$B$11/100)^A34 -> 1877025 | G34: =$B$5*(1+($B$7-$B$9)/1200)^(12*A34)+FV(($B$7-$B$9)/1200,12*A34,-$B$6,0,0) -> 2989529.4 | H34: =MAX(0,G34-B34-$B$13)*$B$12/100 -> 118066.17 | I34: =G34-H34 -> 2871463.2 | J34: =I34/(1+$B$11/100)^A34 -> 1801591.5 | K34: =C34-G34 -> 137405.18 | L34: =F34-J34 -> 75433.494
A35: =ROW()-26 -> 9 | B35: =$B$5+$B$6*12*A35 -> 2160000 | C35: =$B$5*(1+($B$7-$B$8)/1200)^(12*A35)+FV(($B$7-$B$8)/1200,12*A35,-$B$6,0,0) -> 3759167.5 | D35: =MAX(0,C35-B35-$B$13)*$B$12/100 -> 184270.94 | E35: =C35-D35 -> 3574896.6 | F35: =E35/(1+$B$11/100)^A35 -> 2115975.8 | G35: =$B$5*(1+($B$7-$B$9)/1200)^(12*A35)+FV(($B$7-$B$9)/1200,12*A35,-$B$6,0,0) -> 3570879.4 | H35: =MAX(0,G35-B35-$B$13)*$B$12/100 -> 160734.93 | I35: =G35-H35 -> 3410144.5 | J35: =I35/(1+$B$11/100)^A35 -> 2018459.3 | K35: =C35-G35 -> 188288.05 | L35: =F35-J35 -> 97516.482
A36: =ROW()-26 -> 10 | B36: =$B$5+$B$6*12*A36 -> 2400000 | C36: =$B$5*(1+($B$7-$B$8)/1200)^(12*A36)+FV(($B$7-$B$8)/1200,12*A36,-$B$6,0,0) -> 4468064.6 | D36: =MAX(0,C36-B36-$B$13)*$B$12/100 -> 242883.07 | E36: =C36-D36 -> 4225181.5 | F36: =E36/(1+$B$11/100)^A36 -> 2359319.3 | G36: =$B$5*(1+($B$7-$B$9)/1200)^(12*A36)+FV(($B$7-$B$9)/1200,12*A36,-$B$6,0,0) -> 4216296.3 | H36: =MAX(0,G36-B36-$B$13)*$B$12/100 -> 211412.03 | I36: =G36-H36 -> 4004884.2 | J36: =I36/(1+$B$11/100)^A36 -> 2236306.4 | K36: =C36-G36 -> 251768.28 | L36: =F36-J36 -> 123012.83
A37: =ROW()-26 -> 11 | B37: =$B$5+$B$6*12*A37 -> 2640000 | C37: =$B$5*(1+($B$7-$B$8)/1200)^(12*A37)+FV(($B$7-$B$8)/1200,12*A37,-$B$6,0,0) -> 5262922 | D37: =MAX(0,C37-B37-$B$13)*$B$12/100 -> 312240.25 | E37: =C37-D37 -> 4950681.8 | F37: =E37/(1+$B$11/100)^A37 -> 2607957.4 | G37: =$B$5*(1+($B$7-$B$9)/1200)^(12*A37)+FV(($B$7-$B$9)/1200,12*A37,-$B$6,0,0) -> 4932840.3 | H37: =MAX(0,G37-B37-$B$13)*$B$12/100 -> 270980.03 | I37: =G37-H37 -> 4661860.2 | J37: =I37/(1+$B$11/100)^A37 -> 2455809.8 | K37: =C37-G37 -> 330081.74 | L37: =F37-J37 -> 152147.57
A38: =ROW()-26 -> 12 | B38: =$B$5+$B$6*12*A38 -> 2880000 | C38: =$B$5*(1+($B$7-$B$8)/1200)^(12*A38)+FV(($B$7-$B$8)/1200,12*A38,-$B$6,0,0) -> 6154163.3 | D38: =MAX(0,C38-B38-$B$13)*$B$12/100 -> 393645.42 | E38: =C38-D38 -> 5760517.9 | F38: =E38/(1+$B$11/100)^A38 -> 2862800.9 | G38: =$B$5*(1+($B$7-$B$9)/1200)^(12*A38)+FV(($B$7-$B$9)/1200,12*A38,-$B$6,0,0) -> 5728349.9 | H38: =MAX(0,G38-B38-$B$13)*$B$12/100 -> 340418.74 | I38: =G38-H38 -> 5387931.2 | J38: =I38/(1+$B$11/100)^A38 -> 2677636.7 | K38: =C38-G38 -> 425813.45 | L38: =F38-J38 -> 185164.21
... A56: =ROW()-26 -> 30 | B56: =$B$5+$B$6*12*A56 -> 7200000 | C56: =$B$5*(1+($B$7-$B$8)/1200)^(12*A56)+FV(($B$7-$B$8)/1200,12*A56,-$B$6,0,0) -> 62581944 | D56: =MAX(0,C56-B56-$B$13)*$B$12/100 -> 6907118 | E56: =C56-D56 -> 55674826 | F56: =E56/(1+$B$11/100)^A56 -> 9693551.2 | G56: =$B$5*(1+($B$7-$B$9)/1200)^(12*A56)+FV(($B$7-$B$9)/1200,12*A56,-$B$6,0,0) -> 50328020 | H56: =MAX(0,G56-B56-$B$13)*$B$12/100 -> 5375377.5 | I56: =G56-H56 -> 44952642 | J56: =I56/(1+$B$11/100)^A56 -> 7826710.4 | K56: =C56-G56 -> 12253924 | L56: =F56-J56 -> 1866840.7
A59: ASSUMPTIONS & LIMITATIONS
A60: 1. Net return is modeled as gross annual return minus the annual expense ratio, compounded monthly. Actual NAVs deduct expenses daily and realized returns vary.
A61: 2. Direct and regular plans are assumed to hold the same portfolio. Distributor advice, service quality, exit loads, tracking differences, cess, surcharge, and tax-lot timing are excluded.
A62: 3. The tax estimate assumes one full year-end redemption and qualifying long-term gains above the exemption; recent SIP instalments may not qualify as long term.

Sheet Loan Prepayment
A1: HOME-LOAN PREPAYMENT & RATE-CHANGE SCENARIO CALCULATOR
A2: Compare a normal loan, multiple lump sums, monthly extra payments, a mid-term rate change, and their combined effect.
A4: LOAN & PREPAYMENT INPUTS | D4: NORMAL LOAN SUMMARY | G4: SELECTED SCENARIO SUMMARY
A5: Loan Amount (₹) | B5: 10000000 | D5: Monthly EMI | E5: =-PMT($B$6/1200,$B$7*12,$B$5) -> 80559.319 | G5: Chosen Scenario | H5: =$H$13 -> Combination of All
A6: Interest Rate (% p.a.) | B6: ='Common Assumptions'!$B$7 -> 7.5 | D6: Total Interest | E6: =SUM('Prepayment Engine'!$E$2:$E$481) -> 9334236.6 | G6: Payoff Months | H6: =INDEX($D$36:$D$40,MATCH($H$13,$A$36:$A$40,0)) -> 223
A7: Original Tenure (years) | B7: 20 | D7: Total Repayment | E7: =$B$5+$E$6 -> 19334237 | G7: Payoff Years | H7: =$H$6/12 -> 18.583333
A8: Monthly Extra Payment (₹) | B8: 0 | D8: Original Tenure | E8: =$B$7 -> 20 | G8: Total Interest | H8: =INDEX($F$36:$F$40,MATCH($H$13,$A$36:$A$40,0)) -> 6993795.3
A9: Monthly Extra Starts in Month | B9: 1 | D9: Payoff Month | E9: {=IFERROR(_xlfn.XMATCH(TRUE,'Prepayment Engine'!$H$2:$H$481<=0.01,0),480)} -> 240 | G9: Interest Saved | H9: =INDEX($G$36:$G$40,MATCH($H$13,$A$36:$A$40,0)) -> 2340441.3
A10: LUMP-SUM PREPAYMENTS | D10: MID-TERM RATE CHANGE | G10: Total Prepayment | H10: =INDEX($H$36:$H$40,MATCH($H$13,$A$36:$A$40,0)) -> 1500000
A11: Payment Month | B11: Amount (₹) | D11: New Rate Starts in Month | E11: 61 | G11: EMI After Rate Change | H11: =INDEX($C$36:$C$40,MATCH($H$13,$A$36:$A$40,0)) -> 67460.316
A12: 12 | B12: 500000 | D12: New Interest Rate (% p.a.) | E12: =$B$6-1 -> 6.5
A13: 36 | B13: 500000 | D13: Lender Treatment | E13: Keep EMI, change tenure | G13: Detailed Scenario | H13: Combination of All
A14: 60 | B14: 500000
A15: 0 | B15: 0 | D15: Preferred Strategy | E15: Reduce EMI
A16: 0 | B16: 0 | D16: Monthly Extra Ends in Month | E16: 240
A17: 0 | B17: 0
A18: 0 | B18: 0
A19: 0 | B19: 0
A20: 0 | B20: 0
A21: 0 | B21: 0
A22: 0 | B22: 0
A23: 0 | B23: 0
A24: 0 | B24: 0
A25: 0 | B25: 0
A26: 0 | B26: 0
A27: 0 | B27: 0
A28: 0 | B28: 0
... A31: 0 | B31: 0
A34: FIVE-SCENARIO COMPARISON
A35: Scenario | B35: Initial EMI | C35: EMI After Rate Change | D35: Payoff Months | E35: Payoff Years | F35: Total Interest | G35: Interest Savings | H35: Total Prepayment
A36: Normal Loan | B36: ='Prepayment Engine'!$D$2 -> 80559.319 | C36: — | D36: {=IFERROR(_xlfn.XMATCH(TRUE,'Prepayment Engine'!$H$2:$H$481<=0.01,0),480)} -> 240 | E36: =D36/12 -> 20 | F36: =SUM('Prepayment Engine'!$E$2:$E$481) -> 9334236.6 | G36: =$F$36-F36 -> 0 | H36: =SUM('Prepayment Engine'!$G$2:$G$481) -> 0
A37: Multiple Lump Sums | B37: ='Prepayment Engine'!$L$2 -> 80559.319 | C37: — | D37: {=IFERROR(_xlfn.XMATCH(TRUE,'Prepayment Engine'!$P$2:$P$481<=0.01,0),480)} -> 240 | E37: =D37/12 -> 20 | F37: =SUM('Prepayment Engine'!$M$2:$M$481) -> 8174392.1 | G37: =$F$36-F37 -> 1159844.6 | H37: =SUM('Prepayment Engine'!$O$2:$O$481) -> 1500000
A38: Monthly Extra Payment | B38: ='Prepayment Engine'!$T$2 -> 80559.319 | C38: — | D38: {=IFERROR(_xlfn.XMATCH(TRUE,'Prepayment Engine'!$X$2:$X$481<=0.01,0),480)} -> 240 | E38: =D38/12 -> 20 | F38: =SUM('Prepayment Engine'!$U$2:$U$481) -> 9334236.6 | G38: =$F$36-F38 -> 0 | H38: =SUM('Prepayment Engine'!$W$2:$W$481) -> 0
A39: Mid-Term Rate Change | B39: ='Prepayment Engine'!$AB$2 -> 80559.319 | C39: {=INDEX('Prepayment Engine'!$AB$2:$AB$481,$E$11)} -> 80559.319 | D39: {=IFERROR(_xlfn.XMATCH(TRUE,'Prepayment Engine'!$AF$2:$AF$481<=0.01,0),480)} -> 223 | E39: =D39/12 -> 18.583333 | F39: =SUM('Prepayment Engine'!$AC$2:$AC$481) -> 7924399.4 | G39: =$F$36-F39 -> 1409837.3 | H39: =SUM('Prepayment Engine'!$AE$2:$AE$481) -> 0
A40: Combination of All | B40: ='Prepayment Engine'!$AJ$2 -> 80559.319 | C40: {=INDEX('Prepayment Engine'!$AJ$2:$AJ$481,$E$11)} -> 67460.316 | D40: {=IFERROR(_xlfn.XMATCH(TRUE,'Prepayment Engine'!$AN$2:$AN$481<=0.01,0),480)} -> 223 | E40: =D40/12 -> 18.583333 | F40: =SUM('Prepayment Engine'!$AK$2:$AK$481) -> 6993795.3 | G40: =$F$36-F40 -> 2340441.3 | H40: =SUM('Prepayment Engine'!$AM$2:$AM$481) -> 1500000
A44: HOW TO READ THE RESULT
A45: 1. Enter the outstanding loan, current rate and remaining tenure. 2. Add up to five lump sums in A12:B16; use 0 for unused rows. 3. Set monthly extra payment in B8, its start in B9 and end in E16. 4. E11:E13 controls the new rate and whether EMI or tenure changes. 5. Choose the prepayment treatment in E15 and the detailed scenario in H13.
A53: ASSUMPTIONS & LIMITATIONS
A54: Interest is calculated monthly on the reducing balance. EMI is applied first, followed by monthly extra and any lump sum scheduled for that month. Up to five lump sums are supported; enter 0 for unused rows. The model excludes fees, penalties, insurance, taxes, tax benefits, missed payments, and lender-specific day-count rules. Results are planning estimates; confirm the lender’s revised schedule.
A62: YEARLY COMPARISON SCHEDULE
A63: SELECTED-SCENARIO YEARLY SCHEDULE
A64: Year | B64: Opening Balance | C64: Ending Rate % | D64: EMI Paid | E64: Interest Paid | F64: Principal Paid | G64: Prepayment | H64: Closing Balance
A65: 1 | B65: {=IF((A65-1)*12<$H$6,INDEX('Prepayment Engine'!$A$2:$AN$481,(A65-1)*12+1,MATCH($H$13,'Prepayment Engine'!$A$1:$AN$1,0)+1),"")} -> 10000000 | C65: {=IF((A65-1)*12<$H$6,INDEX('Prepayment Engine'!$A$2:$AN$481,MIN(A65*12,$H$6),MATCH($H$13,'Prepayment Engine'!$A$1:$AN$1,0)+2),"")} -> 7.5 | D65: =IF((A65-1)*12<$H$6,SUM(INDEX('Prepayment Engine'!$A$2:$AN$481,(A65-1)*12+1,MATCH($H$13,'Prepayment Engine'!$A$1:$AN$1,0)+3):INDEX('Prepayment Engine'!$A$2:$AN$481,MIN(A65*12,$H$6),MATCH($H$13,'Prepayment Engine'!$A$1:$AN$1,0)+3)),"") -> 966711.83 | E65: =IF((A65-1)*12<$H$6,SUM(INDEX('Prepayment Engine'!$A$2:$AN$481,(A65-1)*12+1,MATCH($H$13,'Prepayment Engine'!$A$1:$AN$1,0)+4):INDEX('Prepayment Engine'!$A$2:$AN$481,MIN(A65*12,$H$6),MATCH($H$13,'Prepayment Engine'!$A$1:$AN$1,0)+4)),"") -> 742393.13 | F65: =IF((A65-1)*12<$H$6,SUM(INDEX('Prepayment Engine'!$A$2:$AN$481,(A65-1)*12+1,MATCH($H$13,'Prepayment Engine'!$A$1:$AN$1,0)+5):INDEX('Prepayment Engine'!$A$2:$AN$481,MIN(A65*12,$H$6),MATCH($H$13,'Prepayment Engine'!$A$1:$AN$1,0)+5)),"") -> 224318.7 | G65: =IF((A65-1)*12<$H$6,SUM(INDEX('Prepayment Engine'!$A$2:$AN$481,(A65-1)*12+1,MATCH($H$13,'Prepayment Engine'!$A$1:$AN$1,0)+6):INDEX('Prepayment Engine'!$A$2:$AN$481,MIN(A65*12,$H$6),MATCH($H$13,'Prepayment Engine'!$A$1:$AN$1,0)+6)),"") -> 500000 | H65: {=IF((A65-1)*12<$H$6,INDEX('Prepayment Engine'!$A$2:$AN$481,MIN(A65*12,$H$6),MATCH($H$13,'Prepayment Engine'!$A$1:$AN$1,0)+7),"")} -> 9275681.3
A66: =A65+1 -> 2 | B66: {=IF((A66-1)*12<$H$6,INDEX('Prepayment Engine'!$A$2:$AN$481,(A66-1)*12+1,MATCH($H$13,'Prepayment Engine'!$A$1:$AN$1,0)+1),"")} -> 9275681.3 | C66: {=IF((A66-1)*12<$H$6,INDEX('Prepayment Engine'!$A$2:$AN$481,MIN(A66*12,$H$6),MATCH($H$13,'Prepayment Engine'!$A$1:$AN$1,0)+2),"")} -> 7.5 | D66: =IF((A66-1)*12<$H$6,SUM(INDEX('Prepayment Engine'!$A$2:$AN$481,(A66-1)*12+1,MATCH($H$13,'Prepayment Engine'!$A$1:$AN$1,0)+3):INDEX('Prepayment Engine'!$A$2:$AN$481,MIN(A66*12,$H$6),MATCH($H$13,'Prepayment Engine'!$A$1:$AN$1,0)+3)),"") -> 917267.1 | E66: =IF((A66-1)*12<$H$6,SUM(INDEX('Prepayment Engine'!$A$2:$AN$481,(A66-1)*12+1,MATCH($H$13,'Prepayment Engine'!$A$1:$AN$1,0)+4):INDEX('Prepayment Engine'!$A$2:$AN$481,MIN(A66*12,$H$6),MATCH($H$13,'Prepayment Engine'!$A$1:$AN$1,0)+4)),"") -> 687897.96 | F66: =IF((A66-1)*12<$H$6,SUM(INDEX('Prepayment Engine'!$A$2:$AN$481,(A66-1)*12+1,MATCH($H$13,'Prepayment Engine'!$A$1:$AN$1,0)+5):INDEX('Prepayment Engine'!$A$2:$AN$481,MIN(A66*12,$H$6),MATCH($H$13,'Prepayment Engine'!$A$1:$AN$1,0)+5)),"") -> 229369.14 | G66: =IF((A66-1)*12<$H$6,SUM(INDEX('Prepayment Engine'!$A$2:$AN$481,(A66-1)*12+1,MATCH($H$13,'Prepayment Engine'!$A$1:$AN$1,0)+6):INDEX('Prepayment Engine'!$A$2:$AN$481,MIN(A66*12,$H$6),MATCH($H$13,'Prepayment Engine'!$A$1:$AN$1,0)+6)),"") -> 0 | H66: {=IF((A66-1)*12<$H$6,INDEX('Prepayment Engine'!$A$2:$AN$481,MIN(A66*12,$H$6),MATCH($H$13,'Prepayment Engine'!$A$1:$AN$1,0)+7),"")} -> 9046312.2
A67: =A66+1 -> 3 | B67: {=IF((A67-1)*12<$H$6,INDEX('Prepayment Engine'!$A$2:$AN$481,(A67-1)*12+1,MATCH($H$13,'Prepayment Engine'!$A$1:$AN$1,0)+1),"")} -> 9046312.2 | C67: {=IF((A67-1)*12<$H$6,INDEX('Prepayment Engine'!$A$2:$AN$481,MIN(A67*12,$H$6),MATCH($H$13,'Prepayment Engine'!$A$1:$AN$1,0)+2),"")} -> 7.5 | D67: =IF((A67-1)*12<$H$6,SUM(INDEX('Prepayment Engine'!$A$2:$AN$481,(A67-1)*12+1,MATCH($H$13,'Prepayment Engine'!$A$1:$AN$1,0)+3):INDEX('Prepayment Engine'!$A$2:$AN$481,MIN(A67*12,$H$6),MATCH($H$13,'Prepayment Engine'!$A$1:$AN$1,0)+3)),"") -> 917267.1 | E67: =IF((A67-1)*12<$H$6,SUM(INDEX('Prepayment Engine'!$A$2:$AN$481,(A67-1)*12+1,MATCH($H$13,'Prepayment Engine'!$A$1:$AN$1,0)+4):INDEX('Prepayment Engine'!$A$2:$AN$481,MIN(A67*12,$H$6),MATCH($H$13,'Prepayment Engine'!$A$1:$AN$1,0)+4)),"") -> 670091.44 | F67: =IF((A67-1)*12<$H$6,SUM(INDEX('Prepayment Engine'!$A$2:$AN$481,(A67-1)*12+1,MATCH($H$13,'Prepayment Engine'!$A$1:$AN$1,0)+5):INDEX('Prepayment Engine'!$A$2:$AN$481,MIN(A67*12,$H$6),MATCH($H$13,'Prepayment Engine'!$A$1:$AN$1,0)+5)),"") -> 247175.66 | G67: =IF((A67-1)*12<$H$6,SUM(INDEX('Prepayment Engine'!$A$2:$AN$481,(A67-1)*12+1,MATCH($H$13,'Prepayment Engine'!$A$1:$AN$1,0)+6):INDEX('Prepayment Engine'!$A$2:$AN$481,MIN(A67*12,$H$6),MATCH($H$13,'Prepayment Engine'!$A$1:$AN$1,0)+6)),"") -> 500000 | H67: {=IF((A67-1)*12<$H$6,INDEX('Prepayment Engine'!$A$2:$AN$481,MIN(A67*12,$H$6),MATCH($H$13,'Prepayment Engine'!$A$1:$AN$1,0)+7),"")} -> 8299136.5
A68: =A67+1 -> 4 | B68: {=IF((A68-1)*12<$H$6,INDEX('Prepayment Engine'!$A$2:$AN$481,(A68-1)*12+1,MATCH($H$13,'Prepayment Engine'!$A$1:$AN$1,0)+1),"")} -> 8299136.5 | C68: {=IF((A68-1)*12<$H$6,INDEX('Prepayment Engine'!$A$2:$AN$481,MIN(A68*12,$H$6),MATCH($H$13,'Prepayment Engine'!$A$1:$AN$1,0)+2),"")} -> 7.5 | D68: =IF((A68-1)*12<$H$6,SUM(INDEX('Prepayment Engine'!$A$2:$AN$481,(A68-1)*12+1,MATCH($H$13,'Prepayment Engine'!$A$1:$AN$1,0)+3):INDEX('Prepayment Engine'!$A$2:$AN$481,MIN(A68*12,$H$6),MATCH($H$13,'Prepayment Engine'!$A$1:$AN$1,0)+3)),"") -> 865144.54 | E68: =IF((A68-1)*12<$H$6,SUM(INDEX('Prepayment Engine'!$A$2:$AN$481,(A68-1)*12+1,MATCH($H$13,'Prepayment Engine'!$A$1:$AN$1,0)+4):INDEX('Prepayment Engine'!$A$2:$AN$481,MIN(A68*12,$H$6),MATCH($H$13,'Prepayment Engine'!$A$1:$AN$1,0)+4)),"") -> 613915.82 | F68: =IF((A68-1)*12<$H$6,SUM(INDEX('Prepayment Engine'!$A$2:$AN$481,(A68-1)*12+1,MATCH($H$13,'Prepayment Engine'!$A$1:$AN$1,0)+5):INDEX('Prepayment Engine'!$A$2:$AN$481,MIN(A68*12,$H$6),MATCH($H$13,'Prepayment Engine'!$A$1:$AN$1,0)+5)),"") -> 251228.72 | G68: =IF((A68-1)*12<$H$6,SUM(INDEX('Prepayment Engine'!$A$2:$AN$481,(A68-1)*12+1,MATCH($H$13,'Prepayment Engine'!$A$1:$AN$1,0)+6):INDEX('Prepayment Engine'!$A$2:$AN$481,MIN(A68*12,$H$6),MATCH($H$13,'Prepayment Engine'!$A$1:$AN$1,0)+6)),"") -> 0 | H68: {=IF((A68-1)*12<$H$6,INDEX('Prepayment Engine'!$A$2:$AN$481,MIN(A68*12,$H$6),MATCH($H$13,'Prepayment Engine'!$A$1:$AN$1,0)+7),"")} -> 8047907.8
A69: =A68+1 -> 5 | B69: {=IF((A69-1)*12<$H$6,INDEX('Prepayment Engine'!$A$2:$AN$481,(A69-1)*12+1,MATCH($H$13,'Prepayment Engine'!$A$1:$AN$1,0)+1),"")} -> 8047907.8 | C69: {=IF((A69-1)*12<$H$6,INDEX('Prepayment Engine'!$A$2:$AN$481,MIN(A69*12,$H$6),MATCH($H$13,'Prepayment Engine'!$A$1:$AN$1,0)+2),"")} -> 7.5 | D69: =IF((A69-1)*12<$H$6,SUM(INDEX('Prepayment Engine'!$A$2:$AN$481,(A69-1)*12+1,MATCH($H$13,'Prepayment Engine'!$A$1:$AN$1,0)+3):INDEX('Prepayment Engine'!$A$2:$AN$481,MIN(A69*12,$H$6),MATCH($H$13,'Prepayment Engine'!$A$1:$AN$1,0)+3)),"") -> 865144.54 | E69: =IF((A69-1)*12<$H$6,SUM(INDEX('Prepayment Engine'!$A$2:$AN$481,(A69-1)*12+1,MATCH($H$13,'Prepayment Engine'!$A$1:$AN$1,0)+4):INDEX('Prepayment Engine'!$A$2:$AN$481,MIN(A69*12,$H$6),MATCH($H$13,'Prepayment Engine'!$A$1:$AN$1,0)+4)),"") -> 594412.28 | F69: =IF((A69-1)*12<$H$6,SUM(INDEX('Prepayment Engine'!$A$2:$AN$481,(A69-1)*12+1,MATCH($H$13,'Prepayment Engine'!$A$1:$AN$1,0)+5):INDEX('Prepayment Engine'!$A$2:$AN$481,MIN(A69*12,$H$6),MATCH($H$13,'Prepayment Engine'!$A$1:$AN$1,0)+5)),"") -> 270732.26 | G69: =IF((A69-1)*12<$H$6,SUM(INDEX('Prepayment Engine'!$A$2:$AN$481,(A69-1)*12+1,MATCH($H$13,'Prepayment Engine'!$A$1:$AN$1,0)+6):INDEX('Prepayment Engine'!$A$2:$AN$481,MIN(A69*12,$H$6),MATCH($H$13,'Prepayment Engine'!$A$1:$AN$1,0)+6)),"") -> 500000 | H69: {=IF((A69-1)*12<$H$6,INDEX('Prepayment Engine'!$A$2:$AN$481,MIN(A69*12,$H$6),MATCH($H$13,'Prepayment Engine'!$A$1:$AN$1,0)+7),"")} -> 7277175.5
A70: =A69+1 -> 6 | B70: {=IF((A70-1)*12<$H$6,INDEX('Prepayment Engine'!$A$2:$AN$481,(A70-1)*12+1,MATCH($H$13,'Prepayment Engine'!$A$1:$AN$1,0)+1),"")} -> 7277175.5 | C70: {=IF((A70-1)*12<$H$6,INDEX('Prepayment Engine'!$A$2:$AN$481,MIN(A70*12,$H$6),MATCH($H$13,'Prepayment Engine'!$A$1:$AN$1,0)+2),"")} -> 6.5 | D70: =IF((A70-1)*12<$H$6,SUM(INDEX('Prepayment Engine'!$A$2:$AN$481,(A70-1)*12+1,MATCH($H$13,'Prepayment Engine'!$A$1:$AN$1,0)+3):INDEX('Prepayment Engine'!$A$2:$AN$481,MIN(A70*12,$H$6),MATCH($H$13,'Prepayment Engine'!$A$1:$AN$1,0)+3)),"") -> 809523.8 | E70: =IF((A70-1)*12<$H$6,SUM(INDEX('Prepayment Engine'!$A$2:$AN$481,(A70-1)*12+1,MATCH($H$13,'Prepayment Engine'!$A$1:$AN$1,0)+4):INDEX('Prepayment Engine'!$A$2:$AN$481,MIN(A70*12,$H$6),MATCH($H$13,'Prepayment Engine'!$A$1:$AN$1,0)+4)),"") -> 462808.06 | F70: =IF((A70-1)*12<$H$6,SUM(INDEX('Prepayment Engine'!$A$2:$AN$481,(A70-1)*12+1,MATCH($H$13,'Prepayment Engine'!$A$1:$AN$1,0)+5):INDEX('Prepayment Engine'!$A$2:$AN$481,MIN(A70*12,$H$6),MATCH($H$13,'Prepayment Engine'!$A$1:$AN$1,0)+5)),"") -> 346715.74 | G70: =IF((A70-1)*12<$H$6,SUM(INDEX('Prepayment Engine'!$A$2:$AN$481,(A70-1)*12+1,MATCH($H$13,'Prepayment Engine'!$A$1:$AN$1,0)+6):INDEX('Prepayment Engine'!$A$2:$AN$481,MIN(A70*12,$H$6),MATCH($H$13,'Prepayment Engine'!$A$1:$AN$1,0)+6)),"") -> 0 | H70: {=IF((A70-1)*12<$H$6,INDEX('Prepayment Engine'!$A$2:$AN$481,MIN(A70*12,$H$6),MATCH($H$13,'Prepayment Engine'!$A$1:$AN$1,0)+7),"")} -> 6930459.8
A71: =A70+1 -> 7 | B71: {=IF((A71-1)*12<$H$6,INDEX('Prepayment Engine'!$A$2:$AN$481,(A71-1)*12+1,MATCH($H$13,'Prepayment Engine'!$A$1:$AN$1,0)+1),"")} -> 6930459.8 | C71: {=IF((A71-1)*12<$H$6,INDEX('Prepayment Engine'!$A$2:$AN$481,MIN(A71*12,$H$6),MATCH($H$13,'Prepayment Engine'!$A$1:$AN$1,0)+2),"")} -> 6.5 | D71: =IF((A71-1)*12<$H$6,SUM(INDEX('Prepayment Engine'!$A$2:$AN$481,(A71-1)*12+1,MATCH($H$13,'Prepayment Engine'!$A$1:$AN$1,0)+3):INDEX('Prepayment Engine'!$A$2:$AN$481,MIN(A71*12,$H$6),MATCH($H$13,'Prepayment Engine'!$A$1:$AN$1,0)+3)),"") -> 809523.8 | E71: =IF((A71-1)*12<$H$6,SUM(INDEX('Prepayment Engine'!$A$2:$AN$481,(A71-1)*12+1,MATCH($H$13,'Prepayment Engine'!$A$1:$AN$1,0)+4):INDEX('Prepayment Engine'!$A$2:$AN$481,MIN(A71*12,$H$6),MATCH($H$13,'Prepayment Engine'!$A$1:$AN$1,0)+4)),"") -> 439587.86 | F71: =IF((A71-1)*12<$H$6,SUM(INDEX('Prepayment Engine'!$A$2:$AN$481,(A71-1)*12+1,MATCH($H$13,'Prepayment Engine'!$A$1:$AN$1,0)+5):INDEX('Prepayment Engine'!$A$2:$AN$481,MIN(A71*12,$H$6),MATCH($H$13,'Prepayment Engine'!$A$1:$AN$1,0)+5)),"") -> 369935.93 | G71: =IF((A71-1)*12<$H$6,SUM(INDEX('Prepayment Engine'!$A$2:$AN$481,(A71-1)*12+1,MATCH($H$13,'Prepayment Engine'!$A$1:$AN$1,0)+6):INDEX('Prepayment Engine'!$A$2:$AN$481,MIN(A71*12,$H$6),MATCH($H$13,'Prepayment Engine'!$A$1:$AN$1,0)+6)),"") -> 0 | H71: {=IF((A71-1)*12<$H$6,INDEX('Prepayment Engine'!$A$2:$AN$481,MIN(A71*12,$H$6),MATCH($H$13,'Prepayment Engine'!$A$1:$AN$1,0)+7),"")} -> 6560523.8
A72: =A71+1 -> 8 | B72: {=IF((A72-1)*12<$H$6,INDEX('Prepayment Engine'!$A$2:$AN$481,(A72-1)*12+1,MATCH($H$13,'Prepayment Engine'!$A$1:$AN$1,0)+1),"")} -> 6560523.8 | C72: {=IF((A72-1)*12<$H$6,INDEX('Prepayment Engine'!$A$2:$AN$481,MIN(A72*12,$H$6),MATCH($H$13,'Prepayment Engine'!$A$1:$AN$1,0)+2),"")} -> 6.5 | D72: =IF((A72-1)*12<$H$6,SUM(INDEX('Prepayment Engine'!$A$2:$AN$481,(A72-1)*12+1,MATCH($H$13,'Prepayment Engine'!$A$1:$AN$1,0)+3):INDEX('Prepayment Engine'!$A$2:$AN$481,MIN(A72*12,$H$6),MATCH($H$13,'Prepayment Engine'!$A$1:$AN$1,0)+3)),"") -> 809523.8 | E72: =IF((A72-1)*12<$H$6,SUM(INDEX('Prepayment Engine'!$A$2:$AN$481,(A72-1)*12+1,MATCH($H$13,'Prepayment Engine'!$A$1:$AN$1,0)+4):INDEX('Prepayment Engine'!$A$2:$AN$481,MIN(A72*12,$H$6),MATCH($H$13,'Prepayment Engine'!$A$1:$AN$1,0)+4)),"") -> 414812.57 | F72: =IF((A72-1)*12<$H$6,SUM(INDEX('Prepayment Engine'!$A$2:$AN$481,(A72-1)*12+1,MATCH($H$13,'Prepayment Engine'!$A$1:$AN$1,0)+5):INDEX('Prepayment Engine'!$A$2:$AN$481,MIN(A72*12,$H$6),MATCH($H$13,'Prepayment Engine'!$A$1:$AN$1,0)+5)),"") -> 394711.23 | G72: =IF((A72-1)*12<$H$6,SUM(INDEX('Prepayment Engine'!$A$2:$AN$481,(A72-1)*12+1,MATCH($H$13,'Prepayment Engine'!$A$1:$AN$1,0)+6):INDEX('Prepayment Engine'!$A$2:$AN$481,MIN(A72*12,$H$6),MATCH($H$13,'Prepayment Engine'!$A$1:$AN$1,0)+6)),"") -> 0 | H72: {=IF((A72-1)*12<$H$6,INDEX('Prepayment Engine'!$A$2:$AN$481,MIN(A72*12,$H$6),MATCH($H$13,'Prepayment Engine'!$A$1:$AN$1,0)+7),"")} -> 6165812.6
A73: =A72+1 -> 9 | B73: {=IF((A73-1)*12<$H$6,INDEX('Prepayment Engine'!$A$2:$AN$481,(A73-1)*12+1,MATCH($H$13,'Prepayment Engine'!$A$1:$AN$1,0)+1),"")} -> 6165812.6 | C73: {=IF((A73-1)*12<$H$6,INDEX('Prepayment Engine'!$A$2:$AN$481,MIN(A73*12,$H$6),MATCH($H$13,'Prepayment Engine'!$A$1:$AN$1,0)+2),"")} -> 6.5 | D73: =IF((A73-1)*12<$H$6,SUM(INDEX('Prepayment Engine'!$A$2:$AN$481,(A73-1)*12+1,MATCH($H$13,'Prepayment Engine'!$A$1:$AN$1,0)+3):INDEX('Prepayment Engine'!$A$2:$AN$481,MIN(A73*12,$H$6),MATCH($H$13,'Prepayment Engine'!$A$1:$AN$1,0)+3)),"") -> 809523.8 | E73: =IF((A73-1)*12<$H$6,SUM(INDEX('Prepayment Engine'!$A$2:$AN$481,(A73-1)*12+1,MATCH($H$13,'Prepayment Engine'!$A$1:$AN$1,0)+4):INDEX('Prepayment Engine'!$A$2:$AN$481,MIN(A73*12,$H$6),MATCH($H$13,'Prepayment Engine'!$A$1:$AN$1,0)+4)),"") -> 388378.03 | F73: =IF((A73-1)*12<$H$6,SUM(INDEX('Prepayment Engine'!$A$2:$AN$481,(A73-1)*12+1,MATCH($H$13,'Prepayment Engine'!$A$1:$AN$1,0)+5):INDEX('Prepayment Engine'!$A$2:$AN$481,MIN(A73*12,$H$6),MATCH($H$13,'Prepayment Engine'!$A$1:$AN$1,0)+5)),"") -> 421145.77 | G73: =IF((A73-1)*12<$H$6,SUM(INDEX('Prepayment Engine'!$A$2:$AN$481,(A73-1)*12+1,MATCH($H$13,'Prepayment Engine'!$A$1:$AN$1,0)+6):INDEX('Prepayment Engine'!$A$2:$AN$481,MIN(A73*12,$H$6),MATCH($H$13,'Prepayment Engine'!$A$1:$AN$1,0)+6)),"") -> 0 | H73: {=IF((A73-1)*12<$H$6,INDEX('Prepayment Engine'!$A$2:$AN$481,MIN(A73*12,$H$6),MATCH($H$13,'Prepayment Engine'!$A$1:$AN$1,0)+7),"")} -> 5744666.8
A74: =A73+1 -> 10 | B74: {=IF((A74-1)*12<$H$6,INDEX('Prepayment Engine'!$A$2:$AN$481,(A74-1)*12+1,MATCH($H$13,'Prepayment Engine'!$A$1:$AN$1,0)+1),"")} -> 5744666.8 | C74: {=IF((A74-1)*12<$H$6,INDEX('Prepayment Engine'!$A$2:$AN$481,MIN(A74*12,$H$6),MATCH($H$13,'Prepayment Engine'!$A$1:$AN$1,0)+2),"")} -> 6.5 | D74: =IF((A74-1)*12<$H$6,SUM(INDEX('Prepayment Engine'!$A$2:$AN$481,(A74-1)*12+1,MATCH($H$13,'Prepayment Engine'!$A$1:$AN$1,0)+3):INDEX('Prepayment Engine'!$A$2:$AN$481,MIN(A74*12,$H$6),MATCH($H$13,'Prepayment Engine'!$A$1:$AN$1,0)+3)),"") -> 809523.8 | E74: =IF((A74-1)*12<$H$6,SUM(INDEX('Prepayment Engine'!$A$2:$AN$481,(A74-1)*12+1,MATCH($H$13,'Prepayment Engine'!$A$1:$AN$1,0)+4):INDEX('Prepayment Engine'!$A$2:$AN$481,MIN(A74*12,$H$6),MATCH($H$13,'Prepayment Engine'!$A$1:$AN$1,0)+4)),"") -> 360173.11 | F74: =IF((A74-1)*12<$H$6,SUM(INDEX('Prepayment Engine'!$A$2:$AN$481,(A74-1)*12+1,MATCH($H$13,'Prepayment Engine'!$A$1:$AN$1,0)+5):INDEX('Prepayment Engine'!$A$2:$AN$481,MIN(A74*12,$H$6),MATCH($H$13,'Prepayment Engine'!$A$1:$AN$1,0)+5)),"") -> 449350.68 | G74: =IF((A74-1)*12<$H$6,SUM(INDEX('Prepayment Engine'!$A$2:$AN$481,(A74-1)*12+1,MATCH($H$13,'Prepayment Engine'!$A$1:$AN$1,0)+6):INDEX('Prepayment Engine'!$A$2:$AN$481,MIN(A74*12,$H$6),MATCH($H$13,'Prepayment Engine'!$A$1:$AN$1,0)+6)),"") -> 0 | H74: {=IF((A74-1)*12<$H$6,INDEX('Prepayment Engine'!$A$2:$AN$481,MIN(A74*12,$H$6),MATCH($H$13,'Prepayment Engine'!$A$1:$AN$1,0)+7),"")} -> 5295316.2
A75: =A74+1 -> 11 | B75: {=IF((A75-1)*12<$H$6,INDEX('Prepayment Engine'!$A$2:$AN$481,(A75-1)*12+1,MATCH($H$13,'Prepayment Engine'!$A$1:$AN$1,0)+1),"")} -> 5295316.2 | C75: {=IF((A75-1)*12<$H$6,INDEX('Prepayment Engine'!$A$2:$AN$481,MIN(A75*12,$H$6),MATCH($H$13,'Prepayment Engine'!$A$1:$AN$1,0)+2),"")} -> 6.5 | D75: =IF((A75-1)*12<$H$6,SUM(INDEX('Prepayment Engine'!$A$2:$AN$481,(A75-1)*12+1,MATCH($H$13,'Prepayment Engine'!$A$1:$AN$1,0)+3):INDEX('Prepayment Engine'!$A$2:$AN$481,MIN(A75*12,$H$6),MATCH($H$13,'Prepayment Engine'!$A$1:$AN$1,0)+3)),"") -> 809523.8 | E75: =IF((A75-1)*12<$H$6,SUM(INDEX('Prepayment Engine'!$A$2:$AN$481,(A75-1)*12+1,MATCH($H$13,'Prepayment Engine'!$A$1:$AN$1,0)+4):INDEX('Prepayment Engine'!$A$2:$AN$481,MIN(A75*12,$H$6),MATCH($H$13,'Prepayment Engine'!$A$1:$AN$1,0)+4)),"") -> 330079.27 | F75: =IF((A75-1)*12<$H$6,SUM(INDEX('Prepayment Engine'!$A$2:$AN$481,(A75-1)*12+1,MATCH($H$13,'Prepayment Engine'!$A$1:$AN$1,0)+5):INDEX('Prepayment Engine'!$A$2:$AN$481,MIN(A75*12,$H$6),MATCH($H$13,'Prepayment Engine'!$A$1:$AN$1,0)+5)),"") -> 479444.53 | G75: =IF((A75-1)*12<$H$6,SUM(INDEX('Prepayment Engine'!$A$2:$AN$481,(A75-1)*12+1,MATCH($H$13,'Prepayment Engine'!$A$1:$AN$1,0)+6):INDEX('Prepayment Engine'!$A$2:$AN$481,MIN(A75*12,$H$6),MATCH($H$13,'Prepayment Engine'!$A$1:$AN$1,0)+6)),"") -> 0 | H75: {=IF((A75-1)*12<$H$6,INDEX('Prepayment Engine'!$A$2:$AN$481,MIN(A75*12,$H$6),MATCH($H$13,'Prepayment Engine'!$A$1:$AN$1,0)+7),"")} -> 4815871.6
A76: =A75+1 -> 12 | B76: {=IF((A76-1)*12<$H$6,INDEX('Prepayment Engine'!$A$2:$AN$481,(A76-1)*12+1,MATCH($H$13,'Prepayment Engine'!$A$1:$AN$1,0)+1),"")} -> 4815871.6 | C76: {=IF((A76-1)*12<$H$6,INDEX('Prepayment Engine'!$A$2:$AN$481,MIN(A76*12,$H$6),MATCH($H$13,'Prepayment Engine'!$A$1:$AN$1,0)+2),"")} -> 6.5 | D76: =IF((A76-1)*12<$H$6,SUM(INDEX('Prepayment Engine'!$A$2:$AN$481,(A76-1)*12+1,MATCH($H$13,'Prepayment Engine'!$A$1:$AN$1,0)+3):INDEX('Prepayment Engine'!$A$2:$AN$481,MIN(A76*12,$H$6),MATCH($H$13,'Prepayment Engine'!$A$1:$AN$1,0)+3)),"") -> 809523.8 | E76: =IF((A76-1)*12<$H$6,SUM(INDEX('Prepayment Engine'!$A$2:$AN$481,(A76-1)*12+1,MATCH($H$13,'Prepayment Engine'!$A$1:$AN$1,0)+4):INDEX('Prepayment Engine'!$A$2:$AN$481,MIN(A76*12,$H$6),MATCH($H$13,'Prepayment Engine'!$A$1:$AN$1,0)+4)),"") -> 297969.98 | F76: =IF((A76-1)*12<$H$6,SUM(INDEX('Prepayment Engine'!$A$2:$AN$481,(A76-1)*12+1,MATCH($H$13,'Prepayment Engine'!$A$1:$AN$1,0)+5):INDEX('Prepayment Engine'!$A$2:$AN$481,MIN(A76*12,$H$6),MATCH($H$13,'Prepayment Engine'!$A$1:$AN$1,0)+5)),"") -> 511553.82 | G76: =IF((A76-1)*12<$H$6,SUM(INDEX('Prepayment Engine'!$A$2:$AN$481,(A76-1)*12+1,MATCH($H$13,'Prepayment Engine'!$A$1:$AN$1,0)+6):INDEX('Prepayment Engine'!$A$2:$AN$481,MIN(A76*12,$H$6),MATCH($H$13,'Prepayment Engine'!$A$1:$AN$1,0)+6)),"") -> 0 | H76: {=IF((A76-1)*12<$H$6,INDEX('Prepayment Engine'!$A$2:$AN$481,MIN(A76*12,$H$6),MATCH($H$13,'Prepayment Engine'!$A$1:$AN$1,0)+7),"")} -> 4304317.8
A77: =A76+1 -> 13 | B77: {=IF((A77-1)*12<$H$6,INDEX('Prepayment Engine'!$A$2:$AN$481,(A77-1)*12+1,MATCH($H$13,'Prepayment Engine'!$A$1:$AN$1,0)+1),"")} -> 4304317.8 | C77: {=IF((A77-1)*12<$H$6,INDEX('Prepayment Engine'!$A$2:$AN$481,MIN(A77*12,$H$6),MATCH($H$13,'Prepayment Engine'!$A$1:$AN$1,0)+2),"")} -> 6.5 | D77: =IF((A77-1)*12<$H$6,SUM(INDEX('Prepayment Engine'!$A$2:$AN$481,(A77-1)*12+1,MATCH($H$13,'Prepayment Engine'!$A$1:$AN$1,0)+3):INDEX('Prepayment Engine'!$A$2:$AN$481,MIN(A77*12,$H$6),MATCH($H$13,'Prepayment Engine'!$A$1:$AN$1,0)+3)),"") -> 809523.8 | E77: =IF((A77-1)*12<$H$6,SUM(INDEX('Prepayment Engine'!$A$2:$AN$481,(A77-1)*12+1,MATCH($H$13,'Prepayment Engine'!$A$1:$AN$1,0)+4):INDEX('Prepayment Engine'!$A$2:$AN$481,MIN(A77*12,$H$6),MATCH($H$13,'Prepayment Engine'!$A$1:$AN$1,0)+4)),"") -> 263710.27 | F77: =IF((A77-1)*12<$H$6,SUM(INDEX('Prepayment Engine'!$A$2:$AN$481,(A77-1)*12+1,MATCH($H$13,'Prepayment Engine'!$A$1:$AN$1,0)+5):INDEX('Prepayment Engine'!$A$2:$AN$481,MIN(A77*12,$H$6),MATCH($H$13,'Prepayment Engine'!$A$1:$AN$1,0)+5)),"") -> 545813.53 | G77: =IF((A77-1)*12<$H$6,SUM(INDEX('Prepayment Engine'!$A$2:$AN$481,(A77-1)*12+1,MATCH($H$13,'Prepayment Engine'!$A$1:$AN$1,0)+6):INDEX('Prepayment Engine'!$A$2:$AN$481,MIN(A77*12,$H$6),MATCH($H$13,'Prepayment Engine'!$A$1:$AN$1,0)+6)),"") -> 0 | H77: {=IF((A77-1)*12<$H$6,INDEX('Prepayment Engine'!$A$2:$AN$481,MIN(A77*12,$H$6),MATCH($H$13,'Prepayment Engine'!$A$1:$AN$1,0)+7),"")} -> 3758504.3
... A104: =A103+1 -> 40 | B104: {=IF((A104-1)*12<$H$6,INDEX('Prepayment Engine'!$A$2:$AN$481,(A104-1)*12+1,MATCH($H$13,'Prepayment Engine'!$A$1:$AN$1,0)+1),"")} | C104: {=IF((A104-1)*12<$H$6,INDEX('Prepayment Engine'!$A$2:$AN$481,MIN(A104*12,$H$6),MATCH($H$13,'Prepayment Engine'!$A$1:$AN$1,0)+2),"")} | D104: =IF((A104-1)*12<$H$6,SUM(INDEX('Prepayment Engine'!$A$2:$AN$481,(A104-1)*12+1,MATCH($H$13,'Prepayment Engine'!$A$1:$AN$1,0)+3):INDEX('Prepayment Engine'!$A$2:$AN$481,MIN(A104*12,$H$6),MATCH($H$13,'Prepayment Engine'!$A$1:$AN$1,0)+3)),"") | E104: =IF((A104-1)*12<$H$6,SUM(INDEX('Prepayment Engine'!$A$2:$AN$481,(A104-1)*12+1,MATCH($H$13,'Prepayment Engine'!$A$1:$AN$1,0)+4):INDEX('Prepayment Engine'!$A$2:$AN$481,MIN(A104*12,$H$6),MATCH($H$13,'Prepayment Engine'!$A$1:$AN$1,0)+4)),"") | F104: =IF((A104-1)*12<$H$6,SUM(INDEX('Prepayment Engine'!$A$2:$AN$481,(A104-1)*12+1,MATCH($H$13,'Prepayment Engine'!$A$1:$AN$1,0)+5):INDEX('Prepayment Engine'!$A$2:$AN$481,MIN(A104*12,$H$6),MATCH($H$13,'Prepayment Engine'!$A$1:$AN$1,0)+5)),"") | G104: =IF((A104-1)*12<$H$6,SUM(INDEX('Prepayment Engine'!$A$2:$AN$481,(A104-1)*12+1,MATCH($H$13,'Prepayment Engine'!$A$1:$AN$1,0)+6):INDEX('Prepayment Engine'!$A$2:$AN$481,MIN(A104*12,$H$6),MATCH($H$13,'Prepayment Engine'!$A$1:$AN$1,0)+6)),"") | H104: {=IF((A104-1)*12<$H$6,INDEX('Prepayment Engine'!$A$2:$AN$481,MIN(A104*12,$H$6),MATCH($H$13,'Prepayment Engine'!$A$1:$AN$1,0)+7),"")}

Sheet Prepayment Engine
A1: Normal Loan | B1: Opening Balance | C1: Rate % | D1: Scheduled EMI | E1: Interest | F1: Principal | G1: Prepayment | H1: Closing Balance | I1: Multiple Lump Sums | J1: Opening Balance | K1: Rate % | L1: Scheduled EMI | M1: Interest | N1: Principal | O1: Prepayment | P1: Closing Balance | Q1: Monthly Extra Payment | R1: Opening Balance | S1: Rate % | T1: Scheduled EMI | U1: Interest | V1: Principal | W1: Prepayment | X1: Closing Balance | Y1: Mid-Term Rate Change | Z1: Opening Balance | AA1: Rate % | AB1: Scheduled EMI | AC1: Interest | AD1: Principal | AE1: Prepayment | AF1: Closing Balance | AG1: Combination of All | AH1: Opening Balance | AI1: Rate % | AJ1: Scheduled EMI | AK1: Interest | AL1: Principal | AM1: Prepayment | AN1: Closing Balance
A2: 1 | B2: ='Loan Prepayment'!$B$5 -> 10000000 | C2: ='Loan Prepayment'!$B$6 -> 7.5 | D2: =IF(B2<=0,0,MIN(-PMT('Loan Prepayment'!$B$6/1200,'Loan Prepayment'!$B$7*12,'Loan Prepayment'!$B$5),B2+E2)) -> 80559.319 | E2: =IF(B2<=0,0,B2*C2/1200) -> 62500 | F2: =MAX(0,D2-E2) -> 18059.319 | G2: 0 | H2: =MAX(0,B2-F2-G2) -> 9981940.7 | I2: 1 | J2: ='Loan Prepayment'!$B$5 -> 10000000 | K2: ='Loan Prepayment'!$B$6 -> 7.5 | L2: =IF(J2<=0,0,MIN(-PMT(K2/1200,'Loan Prepayment'!$B$7*12,J2),J2+M2)) -> 80559.319 | M2: =IF(J2<=0,0,J2*K2/1200) -> 62500 | N2: =MAX(0,L2-M2) -> 18059.319 | O2: =IF(J2<=0,0,MIN(MAX(0,J2-N2),SUMIFS('Loan Prepayment'!$B$12:$B$31,'Loan Prepayment'!$A$12:$A$31,I2)+0)) -> 0 | P2: =MAX(0,J2-N2-O2) -> 9981940.7 | Q2: 1 | R2: ='Loan Prepayment'!$B$5 -> 10000000 | S2: ='Loan Prepayment'!$B$6 -> 7.5 | T2: =IF(R2<=0,0,MIN(-PMT(S2/1200,'Loan Prepayment'!$B$7*12,R2),R2+U2)) -> 80559.319 | U2: =IF(R2<=0,0,R2*S2/1200) -> 62500 | V2: =MAX(0,T2-U2) -> 18059.319 | W2: =IF(R2<=0,0,MIN(MAX(0,R2-V2),0+IF(AND(Q2>='Loan Prepayment'!$B$9,Q2<='Loan Prepayment'!$E$16),'Loan Prepayment'!$B$8,0))) -> 0 | X2: =MAX(0,R2-V2-W2) -> 9981940.7 | Y2: 1 | Z2: ='Loan Prepayment'!$B$5 -> 10000000 | AA2: =IF(Y2>='Loan Prepayment'!$E$11,'Loan Prepayment'!$E$12,'Loan Prepayment'!$B$6) -> 7.5 | AB2: =IF(Z2<=0,0,MIN(-PMT(AA2/1200,'Loan Prepayment'!$B$7*12,Z2),Z2+AC2)) -> 80559.319 | AC2: =IF(Z2<=0,0,Z2*AA2/1200) -> 62500 | AD2: =MAX(0,AB2-AC2) -> 18059.319 | AE2: =IF(Z2<=0,0,MIN(MAX(0,Z2-AD2),0)) -> 0 | AF2: =MAX(0,Z2-AD2-AE2) -> 9981940.7 | AG2: 1 | AH2: ='Loan Prepayment'!$B$5 -> 10000000 | AI2: =IF(AG2>='Loan Prepayment'!$E$11,'Loan Prepayment'!$E$12,'Loan Prepayment'!$B$6) -> 7.5 | AJ2: =IF(AH2<=0,0,MIN(-PMT(AI2/1200,'Loan Prepayment'!$B$7*12,AH2),AH2+AK2)) -> 80559.319 | AK2: =IF(AH2<=0,0,AH2*AI2/1200) -> 62500 | AL2: =MAX(0,AJ2-AK2) -> 18059.319 | AM2: =IF(AH2<=0,0,MIN(MAX(0,AH2-AL2),SUMIFS('Loan Prepayment'!$B$12:$B$31,'Loan Prepayment'!$A$12:$A$31,AG2)+IF(AND(AG2>='Loan Prepayment'!$B$9,AG2<='Loan Prepayment'!$E$16),'Loan Prepayment'!$B$8,0))) -> 0 | AN2: =MAX(0,AH2-AL2-AM2) -> 9981940.7
A3: 2 | B3: =H2 -> 9981940.7 | C3: ='Loan Prepayment'!$B$6 -> 7.5 | D3: =IF(B3<=0,0,MIN(-PMT('Loan Prepayment'!$B$6/1200,'Loan Prepayment'!$B$7*12,'Loan Prepayment'!$B$5),B3+E3)) -> 80559.319 | E3: =IF(B3<=0,0,B3*C3/1200) -> 62387.129 | F3: =MAX(0,D3-E3) -> 18172.19 | G3: 0 | H3: =MAX(0,B3-F3-G3) -> 9963768.5 | I3: 2 | J3: =P2 -> 9981940.7 | K3: ='Loan Prepayment'!$B$6 -> 7.5 | L3: =IF(J3<=0,0,MIN(IF(AND('Loan Prepayment'!$E$15="Reduce EMI",O2>0),-PMT(K3/1200,MAX(1,'Loan Prepayment'!$B$7*12-I3+1),J3),L2),J3+M3)) -> 80559.319 | M3: =IF(J3<=0,0,J3*K3/1200) -> 62387.129 | N3: =MAX(0,L3-M3) -> 18172.19 | O3: =IF(J3<=0,0,MIN(MAX(0,J3-N3),SUMIFS('Loan Prepayment'!$B$12:$B$31,'Loan Prepayment'!$A$12:$A$31,I3)+0)) -> 0 | P3: =MAX(0,J3-N3-O3) -> 9963768.5 | Q3: 2 | R3: =X2 -> 9981940.7 | S3: ='Loan Prepayment'!$B$6 -> 7.5 | T3: =IF(R3<=0,0,MIN(IF(AND('Loan Prepayment'!$E$15="Reduce EMI",W2>0),-PMT(S3/1200,MAX(1,'Loan Prepayment'!$B$7*12-Q3+1),R3),T2),R3+U3)) -> 80559.319 | U3: =IF(R3<=0,0,R3*S3/1200) -> 62387.129 | V3: =MAX(0,T3-U3) -> 18172.19 | W3: =IF(R3<=0,0,MIN(MAX(0,R3-V3),0+IF(AND(Q3>='Loan Prepayment'!$B$9,Q3<='Loan Prepayment'!$E$16),'Loan Prepayment'!$B$8,0))) -> 0 | X3: =MAX(0,R3-V3-W3) -> 9963768.5 | Y3: 2 | Z3: =AF2 -> 9981940.7 | AA3: =IF(Y3>='Loan Prepayment'!$E$11,'Loan Prepayment'!$E$12,'Loan Prepayment'!$B$6) -> 7.5 | AB3: =IF(Z3<=0,0,MIN(IF(Y3='Loan Prepayment'!$E$11,IF('Loan Prepayment'!$E$13="Keep tenure, recalculate EMI",-PMT(AA3/1200,MAX(1,'Loan Prepayment'!$B$7*12-Y3+1),Z3),AB2),AB2),Z3+AC3)) -> 80559.319 | AC3: =IF(Z3<=0,0,Z3*AA3/1200) -> 62387.129 | AD3: =MAX(0,AB3-AC3) -> 18172.19 | AE3: =IF(Z3<=0,0,MIN(MAX(0,Z3-AD3),0)) -> 0 | AF3: =MAX(0,Z3-AD3-AE3) -> 9963768.5 | AG3: 2 | AH3: =AN2 -> 9981940.7 | AI3: =IF(AG3>='Loan Prepayment'!$E$11,'Loan Prepayment'!$E$12,'Loan Prepayment'!$B$6) -> 7.5 | AJ3: =IF(AH3<=0,0,MIN(IF(AG3='Loan Prepayment'!$E$11,IF('Loan Prepayment'!$E$13="Keep tenure, recalculate EMI",-PMT(AI3/1200,MAX(1,'Loan Prepayment'!$B$7*12-AG3+1),AH3),IF(AND('Loan Prepayment'!$E$15="Reduce EMI",AM2>0),-PMT(AI2/1200,MAX(1,'Loan Prepayment'!$B$7*12-AG3+1),AH3),AJ2)),IF(AND('Loan Prepayment'!$E$15="Reduce EMI",AM2>0),-PMT(AI3/1200,MAX(1,'Loan Prepayment'!$B$7*12-AG3+1),AH3),AJ2)),AH3+AK3)) -> 80559.319 | AK3: =IF(AH3<=0,0,AH3*AI3/1200) -> 62387.129 | AL3: =MAX(0,AJ3-AK3) -> 18172.19 | AM3: =IF(AH3<=0,0,MIN(MAX(0,AH3-AL3),SUMIFS('Loan Prepayment'!$B$12:$B$31,'Loan Prepayment'!$A$12:$A$31,AG3)+IF(AND(AG3>='Loan Prepayment'!$B$9,AG3<='Loan Prepayment'!$E$16),'Loan Prepayment'!$B$8,0))) -> 0 | AN3: =MAX(0,AH3-AL3-AM3) -> 9963768.5
A4: 3 | B4: =H3 -> 9963768.5 | C4: ='Loan Prepayment'!$B$6 -> 7.5 | D4: =IF(B4<=0,0,MIN(-PMT('Loan Prepayment'!$B$6/1200,'Loan Prepayment'!$B$7*12,'Loan Prepayment'!$B$5),B4+E4)) -> 80559.319 | E4: =IF(B4<=0,0,B4*C4/1200) -> 62273.553 | F4: =MAX(0,D4-E4) -> 18285.766 | G4: 0 | H4: =MAX(0,B4-F4-G4) -> 9945482.7 | I4: 3 | J4: =P3 -> 9963768.5 | K4: ='Loan Prepayment'!$B$6 -> 7.5 | L4: =IF(J4<=0,0,MIN(IF(AND('Loan Prepayment'!$E$15="Reduce EMI",O3>0),-PMT(K4/1200,MAX(1,'Loan Prepayment'!$B$7*12-I4+1),J4),L3),J4+M4)) -> 80559.319 | M4: =IF(J4<=0,0,J4*K4/1200) -> 62273.553 | N4: =MAX(0,L4-M4) -> 18285.766 | O4: =IF(J4<=0,0,MIN(MAX(0,J4-N4),SUMIFS('Loan Prepayment'!$B$12:$B$31,'Loan Prepayment'!$A$12:$A$31,I4)+0)) -> 0 | P4: =MAX(0,J4-N4-O4) -> 9945482.7 | Q4: 3 | R4: =X3 -> 9963768.5 | S4: ='Loan Prepayment'!$B$6 -> 7.5 | T4: =IF(R4<=0,0,MIN(IF(AND('Loan Prepayment'!$E$15="Reduce EMI",W3>0),-PMT(S4/1200,MAX(1,'Loan Prepayment'!$B$7*12-Q4+1),R4),T3),R4+U4)) -> 80559.319 | U4: =IF(R4<=0,0,R4*S4/1200) -> 62273.553 | V4: =MAX(0,T4-U4) -> 18285.766 | W4: =IF(R4<=0,0,MIN(MAX(0,R4-V4),0+IF(AND(Q4>='Loan Prepayment'!$B$9,Q4<='Loan Prepayment'!$E$16),'Loan Prepayment'!$B$8,0))) -> 0 | X4: =MAX(0,R4-V4-W4) -> 9945482.7 | Y4: 3 | Z4: =AF3 -> 9963768.5 | AA4: =IF(Y4>='Loan Prepayment'!$E$11,'Loan Prepayment'!$E$12,'Loan Prepayment'!$B$6) -> 7.5 | AB4: =IF(Z4<=0,0,MIN(IF(Y4='Loan Prepayment'!$E$11,IF('Loan Prepayment'!$E$13="Keep tenure, recalculate EMI",-PMT(AA4/1200,MAX(1,'Loan Prepayment'!$B$7*12-Y4+1),Z4),AB3),AB3),Z4+AC4)) -> 80559.319 | AC4: =IF(Z4<=0,0,Z4*AA4/1200) -> 62273.553 | AD4: =MAX(0,AB4-AC4) -> 18285.766 | AE4: =IF(Z4<=0,0,MIN(MAX(0,Z4-AD4),0)) -> 0 | AF4: =MAX(0,Z4-AD4-AE4) -> 9945482.7 | AG4: 3 | AH4: =AN3 -> 9963768.5 | AI4: =IF(AG4>='Loan Prepayment'!$E$11,'Loan Prepayment'!$E$12,'Loan Prepayment'!$B$6) -> 7.5 | AJ4: =IF(AH4<=0,0,MIN(IF(AG4='Loan Prepayment'!$E$11,IF('Loan Prepayment'!$E$13="Keep tenure, recalculate EMI",-PMT(AI4/1200,MAX(1,'Loan Prepayment'!$B$7*12-AG4+1),AH4),IF(AND('Loan Prepayment'!$E$15="Reduce EMI",AM3>0),-PMT(AI3/1200,MAX(1,'Loan Prepayment'!$B$7*12-AG4+1),AH4),AJ3)),IF(AND('Loan Prepayment'!$E$15="Reduce EMI",AM3>0),-PMT(AI4/1200,MAX(1,'Loan Prepayment'!$B$7*12-AG4+1),AH4),AJ3)),AH4+AK4)) -> 80559.319 | AK4: =IF(AH4<=0,0,AH4*AI4/1200) -> 62273.553 | AL4: =MAX(0,AJ4-AK4) -> 18285.766 | AM4: =IF(AH4<=0,0,MIN(MAX(0,AH4-AL4),SUMIFS('Loan Prepayment'!$B$12:$B$31,'Loan Prepayment'!$A$12:$A$31,AG4)+IF(AND(AG4>='Loan Prepayment'!$B$9,AG4<='Loan Prepayment'!$E$16),'Loan Prepayment'!$B$8,0))) -> 0 | AN4: =MAX(0,AH4-AL4-AM4) -> 9945482.7
A5: 4 | B5: =H4 -> 9945482.7 | C5: ='Loan Prepayment'!$B$6 -> 7.5 | D5: =IF(B5<=0,0,MIN(-PMT('Loan Prepayment'!$B$6/1200,'Loan Prepayment'!$B$7*12,'Loan Prepayment'!$B$5),B5+E5)) -> 80559.319 | E5: =IF(B5<=0,0,B5*C5/1200) -> 62159.267 | F5: =MAX(0,D5-E5) -> 18400.052 | G5: 0 | H5: =MAX(0,B5-F5-G5) -> 9927082.7 | I5: 4 | J5: =P4 -> 9945482.7 | K5: ='Loan Prepayment'!$B$6 -> 7.5 | L5: =IF(J5<=0,0,MIN(IF(AND('Loan Prepayment'!$E$15="Reduce EMI",O4>0),-PMT(K5/1200,MAX(1,'Loan Prepayment'!$B$7*12-I5+1),J5),L4),J5+M5)) -> 80559.319 | M5: =IF(J5<=0,0,J5*K5/1200) -> 62159.267 | N5: =MAX(0,L5-M5) -> 18400.052 | O5: =IF(J5<=0,0,MIN(MAX(0,J5-N5),SUMIFS('Loan Prepayment'!$B$12:$B$31,'Loan Prepayment'!$A$12:$A$31,I5)+0)) -> 0 | P5: =MAX(0,J5-N5-O5) -> 9927082.7 | Q5: 4 | R5: =X4 -> 9945482.7 | S5: ='Loan Prepayment'!$B$6 -> 7.5 | T5: =IF(R5<=0,0,MIN(IF(AND('Loan Prepayment'!$E$15="Reduce EMI",W4>0),-PMT(S5/1200,MAX(1,'Loan Prepayment'!$B$7*12-Q5+1),R5),T4),R5+U5)) -> 80559.319 | U5: =IF(R5<=0,0,R5*S5/1200) -> 62159.267 | V5: =MAX(0,T5-U5) -> 18400.052 | W5: =IF(R5<=0,0,MIN(MAX(0,R5-V5),0+IF(AND(Q5>='Loan Prepayment'!$B$9,Q5<='Loan Prepayment'!$E$16),'Loan Prepayment'!$B$8,0))) -> 0 | X5: =MAX(0,R5-V5-W5) -> 9927082.7 | Y5: 4 | Z5: =AF4 -> 9945482.7 | AA5: =IF(Y5>='Loan Prepayment'!$E$11,'Loan Prepayment'!$E$12,'Loan Prepayment'!$B$6) -> 7.5 | AB5: =IF(Z5<=0,0,MIN(IF(Y5='Loan Prepayment'!$E$11,IF('Loan Prepayment'!$E$13="Keep tenure, recalculate EMI",-PMT(AA5/1200,MAX(1,'Loan Prepayment'!$B$7*12-Y5+1),Z5),AB4),AB4),Z5+AC5)) -> 80559.319 | AC5: =IF(Z5<=0,0,Z5*AA5/1200) -> 62159.267 | AD5: =MAX(0,AB5-AC5) -> 18400.052 | AE5: =IF(Z5<=0,0,MIN(MAX(0,Z5-AD5),0)) -> 0 | AF5: =MAX(0,Z5-AD5-AE5) -> 9927082.7 | AG5: 4 | AH5: =AN4 -> 9945482.7 | AI5: =IF(AG5>='Loan Prepayment'!$E$11,'Loan Prepayment'!$E$12,'Loan Prepayment'!$B$6) -> 7.5 | AJ5: =IF(AH5<=0,0,MIN(IF(AG5='Loan Prepayment'!$E$11,IF('Loan Prepayment'!$E$13="Keep tenure, recalculate EMI",-PMT(AI5/1200,MAX(1,'Loan Prepayment'!$B$7*12-AG5+1),AH5),IF(AND('Loan Prepayment'!$E$15="Reduce EMI",AM4>0),-PMT(AI4/1200,MAX(1,'Loan Prepayment'!$B$7*12-AG5+1),AH5),AJ4)),IF(AND('Loan Prepayment'!$E$15="Reduce EMI",AM4>0),-PMT(AI5/1200,MAX(1,'Loan Prepayment'!$B$7*12-AG5+1),AH5),AJ4)),AH5+AK5)) -> 80559.319 | AK5: =IF(AH5<=0,0,AH5*AI5/1200) -> 62159.267 | AL5: =MAX(0,AJ5-AK5) -> 18400.052 | AM5: =IF(AH5<=0,0,MIN(MAX(0,AH5-AL5),SUMIFS('Loan Prepayment'!$B$12:$B$31,'Loan Prepayment'!$A$12:$A$31,AG5)+IF(AND(AG5>='Loan Prepayment'!$B$9,AG5<='Loan Prepayment'!$E$16),'Loan Prepayment'!$B$8,0))) -> 0 | AN5: =MAX(0,AH5-AL5-AM5) -> 9927082.7
A6: 5 | B6: =H5 -> 9927082.7 | C6: ='Loan Prepayment'!$B$6 -> 7.5 | D6: =IF(B6<=0,0,MIN(-PMT('Loan Prepayment'!$B$6/1200,'Loan Prepayment'!$B$7*12,'Loan Prepayment'!$B$5),B6+E6)) -> 80559.319 | E6: =IF(B6<=0,0,B6*C6/1200) -> 62044.267 | F6: =MAX(0,D6-E6) -> 18515.053 | G6: 0 | H6: =MAX(0,B6-F6-G6) -> 9908567.6 | I6: 5 | J6: =P5 -> 9927082.7 | K6: ='Loan Prepayment'!$B$6 -> 7.5 | L6: =IF(J6<=0,0,MIN(IF(AND('Loan Prepayment'!$E$15="Reduce EMI",O5>0),-PMT(K6/1200,MAX(1,'Loan Prepayment'!$B$7*12-I6+1),J6),L5),J6+M6)) -> 80559.319 | M6: =IF(J6<=0,0,J6*K6/1200) -> 62044.267 | N6: =MAX(0,L6-M6) -> 18515.053 | O6: =IF(J6<=0,0,MIN(MAX(0,J6-N6),SUMIFS('Loan Prepayment'!$B$12:$B$31,'Loan Prepayment'!$A$12:$A$31,I6)+0)) -> 0 | P6: =MAX(0,J6-N6-O6) -> 9908567.6 | Q6: 5 | R6: =X5 -> 9927082.7 | S6: ='Loan Prepayment'!$B$6 -> 7.5 | T6: =IF(R6<=0,0,MIN(IF(AND('Loan Prepayment'!$E$15="Reduce EMI",W5>0),-PMT(S6/1200,MAX(1,'Loan Prepayment'!$B$7*12-Q6+1),R6),T5),R6+U6)) -> 80559.319 | U6: =IF(R6<=0,0,R6*S6/1200) -> 62044.267 | V6: =MAX(0,T6-U6) -> 18515.053 | W6: =IF(R6<=0,0,MIN(MAX(0,R6-V6),0+IF(AND(Q6>='Loan Prepayment'!$B$9,Q6<='Loan Prepayment'!$E$16),'Loan Prepayment'!$B$8,0))) -> 0 | X6: =MAX(0,R6-V6-W6) -> 9908567.6 | Y6: 5 | Z6: =AF5 -> 9927082.7 | AA6: =IF(Y6>='Loan Prepayment'!$E$11,'Loan Prepayment'!$E$12,'Loan Prepayment'!$B$6) -> 7.5 | AB6: =IF(Z6<=0,0,MIN(IF(Y6='Loan Prepayment'!$E$11,IF('Loan Prepayment'!$E$13="Keep tenure, recalculate EMI",-PMT(AA6/1200,MAX(1,'Loan Prepayment'!$B$7*12-Y6+1),Z6),AB5),AB5),Z6+AC6)) -> 80559.319 | AC6: =IF(Z6<=0,0,Z6*AA6/1200) -> 62044.267 | AD6: =MAX(0,AB6-AC6) -> 18515.053 | AE6: =IF(Z6<=0,0,MIN(MAX(0,Z6-AD6),0)) -> 0 | AF6: =MAX(0,Z6-AD6-AE6) -> 9908567.6 | AG6: 5 | AH6: =AN5 -> 9927082.7 | AI6: =IF(AG6>='Loan Prepayment'!$E$11,'Loan Prepayment'!$E$12,'Loan Prepayment'!$B$6) -> 7.5 | AJ6: =IF(AH6<=0,0,MIN(IF(AG6='Loan Prepayment'!$E$11,IF('Loan Prepayment'!$E$13="Keep tenure, recalculate EMI",-PMT(AI6/1200,MAX(1,'Loan Prepayment'!$B$7*12-AG6+1),AH6),IF(AND('Loan Prepayment'!$E$15="Reduce EMI",AM5>0),-PMT(AI5/1200,MAX(1,'Loan Prepayment'!$B$7*12-AG6+1),AH6),AJ5)),IF(AND('Loan Prepayment'!$E$15="Reduce EMI",AM5>0),-PMT(AI6/1200,MAX(1,'Loan Prepayment'!$B$7*12-AG6+1),AH6),AJ5)),AH6+AK6)) -> 80559.319 | AK6: =IF(AH6<=0,0,AH6*AI6/1200) -> 62044.267 | AL6: =MAX(0,AJ6-AK6) -> 18515.053 | AM6: =IF(AH6<=0,0,MIN(MAX(0,AH6-AL6),SUMIFS('Loan Prepayment'!$B$12:$B$31,'Loan Prepayment'!$A$12:$A$31,AG6)+IF(AND(AG6>='Loan Prepayment'!$B$9,AG6<='Loan Prepayment'!$E$16),'Loan Prepayment'!$B$8,0))) -> 0 | AN6: =MAX(0,AH6-AL6-AM6) -> 9908567.6
A7: 6 | B7: =H6 -> 9908567.6 | C7: ='Loan Prepayment'!$B$6 -> 7.5 | D7: =IF(B7<=0,0,MIN(-PMT('Loan Prepayment'!$B$6/1200,'Loan Prepayment'!$B$7*12,'Loan Prepayment'!$B$5),B7+E7)) -> 80559.319 | E7: =IF(B7<=0,0,B7*C7/1200) -> 61928.548 | F7: =MAX(0,D7-E7) -> 18630.772 | G7: 0 | H7: =MAX(0,B7-F7-G7) -> 9889936.8 | I7: 6 | J7: =P6 -> 9908567.6 | K7: ='Loan Prepayment'!$B$6 -> 7.5 | L7: =IF(J7<=0,0,MIN(IF(AND('Loan Prepayment'!$E$15="Reduce EMI",O6>0),-PMT(K7/1200,MAX(1,'Loan Prepayment'!$B$7*12-I7+1),J7),L6),J7+M7)) -> 80559.319 | M7: =IF(J7<=0,0,J7*K7/1200) -> 61928.548 | N7: =MAX(0,L7-M7) -> 18630.772 | O7: =IF(J7<=0,0,MIN(MAX(0,J7-N7),SUMIFS('Loan Prepayment'!$B$12:$B$31,'Loan Prepayment'!$A$12:$A$31,I7)+0)) -> 0 | P7: =MAX(0,J7-N7-O7) -> 9889936.8 | Q7: 6 | R7: =X6 -> 9908567.6 | S7: ='Loan Prepayment'!$B$6 -> 7.5 | T7: =IF(R7<=0,0,MIN(IF(AND('Loan Prepayment'!$E$15="Reduce EMI",W6>0),-PMT(S7/1200,MAX(1,'Loan Prepayment'!$B$7*12-Q7+1),R7),T6),R7+U7)) -> 80559.319 | U7: =IF(R7<=0,0,R7*S7/1200) -> 61928.548 | V7: =MAX(0,T7-U7) -> 18630.772 | W7: =IF(R7<=0,0,MIN(MAX(0,R7-V7),0+IF(AND(Q7>='Loan Prepayment'!$B$9,Q7<='Loan Prepayment'!$E$16),'Loan Prepayment'!$B$8,0))) -> 0 | X7: =MAX(0,R7-V7-W7) -> 9889936.8 | Y7: 6 | Z7: =AF6 -> 9908567.6 | AA7: =IF(Y7>='Loan Prepayment'!$E$11,'Loan Prepayment'!$E$12,'Loan Prepayment'!$B$6) -> 7.5 | AB7: =IF(Z7<=0,0,MIN(IF(Y7='Loan Prepayment'!$E$11,IF('Loan Prepayment'!$E$13="Keep tenure, recalculate EMI",-PMT(AA7/1200,MAX(1,'Loan Prepayment'!$B$7*12-Y7+1),Z7),AB6),AB6),Z7+AC7)) -> 80559.319 | AC7: =IF(Z7<=0,0,Z7*AA7/1200) -> 61928.548 | AD7: =MAX(0,AB7-AC7) -> 18630.772 | AE7: =IF(Z7<=0,0,MIN(MAX(0,Z7-AD7),0)) -> 0 | AF7: =MAX(0,Z7-AD7-AE7) -> 9889936.8 | AG7: 6 | AH7: =AN6 -> 9908567.6 | AI7: =IF(AG7>='Loan Prepayment'!$E$11,'Loan Prepayment'!$E$12,'Loan Prepayment'!$B$6) -> 7.5 | AJ7: =IF(AH7<=0,0,MIN(IF(AG7='Loan Prepayment'!$E$11,IF('Loan Prepayment'!$E$13="Keep tenure, recalculate EMI",-PMT(AI7/1200,MAX(1,'Loan Prepayment'!$B$7*12-AG7+1),AH7),IF(AND('Loan Prepayment'!$E$15="Reduce EMI",AM6>0),-PMT(AI6/1200,MAX(1,'Loan Prepayment'!$B$7*12-AG7+1),AH7),AJ6)),IF(AND('Loan Prepayment'!$E$15="Reduce EMI",AM6>0),-PMT(AI7/1200,MAX(1,'Loan Prepayment'!$B$7*12-AG7+1),AH7),AJ6)),AH7+AK7)) -> 80559.319 | AK7: =IF(AH7<=0,0,AH7*AI7/1200) -> 61928.548 | AL7: =MAX(0,AJ7-AK7) -> 18630.772 | AM7: =IF(AH7<=0,0,MIN(MAX(0,AH7-AL7),SUMIFS('Loan Prepayment'!$B$12:$B$31,'Loan Prepayment'!$A$12:$A$31,AG7)+IF(AND(AG7>='Loan Prepayment'!$B$9,AG7<='Loan Prepayment'!$E$16),'Loan Prepayment'!$B$8,0))) -> 0 | AN7: =MAX(0,AH7-AL7-AM7) -> 9889936.8
A8: 7 | B8: =H7 -> 9889936.8 | C8: ='Loan Prepayment'!$B$6 -> 7.5 | D8: =IF(B8<=0,0,MIN(-PMT('Loan Prepayment'!$B$6/1200,'Loan Prepayment'!$B$7*12,'Loan Prepayment'!$B$5),B8+E8)) -> 80559.319 | E8: =IF(B8<=0,0,B8*C8/1200) -> 61812.105 | F8: =MAX(0,D8-E8) -> 18747.214 | G8: 0 | H8: =MAX(0,B8-F8-G8) -> 9871189.6 | I8: 7 | J8: =P7 -> 9889936.8 | K8: ='Loan Prepayment'!$B$6 -> 7.5 | L8: =IF(J8<=0,0,MIN(IF(AND('Loan Prepayment'!$E$15="Reduce EMI",O7>0),-PMT(K8/1200,MAX(1,'Loan Prepayment'!$B$7*12-I8+1),J8),L7),J8+M8)) -> 80559.319 | M8: =IF(J8<=0,0,J8*K8/1200) -> 61812.105 | N8: =MAX(0,L8-M8) -> 18747.214 | O8: =IF(J8<=0,0,MIN(MAX(0,J8-N8),SUMIFS('Loan Prepayment'!$B$12:$B$31,'Loan Prepayment'!$A$12:$A$31,I8)+0)) -> 0 | P8: =MAX(0,J8-N8-O8) -> 9871189.6 | Q8: 7 | R8: =X7 -> 9889936.8 | S8: ='Loan Prepayment'!$B$6 -> 7.5 | T8: =IF(R8<=0,0,MIN(IF(AND('Loan Prepayment'!$E$15="Reduce EMI",W7>0),-PMT(S8/1200,MAX(1,'Loan Prepayment'!$B$7*12-Q8+1),R8),T7),R8+U8)) -> 80559.319 | U8: =IF(R8<=0,0,R8*S8/1200) -> 61812.105 | V8: =MAX(0,T8-U8) -> 18747.214 | W8: =IF(R8<=0,0,MIN(MAX(0,R8-V8),0+IF(AND(Q8>='Loan Prepayment'!$B$9,Q8<='Loan Prepayment'!$E$16),'Loan Prepayment'!$B$8,0))) -> 0 | X8: =MAX(0,R8-V8-W8) -> 9871189.6 | Y8: 7 | Z8: =AF7 -> 9889936.8 | AA8: =IF(Y8>='Loan Prepayment'!$E$11,'Loan Prepayment'!$E$12,'Loan Prepayment'!$B$6) -> 7.5 | AB8: =IF(Z8<=0,0,MIN(IF(Y8='Loan Prepayment'!$E$11,IF('Loan Prepayment'!$E$13="Keep tenure, recalculate EMI",-PMT(AA8/1200,MAX(1,'Loan Prepayment'!$B$7*12-Y8+1),Z8),AB7),AB7),Z8+AC8)) -> 80559.319 | AC8: =IF(Z8<=0,0,Z8*AA8/1200) -> 61812.105 | AD8: =MAX(0,AB8-AC8) -> 18747.214 | AE8: =IF(Z8<=0,0,MIN(MAX(0,Z8-AD8),0)) -> 0 | AF8: =MAX(0,Z8-AD8-AE8) -> 9871189.6 | AG8: 7 | AH8: =AN7 -> 9889936.8 | AI8: =IF(AG8>='Loan Prepayment'!$E$11,'Loan Prepayment'!$E$12,'Loan Prepayment'!$B$6) -> 7.5 | AJ8: =IF(AH8<=0,0,MIN(IF(AG8='Loan Prepayment'!$E$11,IF('Loan Prepayment'!$E$13="Keep tenure, recalculate EMI",-PMT(AI8/1200,MAX(1,'Loan Prepayment'!$B$7*12-AG8+1),AH8),IF(AND('Loan Prepayment'!$E$15="Reduce EMI",AM7>0),-PMT(AI7/1200,MAX(1,'Loan Prepayment'!$B$7*12-AG8+1),AH8),AJ7)),IF(AND('Loan Prepayment'!$E$15="Reduce EMI",AM7>0),-PMT(AI8/1200,MAX(1,'Loan Prepayment'!$B$7*12-AG8+1),AH8),AJ7)),AH8+AK8)) -> 80559.319 | AK8: =IF(AH8<=0,0,AH8*AI8/1200) -> 61812.105 | AL8: =MAX(0,AJ8-AK8) -> 18747.214 | AM8: =IF(AH8<=0,0,MIN(MAX(0,AH8-AL8),SUMIFS('Loan Prepayment'!$B$12:$B$31,'Loan Prepayment'!$A$12:$A$31,AG8)+IF(AND(AG8>='Loan Prepayment'!$B$9,AG8<='Loan Prepayment'!$E$16),'Loan Prepayment'!$B$8,0))) -> 0 | AN8: =MAX(0,AH8-AL8-AM8) -> 9871189.6
A9: 8 | B9: =H8 -> 9871189.6 | C9: ='Loan Prepayment'!$B$6 -> 7.5 | D9: =IF(B9<=0,0,MIN(-PMT('Loan Prepayment'!$B$6/1200,'Loan Prepayment'!$B$7*12,'Loan Prepayment'!$B$5),B9+E9)) -> 80559.319 | E9: =IF(B9<=0,0,B9*C9/1200) -> 61694.935 | F9: =MAX(0,D9-E9) -> 18864.384 | G9: 0 | H9: =MAX(0,B9-F9-G9) -> 9852325.2 | I9: 8 | J9: =P8 -> 9871189.6 | K9: ='Loan Prepayment'!$B$6 -> 7.5 | L9: =IF(J9<=0,0,MIN(IF(AND('Loan Prepayment'!$E$15="Reduce EMI",O8>0),-PMT(K9/1200,MAX(1,'Loan Prepayment'!$B$7*12-I9+1),J9),L8),J9+M9)) -> 80559.319 | M9: =IF(J9<=0,0,J9*K9/1200) -> 61694.935 | N9: =MAX(0,L9-M9) -> 18864.384 | O9: =IF(J9<=0,0,MIN(MAX(0,J9-N9),SUMIFS('Loan Prepayment'!$B$12:$B$31,'Loan Prepayment'!$A$12:$A$31,I9)+0)) -> 0 | P9: =MAX(0,J9-N9-O9) -> 9852325.2 | Q9: 8 | R9: =X8 -> 9871189.6 | S9: ='Loan Prepayment'!$B$6 -> 7.5 | T9: =IF(R9<=0,0,MIN(IF(AND('Loan Prepayment'!$E$15="Reduce EMI",W8>0),-PMT(S9/1200,MAX(1,'Loan Prepayment'!$B$7*12-Q9+1),R9),T8),R9+U9)) -> 80559.319 | U9: =IF(R9<=0,0,R9*S9/1200) -> 61694.935 | V9: =MAX(0,T9-U9) -> 18864.384 | W9: =IF(R9<=0,0,MIN(MAX(0,R9-V9),0+IF(AND(Q9>='Loan Prepayment'!$B$9,Q9<='Loan Prepayment'!$E$16),'Loan Prepayment'!$B$8,0))) -> 0 | X9: =MAX(0,R9-V9-W9) -> 9852325.2 | Y9: 8 | Z9: =AF8 -> 9871189.6 | AA9: =IF(Y9>='Loan Prepayment'!$E$11,'Loan Prepayment'!$E$12,'Loan Prepayment'!$B$6) -> 7.5 | AB9: =IF(Z9<=0,0,MIN(IF(Y9='Loan Prepayment'!$E$11,IF('Loan Prepayment'!$E$13="Keep tenure, recalculate EMI",-PMT(AA9/1200,MAX(1,'Loan Prepayment'!$B$7*12-Y9+1),Z9),AB8),AB8),Z9+AC9)) -> 80559.319 | AC9: =IF(Z9<=0,0,Z9*AA9/1200) -> 61694.935 | AD9: =MAX(0,AB9-AC9) -> 18864.384 | AE9: =IF(Z9<=0,0,MIN(MAX(0,Z9-AD9),0)) -> 0 | AF9: =MAX(0,Z9-AD9-AE9) -> 9852325.2 | AG9: 8 | AH9: =AN8 -> 9871189.6 | AI9: =IF(AG9>='Loan Prepayment'!$E$11,'Loan Prepayment'!$E$12,'Loan Prepayment'!$B$6) -> 7.5 | AJ9: =IF(AH9<=0,0,MIN(IF(AG9='Loan Prepayment'!$E$11,IF('Loan Prepayment'!$E$13="Keep tenure, recalculate EMI",-PMT(AI9/1200,MAX(1,'Loan Prepayment'!$B$7*12-AG9+1),AH9),IF(AND('Loan Prepayment'!$E$15="Reduce EMI",AM8>0),-PMT(AI8/1200,MAX(1,'Loan Prepayment'!$B$7*12-AG9+1),AH9),AJ8)),IF(AND('Loan Prepayment'!$E$15="Reduce EMI",AM8>0),-PMT(AI9/1200,MAX(1,'Loan Prepayment'!$B$7*12-AG9+1),AH9),AJ8)),AH9+AK9)) -> 80559.319 | AK9: =IF(AH9<=0,0,AH9*AI9/1200) -> 61694.935 | AL9: =MAX(0,AJ9-AK9) -> 18864.384 | AM9: =IF(AH9<=0,0,MIN(MAX(0,AH9-AL9),SUMIFS('Loan Prepayment'!$B$12:$B$31,'Loan Prepayment'!$A$12:$A$31,AG9)+IF(AND(AG9>='Loan Prepayment'!$B$9,AG9<='Loan Prepayment'!$E$16),'Loan Prepayment'!$B$8,0))) -> 0 | AN9: =MAX(0,AH9-AL9-AM9) -> 9852325.2
A10: 9 | B10: =H9 -> 9852325.2 | C10: ='Loan Prepayment'!$B$6 -> 7.5 | D10: =IF(B10<=0,0,MIN(-PMT('Loan Prepayment'!$B$6/1200,'Loan Prepayment'!$B$7*12,'Loan Prepayment'!$B$5),B10+E10)) -> 80559.319 | E10: =IF(B10<=0,0,B10*C10/1200) -> 61577.033 | F10: =MAX(0,D10-E10) -> 18982.287 | G10: 0 | H10: =MAX(0,B10-F10-G10) -> 9833343 | I10: 9 | J10: =P9 -> 9852325.2 | K10: ='Loan Prepayment'!$B$6 -> 7.5 | L10: =IF(J10<=0,0,MIN(IF(AND('Loan Prepayment'!$E$15="Reduce EMI",O9>0),-PMT(K10/1200,MAX(1,'Loan Prepayment'!$B$7*12-I10+1),J10),L9),J10+M10)) -> 80559.319 | M10: =IF(J10<=0,0,J10*K10/1200) -> 61577.033 | N10: =MAX(0,L10-M10) -> 18982.287 | O10: =IF(J10<=0,0,MIN(MAX(0,J10-N10),SUMIFS('Loan Prepayment'!$B$12:$B$31,'Loan Prepayment'!$A$12:$A$31,I10)+0)) -> 0 | P10: =MAX(0,J10-N10-O10) -> 9833343 | Q10: 9 | R10: =X9 -> 9852325.2 | S10: ='Loan Prepayment'!$B$6 -> 7.5 | T10: =IF(R10<=0,0,MIN(IF(AND('Loan Prepayment'!$E$15="Reduce EMI",W9>0),-PMT(S10/1200,MAX(1,'Loan Prepayment'!$B$7*12-Q10+1),R10),T9),R10+U10)) -> 80559.319 | U10: =IF(R10<=0,0,R10*S10/1200) -> 61577.033 | V10: =MAX(0,T10-U10) -> 18982.287 | W10: =IF(R10<=0,0,MIN(MAX(0,R10-V10),0+IF(AND(Q10>='Loan Prepayment'!$B$9,Q10<='Loan Prepayment'!$E$16),'Loan Prepayment'!$B$8,0))) -> 0 | X10: =MAX(0,R10-V10-W10) -> 9833343 | Y10: 9 | Z10: =AF9 -> 9852325.2 | AA10: =IF(Y10>='Loan Prepayment'!$E$11,'Loan Prepayment'!$E$12,'Loan Prepayment'!$B$6) -> 7.5 | AB10: =IF(Z10<=0,0,MIN(IF(Y10='Loan Prepayment'!$E$11,IF('Loan Prepayment'!$E$13="Keep tenure, recalculate EMI",-PMT(AA10/1200,MAX(1,'Loan Prepayment'!$B$7*12-Y10+1),Z10),AB9),AB9),Z10+AC10)) -> 80559.319 | AC10: =IF(Z10<=0,0,Z10*AA10/1200) -> 61577.033 | AD10: =MAX(0,AB10-AC10) -> 18982.287 | AE10: =IF(Z10<=0,0,MIN(MAX(0,Z10-AD10),0)) -> 0 | AF10: =MAX(0,Z10-AD10-AE10) -> 9833343 | AG10: 9 | AH10: =AN9 -> 9852325.2 | AI10: =IF(AG10>='Loan Prepayment'!$E$11,'Loan Prepayment'!$E$12,'Loan Prepayment'!$B$6) -> 7.5 | AJ10: =IF(AH10<=0,0,MIN(IF(AG10='Loan Prepayment'!$E$11,IF('Loan Prepayment'!$E$13="Keep tenure, recalculate EMI",-PMT(AI10/1200,MAX(1,'Loan Prepayment'!$B$7*12-AG10+1),AH10),IF(AND('Loan Prepayment'!$E$15="Reduce EMI",AM9>0),-PMT(AI9/1200,MAX(1,'Loan Prepayment'!$B$7*12-AG10+1),AH10),AJ9)),IF(AND('Loan Prepayment'!$E$15="Reduce EMI",AM9>0),-PMT(AI10/1200,MAX(1,'Loan Prepayment'!$B$7*12-AG10+1),AH10),AJ9)),AH10+AK10)) -> 80559.319 | AK10: =IF(AH10<=0,0,AH10*AI10/1200) -> 61577.033 | AL10: =MAX(0,AJ10-AK10) -> 18982.287 | AM10: =IF(AH10<=0,0,MIN(MAX(0,AH10-AL10),SUMIFS('Loan Prepayment'!$B$12:$B$31,'Loan Prepayment'!$A$12:$A$31,AG10)+IF(AND(AG10>='Loan Prepayment'!$B$9,AG10<='Loan Prepayment'!$E$16),'Loan Prepayment'!$B$8,0))) -> 0 | AN10: =MAX(0,AH10-AL10-AM10) -> 9833343
A11: 10 | B11: =H10 -> 9833343 | C11: ='Loan Prepayment'!$B$6 -> 7.5 | D11: =IF(B11<=0,0,MIN(-PMT('Loan Prepayment'!$B$6/1200,'Loan Prepayment'!$B$7*12,'Loan Prepayment'!$B$5),B11+E11)) -> 80559.319 | E11: =IF(B11<=0,0,B11*C11/1200) -> 61458.394 | F11: =MAX(0,D11-E11) -> 19100.926 | G11: 0 | H11: =MAX(0,B11-F11-G11) -> 9814242 | I11: 10 | J11: =P10 -> 9833343 | K11: ='Loan Prepayment'!$B$6 -> 7.5 | L11: =IF(J11<=0,0,MIN(IF(AND('Loan Prepayment'!$E$15="Reduce EMI",O10>0),-PMT(K11/1200,MAX(1,'Loan Prepayment'!$B$7*12-I11+1),J11),L10),J11+M11)) -> 80559.319 | M11: =IF(J11<=0,0,J11*K11/1200) -> 61458.394 | N11: =MAX(0,L11-M11) -> 19100.926 | O11: =IF(J11<=0,0,MIN(MAX(0,J11-N11),SUMIFS('Loan Prepayment'!$B$12:$B$31,'Loan Prepayment'!$A$12:$A$31,I11)+0)) -> 0 | P11: =MAX(0,J11-N11-O11) -> 9814242 | Q11: 10 | R11: =X10 -> 9833343 | S11: ='Loan Prepayment'!$B$6 -> 7.5 | T11: =IF(R11<=0,0,MIN(IF(AND('Loan Prepayment'!$E$15="Reduce EMI",W10>0),-PMT(S11/1200,MAX(1,'Loan Prepayment'!$B$7*12-Q11+1),R11),T10),R11+U11)) -> 80559.319 | U11: =IF(R11<=0,0,R11*S11/1200) -> 61458.394 | V11: =MAX(0,T11-U11) -> 19100.926 | W11: =IF(R11<=0,0,MIN(MAX(0,R11-V11),0+IF(AND(Q11>='Loan Prepayment'!$B$9,Q11<='Loan Prepayment'!$E$16),'Loan Prepayment'!$B$8,0))) -> 0 | X11: =MAX(0,R11-V11-W11) -> 9814242 | Y11: 10 | Z11: =AF10 -> 9833343 | AA11: =IF(Y11>='Loan Prepayment'!$E$11,'Loan Prepayment'!$E$12,'Loan Prepayment'!$B$6) -> 7.5 | AB11: =IF(Z11<=0,0,MIN(IF(Y11='Loan Prepayment'!$E$11,IF('Loan Prepayment'!$E$13="Keep tenure, recalculate EMI",-PMT(AA11/1200,MAX(1,'Loan Prepayment'!$B$7*12-Y11+1),Z11),AB10),AB10),Z11+AC11)) -> 80559.319 | AC11: =IF(Z11<=0,0,Z11*AA11/1200) -> 61458.394 | AD11: =MAX(0,AB11-AC11) -> 19100.926 | AE11: =IF(Z11<=0,0,MIN(MAX(0,Z11-AD11),0)) -> 0 | AF11: =MAX(0,Z11-AD11-AE11) -> 9814242 | AG11: 10 | AH11: =AN10 -> 9833343 | AI11: =IF(AG11>='Loan Prepayment'!$E$11,'Loan Prepayment'!$E$12,'Loan Prepayment'!$B$6) -> 7.5 | AJ11: =IF(AH11<=0,0,MIN(IF(AG11='Loan Prepayment'!$E$11,IF('Loan Prepayment'!$E$13="Keep tenure, recalculate EMI",-PMT(AI11/1200,MAX(1,'Loan Prepayment'!$B$7*12-AG11+1),AH11),IF(AND('Loan Prepayment'!$E$15="Reduce EMI",AM10>0),-PMT(AI10/1200,MAX(1,'Loan Prepayment'!$B$7*12-AG11+1),AH11),AJ10)),IF(AND('Loan Prepayment'!$E$15="Reduce EMI",AM10>0),-PMT(AI11/1200,MAX(1,'Loan Prepayment'!$B$7*12-AG11+1),AH11),AJ10)),AH11+AK11)) -> 80559.319 | AK11: =IF(AH11<=0,0,AH11*AI11/1200) -> 61458.394 | AL11: =MAX(0,AJ11-AK11) -> 19100.926 | AM11: =IF(AH11<=0,0,MIN(MAX(0,AH11-AL11),SUMIFS('Loan Prepayment'!$B$12:$B$31,'Loan Prepayment'!$A$12:$A$31,AG11)+IF(AND(AG11>='Loan Prepayment'!$B$9,AG11<='Loan Prepayment'!$E$16),'Loan Prepayment'!$B$8,0))) -> 0 | AN11: =MAX(0,AH11-AL11-AM11) -> 9814242
A12: 11 | B12: =H11 -> 9814242 | C12: ='Loan Prepayment'!$B$6 -> 7.5 | D12: =IF(B12<=0,0,MIN(-PMT('Loan Prepayment'!$B$6/1200,'Loan Prepayment'!$B$7*12,'Loan Prepayment'!$B$5),B12+E12)) -> 80559.319 | E12: =IF(B12<=0,0,B12*C12/1200) -> 61339.013 | F12: =MAX(0,D12-E12) -> 19220.307 | G12: 0 | H12: =MAX(0,B12-F12-G12) -> 9795021.7 | I12: 11 | J12: =P11 -> 9814242 | K12: ='Loan Prepayment'!$B$6 -> 7.5 | L12: =IF(J12<=0,0,MIN(IF(AND('Loan Prepayment'!$E$15="Reduce EMI",O11>0),-PMT(K12/1200,MAX(1,'Loan Prepayment'!$B$7*12-I12+1),J12),L11),J12+M12)) -> 80559.319 | M12: =IF(J12<=0,0,J12*K12/1200) -> 61339.013 | N12: =MAX(0,L12-M12) -> 19220.307 | O12: =IF(J12<=0,0,MIN(MAX(0,J12-N12),SUMIFS('Loan Prepayment'!$B$12:$B$31,'Loan Prepayment'!$A$12:$A$31,I12)+0)) -> 0 | P12: =MAX(0,J12-N12-O12) -> 9795021.7 | Q12: 11 | R12: =X11 -> 9814242 | S12: ='Loan Prepayment'!$B$6 -> 7.5 | T12: =IF(R12<=0,0,MIN(IF(AND('Loan Prepayment'!$E$15="Reduce EMI",W11>0),-PMT(S12/1200,MAX(1,'Loan Prepayment'!$B$7*12-Q12+1),R12),T11),R12+U12)) -> 80559.319 | U12: =IF(R12<=0,0,R12*S12/1200) -> 61339.013 | V12: =MAX(0,T12-U12) -> 19220.307 | W12: =IF(R12<=0,0,MIN(MAX(0,R12-V12),0+IF(AND(Q12>='Loan Prepayment'!$B$9,Q12<='Loan Prepayment'!$E$16),'Loan Prepayment'!$B$8,0))) -> 0 | X12: =MAX(0,R12-V12-W12) -> 9795021.7 | Y12: 11 | Z12: =AF11 -> 9814242 | AA12: =IF(Y12>='Loan Prepayment'!$E$11,'Loan Prepayment'!$E$12,'Loan Prepayment'!$B$6) -> 7.5 | AB12: =IF(Z12<=0,0,MIN(IF(Y12='Loan Prepayment'!$E$11,IF('Loan Prepayment'!$E$13="Keep tenure, recalculate EMI",-PMT(AA12/1200,MAX(1,'Loan Prepayment'!$B$7*12-Y12+1),Z12),AB11),AB11),Z12+AC12)) -> 80559.319 | AC12: =IF(Z12<=0,0,Z12*AA12/1200) -> 61339.013 | AD12: =MAX(0,AB12-AC12) -> 19220.307 | AE12: =IF(Z12<=0,0,MIN(MAX(0,Z12-AD12),0)) -> 0 | AF12: =MAX(0,Z12-AD12-AE12) -> 9795021.7 | AG12: 11 | AH12: =AN11 -> 9814242 | AI12: =IF(AG12>='Loan Prepayment'!$E$11,'Loan Prepayment'!$E$12,'Loan Prepayment'!$B$6) -> 7.5 | AJ12: =IF(AH12<=0,0,MIN(IF(AG12='Loan Prepayment'!$E$11,IF('Loan Prepayment'!$E$13="Keep tenure, recalculate EMI",-PMT(AI12/1200,MAX(1,'Loan Prepayment'!$B$7*12-AG12+1),AH12),IF(AND('Loan Prepayment'!$E$15="Reduce EMI",AM11>0),-PMT(AI11/1200,MAX(1,'Loan Prepayment'!$B$7*12-AG12+1),AH12),AJ11)),IF(AND('Loan Prepayment'!$E$15="Reduce EMI",AM11>0),-PMT(AI12/1200,MAX(1,'Loan Prepayment'!$B$7*12-AG12+1),AH12),AJ11)),AH12+AK12)) -> 80559.319 | AK12: =IF(AH12<=0,0,AH12*AI12/1200) -> 61339.013 | AL12: =MAX(0,AJ12-AK12) -> 19220.307 | AM12: =IF(AH12<=0,0,MIN(MAX(0,AH12-AL12),SUMIFS('Loan Prepayment'!$B$12:$B$31,'Loan Prepayment'!$A$12:$A$31,AG12)+IF(AND(AG12>='Loan Prepayment'!$B$9,AG12<='Loan Prepayment'!$E$16),'Loan Prepayment'!$B$8,0))) -> 0 | AN12: =MAX(0,AH12-AL12-AM12) -> 9795021.7
A13: 12 | B13: =H12 -> 9795021.7 | C13: ='Loan Prepayment'!$B$6 -> 7.5 | D13: =IF(B13<=0,0,MIN(-PMT('Loan Prepayment'!$B$6/1200,'Loan Prepayment'!$B$7*12,'Loan Prepayment'!$B$5),B13+E13)) -> 80559.319 | E13: =IF(B13<=0,0,B13*C13/1200) -> 61218.886 | F13: =MAX(0,D13-E13) -> 19340.434 | G13: 0 | H13: =MAX(0,B13-F13-G13) -> 9775681.3 | I13: 12 | J13: =P12 -> 9795021.7 | K13: ='Loan Prepayment'!$B$6 -> 7.5 | L13: =IF(J13<=0,0,MIN(IF(AND('Loan Prepayment'!$E$15="Reduce EMI",O12>0),-PMT(K13/1200,MAX(1,'Loan Prepayment'!$B$7*12-I13+1),J13),L12),J13+M13)) -> 80559.319 | M13: =IF(J13<=0,0,J13*K13/1200) -> 61218.886 | N13: =MAX(0,L13-M13) -> 19340.434 | O13: =IF(J13<=0,0,MIN(MAX(0,J13-N13),SUMIFS('Loan Prepayment'!$B$12:$B$31,'Loan Prepayment'!$A$12:$A$31,I13)+0)) -> 500000 | P13: =MAX(0,J13-N13-O13) -> 9275681.3 | Q13: 12 | R13: =X12 -> 9795021.7 | S13: ='Loan Prepayment'!$B$6 -> 7.5 | T13: =IF(R13<=0,0,MIN(IF(AND('Loan Prepayment'!$E$15="Reduce EMI",W12>0),-PMT(S13/1200,MAX(1,'Loan Prepayment'!$B$7*12-Q13+1),R13),T12),R13+U13)) -> 80559.319 | U13: =IF(R13<=0,0,R13*S13/1200) -> 61218.886 | V13: =MAX(0,T13-U13) -> 19340.434 | W13: =IF(R13<=0,0,MIN(MAX(0,R13-V13),0+IF(AND(Q13>='Loan Prepayment'!$B$9,Q13<='Loan Prepayment'!$E$16),'Loan Prepayment'!$B$8,0))) -> 0 | X13: =MAX(0,R13-V13-W13) -> 9775681.3 | Y13: 12 | Z13: =AF12 -> 9795021.7 | AA13: =IF(Y13>='Loan Prepayment'!$E$11,'Loan Prepayment'!$E$12,'Loan Prepayment'!$B$6) -> 7.5 | AB13: =IF(Z13<=0,0,MIN(IF(Y13='Loan Prepayment'!$E$11,IF('Loan Prepayment'!$E$13="Keep tenure, recalculate EMI",-PMT(AA13/1200,MAX(1,'Loan Prepayment'!$B$7*12-Y13+1),Z13),AB12),AB12),Z13+AC13)) -> 80559.319 | AC13: =IF(Z13<=0,0,Z13*AA13/1200) -> 61218.886 | AD13: =MAX(0,AB13-AC13) -> 19340.434 | AE13: =IF(Z13<=0,0,MIN(MAX(0,Z13-AD13),0)) -> 0 | AF13: =MAX(0,Z13-AD13-AE13) -> 9775681.3 | AG13: 12 | AH13: =AN12 -> 9795021.7 | AI13: =IF(AG13>='Loan Prepayment'!$E$11,'Loan Prepayment'!$E$12,'Loan Prepayment'!$B$6) -> 7.5 | AJ13: =IF(AH13<=0,0,MIN(IF(AG13='Loan Prepayment'!$E$11,IF('Loan Prepayment'!$E$13="Keep tenure, recalculate EMI",-PMT(AI13/1200,MAX(1,'Loan Prepayment'!$B$7*12-AG13+1),AH13),IF(AND('Loan Prepayment'!$E$15="Reduce EMI",AM12>0),-PMT(AI12/1200,MAX(1,'Loan Prepayment'!$B$7*12-AG13+1),AH13),AJ12)),IF(AND('Loan Prepayment'!$E$15="Reduce EMI",AM12>0),-PMT(AI13/1200,MAX(1,'Loan Prepayment'!$B$7*12-AG13+1),AH13),AJ12)),AH13+AK13)) -> 80559.319 | AK13: =IF(AH13<=0,0,AH13*AI13/1200) -> 61218.886 | AL13: =MAX(0,AJ13-AK13) -> 19340.434 | AM13: =IF(AH13<=0,0,MIN(MAX(0,AH13-AL13),SUMIFS('Loan Prepayment'!$B$12:$B$31,'Loan Prepayment'!$A$12:$A$31,AG13)+IF(AND(AG13>='Loan Prepayment'!$B$9,AG13<='Loan Prepayment'!$E$16),'Loan Prepayment'!$B$8,0))) -> 500000 | AN13: =MAX(0,AH13-AL13-AM13) -> 9275681.3
A14: 13 | B14: =H13 -> 9775681.3 | C14: ='Loan Prepayment'!$B$6 -> 7.5 | D14: =IF(B14<=0,0,MIN(-PMT('Loan Prepayment'!$B$6/1200,'Loan Prepayment'!$B$7*12,'Loan Prepayment'!$B$5),B14+E14)) -> 80559.319 | E14: =IF(B14<=0,0,B14*C14/1200) -> 61098.008 | F14: =MAX(0,D14-E14) -> 19461.311 | G14: 0 | H14: =MAX(0,B14-F14-G14) -> 9756220 | I14: 13 | J14: =P13 -> 9275681.3 | K14: ='Loan Prepayment'!$B$6 -> 7.5 | L14: =IF(J14<=0,0,MIN(IF(AND('Loan Prepayment'!$E$15="Reduce EMI",O13>0),-PMT(K14/1200,MAX(1,'Loan Prepayment'!$B$7*12-I14+1),J14),L13),J14+M14)) -> 76438.925 | M14: =IF(J14<=0,0,J14*K14/1200) -> 57973.008 | N14: =MAX(0,L14-M14) -> 18465.917 | O14: =IF(J14<=0,0,MIN(MAX(0,J14-N14),SUMIFS('Loan Prepayment'!$B$12:$B$31,'Loan Prepayment'!$A$12:$A$31,I14)+0)) -> 0 | P14: =MAX(0,J14-N14-O14) -> 9257215.4 | Q14: 13 | R14: =X13 -> 9775681.3 | S14: ='Loan Prepayment'!$B$6 -> 7.5 | T14: =IF(R14<=0,0,MIN(IF(AND('Loan Prepayment'!$E$15="Reduce EMI",W13>0),-PMT(S14/1200,MAX(1,'Loan Prepayment'!$B$7*12-Q14+1),R14),T13),R14+U14)) -> 80559.319 | U14: =IF(R14<=0,0,R14*S14/1200) -> 61098.008 | V14: =MAX(0,T14-U14) -> 19461.311 | W14: =IF(R14<=0,0,MIN(MAX(0,R14-V14),0+IF(AND(Q14>='Loan Prepayment'!$B$9,Q14<='Loan Prepayment'!$E$16),'Loan Prepayment'!$B$8,0))) -> 0 | X14: =MAX(0,R14-V14-W14) -> 9756220 | Y14: 13 | Z14: =AF13 -> 9775681.3 | AA14: =IF(Y14>='Loan Prepayment'!$E$11,'Loan Prepayment'!$E$12,'Loan Prepayment'!$B$6) -> 7.5 | AB14: =IF(Z14<=0,0,MIN(IF(Y14='Loan Prepayment'!$E$11,IF('Loan Prepayment'!$E$13="Keep tenure, recalculate EMI",-PMT(AA14/1200,MAX(1,'Loan Prepayment'!$B$7*12-Y14+1),Z14),AB13),AB13),Z14+AC14)) -> 80559.319 | AC14: =IF(Z14<=0,0,Z14*AA14/1200) -> 61098.008 | AD14: =MAX(0,AB14-AC14) -> 19461.311 | AE14: =IF(Z14<=0,0,MIN(MAX(0,Z14-AD14),0)) -> 0 | AF14: =MAX(0,Z14-AD14-AE14) -> 9756220 | AG14: 13 | AH14: =AN13 -> 9275681.3 | AI14: =IF(AG14>='Loan Prepayment'!$E$11,'Loan Prepayment'!$E$12,'Loan Prepayment'!$B$6) -> 7.5 | AJ14: =IF(AH14<=0,0,MIN(IF(AG14='Loan Prepayment'!$E$11,IF('Loan Prepayment'!$E$13="Keep tenure, recalculate EMI",-PMT(AI14/1200,MAX(1,'Loan Prepayment'!$B$7*12-AG14+1),AH14),IF(AND('Loan Prepayment'!$E$15="Reduce EMI",AM13>0),-PMT(AI13/1200,MAX(1,'Loan Prepayment'!$B$7*12-AG14+1),AH14),AJ13)),IF(AND('Loan Prepayment'!$E$15="Reduce EMI",AM13>0),-PMT(AI14/1200,MAX(1,'Loan Prepayment'!$B$7*12-AG14+1),AH14),AJ13)),AH14+AK14)) -> 76438.925 | AK14: =IF(AH14<=0,0,AH14*AI14/1200) -> 57973.008 | AL14: =MAX(0,AJ14-AK14) -> 18465.917 | AM14: =IF(AH14<=0,0,MIN(MAX(0,AH14-AL14),SUMIFS('Loan Prepayment'!$B$12:$B$31,'Loan Prepayment'!$A$12:$A$31,AG14)+IF(AND(AG14>='Loan Prepayment'!$B$9,AG14<='Loan Prepayment'!$E$16),'Loan Prepayment'!$B$8,0))) -> 0 | AN14: =MAX(0,AH14-AL14-AM14) -> 9257215.4
... A361: 360 | B361: =H360 -> 0 | C361: ='Loan Prepayment'!$B$6 -> 7.5 | D361: =IF(B361<=0,0,MIN(-PMT('Loan Prepayment'!$B$6/1200,'Loan Prepayment'!$B$7*12,'Loan Prepayment'!$B$5),B361+E361)) -> 0 | E361: =IF(B361<=0,0,B361*C361/1200) -> 0 | F361: =MAX(0,D361-E361) -> 0 | G361: 0 | H361: =MAX(0,B361-F361-G361) -> 0 | I361: 360 | J361: =P360 -> 0 | K361: ='Loan Prepayment'!$B$6 -> 7.5 | L361: =IF(J361<=0,0,MIN(IF(AND('Loan Prepayment'!$E$15="Reduce EMI",O360>0),-PMT(K361/1200,MAX(1,'Loan Prepayment'!$B$7*12-I361+1),J361),L360),J361+M361)) -> 0 | M361: =IF(J361<=0,0,J361*K361/1200) -> 0 | N361: =MAX(0,L361-M361) -> 0 | O361: =IF(J361<=0,0,MIN(MAX(0,J361-N361),SUMIFS('Loan Prepayment'!$B$12:$B$31,'Loan Prepayment'!$A$12:$A$31,I361)+0)) -> 0 | P361: =MAX(0,J361-N361-O361) -> 0 | Q361: 360 | R361: =X360 -> 0 | S361: ='Loan Prepayment'!$B$6 -> 7.5 | T361: =IF(R361<=0,0,MIN(IF(AND('Loan Prepayment'!$E$15="Reduce EMI",W360>0),-PMT(S361/1200,MAX(1,'Loan Prepayment'!$B$7*12-Q361+1),R361),T360),R361+U361)) -> 0 | U361: =IF(R361<=0,0,R361*S361/1200) -> 0 | V361: =MAX(0,T361-U361) -> 0 | W361: =IF(R361<=0,0,MIN(MAX(0,R361-V361),0+IF(AND(Q361>='Loan Prepayment'!$B$9,Q361<='Loan Prepayment'!$E$16),'Loan Prepayment'!$B$8,0))) -> 0 | X361: =MAX(0,R361-V361-W361) -> 0 | Y361: 360 | Z361: =AF360 -> 0 | AA361: =IF(Y361>='Loan Prepayment'!$E$11,'Loan Prepayment'!$E$12,'Loan Prepayment'!$B$6) -> 6.5 | AB361: =IF(Z361<=0,0,MIN(IF(Y361='Loan Prepayment'!$E$11,IF('Loan Prepayment'!$E$13="Keep tenure, recalculate EMI",-PMT(AA361/1200,MAX(1,'Loan Prepayment'!$B$7*12-Y361+1),Z361),AB360),AB360),Z361+AC361)) -> 0 | AC361: =IF(Z361<=0,0,Z361*AA361/1200) -> 0 | AD361: =MAX(0,AB361-AC361) -> 0 | AE361: =IF(Z361<=0,0,MIN(MAX(0,Z361-AD361),0)) -> 0 | AF361: =MAX(0,Z361-AD361-AE361) -> 0 | AG361: 360 | AH361: =AN360 -> 0 | AI361: =IF(AG361>='Loan Prepayment'!$E$11,'Loan Prepayment'!$E$12,'Loan Prepayment'!$B$6) -> 6.5 | AJ361: =IF(AH361<=0,0,MIN(IF(AG361='Loan Prepayment'!$E$11,IF('Loan Prepayment'!$E$13="Keep tenure, recalculate EMI",-PMT(AI361/1200,MAX(1,'Loan Prepayment'!$B$7*12-AG361+1),AH361),IF(AND('Loan Prepayment'!$E$15="Reduce EMI",AM360>0),-PMT(AI360/1200,MAX(1,'Loan Prepayment'!$B$7*12-AG361+1),AH361),AJ360)),IF(AND('Loan Prepayment'!$E$15="Reduce EMI",AM360>0),-PMT(AI361/1200,MAX(1,'Loan Prepayment'!$B$7*12-AG361+1),AH361),AJ360)),AH361+AK361)) -> 0 | AK361: =IF(AH361<=0,0,AH361*AI361/1200) -> 0 | AL361: =MAX(0,AJ361-AK361) -> 0 | AM361: =IF(AH361<=0,0,MIN(MAX(0,AH361-AL361),SUMIFS('Loan Prepayment'!$B$12:$B$31,'Loan Prepayment'!$A$12:$A$31,AG361)+IF(AND(AG361>='Loan Prepayment'!$B$9,AG361<='Loan Prepayment'!$E$16),'Loan Prepayment'!$B$8,0))) -> 0 | AN361: =MAX(0,AH361-AL361-AM361) -> 0
A362: =A361+1 -> 361 | B362: =H361 -> 0 | C362: ='Loan Prepayment'!$B$6 -> 7.5 | D362: =IF(B362<=0,0,MIN(-PMT('Loan Prepayment'!$B$6/1200,'Loan Prepayment'!$B$7*12,'Loan Prepayment'!$B$5),B362+E362)) -> 0 | E362: =IF(B362<=0,0,B362*C362/1200) -> 0 | F362: =MAX(0,D362-E362) -> 0 | G362: 0 | H362: =MAX(0,B362-F362-G362) -> 0 | I362: =I361+1 -> 361 | J362: =P361 -> 0 | K362: ='Loan Prepayment'!$B$6 -> 7.5 | L362: =IF(J362<=0,0,MIN(IF(AND('Loan Prepayment'!$E$15="Reduce EMI",O361>0),-PMT(K362/1200,MAX(1,'Loan Prepayment'!$B$7*12-I362+1),J362),L361),J362+M362)) -> 0 | M362: =IF(J362<=0,0,J362*K362/1200) -> 0 | N362: =MAX(0,L362-M362) -> 0 | O362: =IF(J362<=0,0,MIN(MAX(0,J362-N362),SUMIFS('Loan Prepayment'!$B$12:$B$31,'Loan Prepayment'!$A$12:$A$31,I362)+0)) -> 0 | P362: =MAX(0,J362-N362-O362) -> 0 | Q362: =Q361+1 -> 361 | R362: =X361 -> 0 | S362: ='Loan Prepayment'!$B$6 -> 7.5 | T362: =IF(R362<=0,0,MIN(IF(AND('Loan Prepayment'!$E$15="Reduce EMI",W361>0),-PMT(S362/1200,MAX(1,'Loan Prepayment'!$B$7*12-Q362+1),R362),T361),R362+U362)) -> 0 | U362: =IF(R362<=0,0,R362*S362/1200) -> 0 | V362: =MAX(0,T362-U362) -> 0 | W362: =IF(R362<=0,0,MIN(MAX(0,R362-V362),0+IF(AND(Q362>='Loan Prepayment'!$B$9,Q362<='Loan Prepayment'!$E$16),'Loan Prepayment'!$B$8,0))) -> 0 | X362: =MAX(0,R362-V362-W362) -> 0 | Y362: =Y361+1 -> 361 | Z362: =AF361 -> 0 | AA362: =IF(Y362>='Loan Prepayment'!$E$11,'Loan Prepayment'!$E$12,'Loan Prepayment'!$B$6) -> 6.5 | AB362: =IF(Z362<=0,0,MIN(IF(Y362='Loan Prepayment'!$E$11,IF('Loan Prepayment'!$E$13="Keep tenure, recalculate EMI",-PMT(AA362/1200,MAX(1,'Loan Prepayment'!$B$7*12-Y362+1),Z362),AB361),AB361),Z362+AC362)) -> 0 | AC362: =IF(Z362<=0,0,Z362*AA362/1200) -> 0 | AD362: =MAX(0,AB362-AC362) -> 0 | AE362: =IF(Z362<=0,0,MIN(MAX(0,Z362-AD362),0)) -> 0 | AF362: =MAX(0,Z362-AD362-AE362) -> 0 | AG362: =AG361+1 -> 361 | AH362: =AN361 -> 0 | AI362: =IF(AG362>='Loan Prepayment'!$E$11,'Loan Prepayment'!$E$12,'Loan Prepayment'!$B$6) -> 6.5 | AJ362: =IF(AH362<=0,0,MIN(IF(AG362='Loan Prepayment'!$E$11,IF('Loan Prepayment'!$E$13="Keep tenure, recalculate EMI",-PMT(AI362/1200,MAX(1,'Loan Prepayment'!$B$7*12-AG362+1),AH362),IF(AND('Loan Prepayment'!$E$15="Reduce EMI",AM361>0),-PMT(AI361/1200,MAX(1,'Loan Prepayment'!$B$7*12-AG362+1),AH362),AJ361)),IF(AND('Loan Prepayment'!$E$15="Reduce EMI",AM361>0),-PMT(AI362/1200,MAX(1,'Loan Prepayment'!$B$7*12-AG362+1),AH362),AJ361)),AH362+AK362)) -> 0 | AK362: =IF(AH362<=0,0,AH362*AI362/1200) -> 0 | AL362: =MAX(0,AJ362-AK362) -> 0 | AM362: =IF(AH362<=0,0,MIN(MAX(0,AH362-AL362),SUMIFS('Loan Prepayment'!$B$12:$B$31,'Loan Prepayment'!$A$12:$A$31,AG362)+IF(AND(AG362>='Loan Prepayment'!$B$9,AG362<='Loan Prepayment'!$E$16),'Loan Prepayment'!$B$8,0))) -> 0 | AN362: =MAX(0,AH362-AL362-AM362) -> 0
A363: =A362+1 -> 362 | B363: =H362 -> 0 | C363: ='Loan Prepayment'!$B$6 -> 7.5 | D363: =IF(B363<=0,0,MIN(-PMT('Loan Prepayment'!$B$6/1200,'Loan Prepayment'!$B$7*12,'Loan Prepayment'!$B$5),B363+E363)) -> 0 | E363: =IF(B363<=0,0,B363*C363/1200) -> 0 | F363: =MAX(0,D363-E363) -> 0 | G363: 0 | H363: =MAX(0,B363-F363-G363) -> 0 | I363: =I362+1 -> 362 | J363: =P362 -> 0 | K363: ='Loan Prepayment'!$B$6 -> 7.5 | L363: =IF(J363<=0,0,MIN(IF(AND('Loan Prepayment'!$E$15="Reduce EMI",O362>0),-PMT(K363/1200,MAX(1,'Loan Prepayment'!$B$7*12-I363+1),J363),L362),J363+M363)) -> 0 | M363: =IF(J363<=0,0,J363*K363/1200) -> 0 | N363: =MAX(0,L363-M363) -> 0 | O363: =IF(J363<=0,0,MIN(MAX(0,J363-N363),SUMIFS('Loan Prepayment'!$B$12:$B$31,'Loan Prepayment'!$A$12:$A$31,I363)+0)) -> 0 | P363: =MAX(0,J363-N363-O363) -> 0 | Q363: =Q362+1 -> 362 | R363: =X362 -> 0 | S363: ='Loan Prepayment'!$B$6 -> 7.5 | T363: =IF(R363<=0,0,MIN(IF(AND('Loan Prepayment'!$E$15="Reduce EMI",W362>0),-PMT(S363/1200,MAX(1,'Loan Prepayment'!$B$7*12-Q363+1),R363),T362),R363+U363)) -> 0 | U363: =IF(R363<=0,0,R363*S363/1200) -> 0 | V363: =MAX(0,T363-U363) -> 0 | W363: =IF(R363<=0,0,MIN(MAX(0,R363-V363),0+IF(AND(Q363>='Loan Prepayment'!$B$9,Q363<='Loan Prepayment'!$E$16),'Loan Prepayment'!$B$8,0))) -> 0 | X363: =MAX(0,R363-V363-W363) -> 0 | Y363: =Y362+1 -> 362 | Z363: =AF362 -> 0 | AA363: =IF(Y363>='Loan Prepayment'!$E$11,'Loan Prepayment'!$E$12,'Loan Prepayment'!$B$6) -> 6.5 | AB363: =IF(Z363<=0,0,MIN(IF(Y363='Loan Prepayment'!$E$11,IF('Loan Prepayment'!$E$13="Keep tenure, recalculate EMI",-PMT(AA363/1200,MAX(1,'Loan Prepayment'!$B$7*12-Y363+1),Z363),AB362),AB362),Z363+AC363)) -> 0 | AC363: =IF(Z363<=0,0,Z363*AA363/1200) -> 0 | AD363: =MAX(0,AB363-AC363) -> 0 | AE363: =IF(Z363<=0,0,MIN(MAX(0,Z363-AD363),0)) -> 0 | AF363: =MAX(0,Z363-AD363-AE363) -> 0 | AG363: =AG362+1 -> 362 | AH363: =AN362 -> 0 | AI363: =IF(AG363>='Loan Prepayment'!$E$11,'Loan Prepayment'!$E$12,'Loan Prepayment'!$B$6) -> 6.5 | AJ363: =IF(AH363<=0,0,MIN(IF(AG363='Loan Prepayment'!$E$11,IF('Loan Prepayment'!$E$13="Keep tenure, recalculate EMI",-PMT(AI363/1200,MAX(1,'Loan Prepayment'!$B$7*12-AG363+1),AH363),IF(AND('Loan Prepayment'!$E$15="Reduce EMI",AM362>0),-PMT(AI362/1200,MAX(1,'Loan Prepayment'!$B$7*12-AG363+1),AH363),AJ362)),IF(AND('Loan Prepayment'!$E$15="Reduce EMI",AM362>0),-PMT(AI363/1200,MAX(1,'Loan Prepayment'!$B$7*12-AG363+1),AH363),AJ362)),AH363+AK363)) -> 0 | AK363: =IF(AH363<=0,0,AH363*AI363/1200) -> 0 | AL363: =MAX(0,AJ363-AK363) -> 0 | AM363: =IF(AH363<=0,0,MIN(MAX(0,AH363-AL363),SUMIFS('Loan Prepayment'!$B$12:$B$31,'Loan Prepayment'!$A$12:$A$31,AG363)+IF(AND(AG363>='Loan Prepayment'!$B$9,AG363<='Loan Prepayment'!$E$16),'Loan Prepayment'!$B$8,0))) -> 0 | AN363: =MAX(0,AH363-AL363-AM363) -> 0
A364: =A363+1 -> 363 | B364: =H363 -> 0 | C364: ='Loan Prepayment'!$B$6 -> 7.5 | D364: =IF(B364<=0,0,MIN(-PMT('Loan Prepayment'!$B$6/1200,'Loan Prepayment'!$B$7*12,'Loan Prepayment'!$B$5),B364+E364)) -> 0 | E364: =IF(B364<=0,0,B364*C364/1200) -> 0 | F364: =MAX(0,D364-E364) -> 0 | G364: 0 | H364: =MAX(0,B364-F364-G364) -> 0 | I364: =I363+1 -> 363 | J364: =P363 -> 0 | K364: ='Loan Prepayment'!$B$6 -> 7.5 | L364: =IF(J364<=0,0,MIN(IF(AND('Loan Prepayment'!$E$15="Reduce EMI",O363>0),-PMT(K364/1200,MAX(1,'Loan Prepayment'!$B$7*12-I364+1),J364),L363),J364+M364)) -> 0 | M364: =IF(J364<=0,0,J364*K364/1200) -> 0 | N364: =MAX(0,L364-M364) -> 0 | O364: =IF(J364<=0,0,MIN(MAX(0,J364-N364),SUMIFS('Loan Prepayment'!$B$12:$B$31,'Loan Prepayment'!$A$12:$A$31,I364)+0)) -> 0 | P364: =MAX(0,J364-N364-O364) -> 0 | Q364: =Q363+1 -> 363 | R364: =X363 -> 0 | S364: ='Loan Prepayment'!$B$6 -> 7.5 | T364: =IF(R364<=0,0,MIN(IF(AND('Loan Prepayment'!$E$15="Reduce EMI",W363>0),-PMT(S364/1200,MAX(1,'Loan Prepayment'!$B$7*12-Q364+1),R364),T363),R364+U364)) -> 0 | U364: =IF(R364<=0,0,R364*S364/1200) -> 0 | V364: =MAX(0,T364-U364) -> 0 | W364: =IF(R364<=0,0,MIN(MAX(0,R364-V364),0+IF(AND(Q364>='Loan Prepayment'!$B$9,Q364<='Loan Prepayment'!$E$16),'Loan Prepayment'!$B$8,0))) -> 0 | X364: =MAX(0,R364-V364-W364) -> 0 | Y364: =Y363+1 -> 363 | Z364: =AF363 -> 0 | AA364: =IF(Y364>='Loan Prepayment'!$E$11,'Loan Prepayment'!$E$12,'Loan Prepayment'!$B$6) -> 6.5 | AB364: =IF(Z364<=0,0,MIN(IF(Y364='Loan Prepayment'!$E$11,IF('Loan Prepayment'!$E$13="Keep tenure, recalculate EMI",-PMT(AA364/1200,MAX(1,'Loan Prepayment'!$B$7*12-Y364+1),Z364),AB363),AB363),Z364+AC364)) -> 0 | AC364: =IF(Z364<=0,0,Z364*AA364/1200) -> 0 | AD364: =MAX(0,AB364-AC364) -> 0 | AE364: =IF(Z364<=0,0,MIN(MAX(0,Z364-AD364),0)) -> 0 | AF364: =MAX(0,Z364-AD364-AE364) -> 0 | AG364: =AG363+1 -> 363 | AH364: =AN363 -> 0 | AI364: =IF(AG364>='Loan Prepayment'!$E$11,'Loan Prepayment'!$E$12,'Loan Prepayment'!$B$6) -> 6.5 | AJ364: =IF(AH364<=0,0,MIN(IF(AG364='Loan Prepayment'!$E$11,IF('Loan Prepayment'!$E$13="Keep tenure, recalculate EMI",-PMT(AI364/1200,MAX(1,'Loan Prepayment'!$B$7*12-AG364+1),AH364),IF(AND('Loan Prepayment'!$E$15="Reduce EMI",AM363>0),-PMT(AI363/1200,MAX(1,'Loan Prepayment'!$B$7*12-AG364+1),AH364),AJ363)),IF(AND('Loan Prepayment'!$E$15="Reduce EMI",AM363>0),-PMT(AI364/1200,MAX(1,'Loan Prepayment'!$B$7*12-AG364+1),AH364),AJ363)),AH364+AK364)) -> 0 | AK364: =IF(AH364<=0,0,AH364*AI364/1200) -> 0 | AL364: =MAX(0,AJ364-AK364) -> 0 | AM364: =IF(AH364<=0,0,MIN(MAX(0,AH364-AL364),SUMIFS('Loan Prepayment'!$B$12:$B$31,'Loan Prepayment'!$A$12:$A$31,AG364)+IF(AND(AG364>='Loan Prepayment'!$B$9,AG364<='Loan Prepayment'!$E$16),'Loan Prepayment'!$B$8,0))) -> 0 | AN364: =MAX(0,AH364-AL364-AM364) -> 0
A365: =A364+1 -> 364 | B365: =H364 -> 0 | C365: ='Loan Prepayment'!$B$6 -> 7.5 | D365: =IF(B365<=0,0,MIN(-PMT('Loan Prepayment'!$B$6/1200,'Loan Prepayment'!$B$7*12,'Loan Prepayment'!$B$5),B365+E365)) -> 0 | E365: =IF(B365<=0,0,B365*C365/1200) -> 0 | F365: =MAX(0,D365-E365) -> 0 | G365: 0 | H365: =MAX(0,B365-F365-G365) -> 0 | I365: =I364+1 -> 364 | J365: =P364 -> 0 | K365: ='Loan Prepayment'!$B$6 -> 7.5 | L365: =IF(J365<=0,0,MIN(IF(AND('Loan Prepayment'!$E$15="Reduce EMI",O364>0),-PMT(K365/1200,MAX(1,'Loan Prepayment'!$B$7*12-I365+1),J365),L364),J365+M365)) -> 0 | M365: =IF(J365<=0,0,J365*K365/1200) -> 0 | N365: =MAX(0,L365-M365) -> 0 | O365: =IF(J365<=0,0,MIN(MAX(0,J365-N365),SUMIFS('Loan Prepayment'!$B$12:$B$31,'Loan Prepayment'!$A$12:$A$31,I365)+0)) -> 0 | P365: =MAX(0,J365-N365-O365) -> 0 | Q365: =Q364+1 -> 364 | R365: =X364 -> 0 | S365: ='Loan Prepayment'!$B$6 -> 7.5 | T365: =IF(R365<=0,0,MIN(IF(AND('Loan Prepayment'!$E$15="Reduce EMI",W364>0),-PMT(S365/1200,MAX(1,'Loan Prepayment'!$B$7*12-Q365+1),R365),T364),R365+U365)) -> 0 | U365: =IF(R365<=0,0,R365*S365/1200) -> 0 | V365: =MAX(0,T365-U365) -> 0 | W365: =IF(R365<=0,0,MIN(MAX(0,R365-V365),0+IF(AND(Q365>='Loan Prepayment'!$B$9,Q365<='Loan Prepayment'!$E$16),'Loan Prepayment'!$B$8,0))) -> 0 | X365: =MAX(0,R365-V365-W365) -> 0 | Y365: =Y364+1 -> 364 | Z365: =AF364 -> 0 | AA365: =IF(Y365>='Loan Prepayment'!$E$11,'Loan Prepayment'!$E$12,'Loan Prepayment'!$B$6) -> 6.5 | AB365: =IF(Z365<=0,0,MIN(IF(Y365='Loan Prepayment'!$E$11,IF('Loan Prepayment'!$E$13="Keep tenure, recalculate EMI",-PMT(AA365/1200,MAX(1,'Loan Prepayment'!$B$7*12-Y365+1),Z365),AB364),AB364),Z365+AC365)) -> 0 | AC365: =IF(Z365<=0,0,Z365*AA365/1200) -> 0 | AD365: =MAX(0,AB365-AC365) -> 0 | AE365: =IF(Z365<=0,0,MIN(MAX(0,Z365-AD365),0)) -> 0 | AF365: =MAX(0,Z365-AD365-AE365) -> 0 | AG365: =AG364+1 -> 364 | AH365: =AN364 -> 0 | AI365: =IF(AG365>='Loan Prepayment'!$E$11,'Loan Prepayment'!$E$12,'Loan Prepayment'!$B$6) -> 6.5 | AJ365: =IF(AH365<=0,0,MIN(IF(AG365='Loan Prepayment'!$E$11,IF('Loan Prepayment'!$E$13="Keep tenure, recalculate EMI",-PMT(AI365/1200,MAX(1,'Loan Prepayment'!$B$7*12-AG365+1),AH365),IF(AND('Loan Prepayment'!$E$15="Reduce EMI",AM364>0),-PMT(AI364/1200,MAX(1,'Loan Prepayment'!$B$7*12-AG365+1),AH365),AJ364)),IF(AND('Loan Prepayment'!$E$15="Reduce EMI",AM364>0),-PMT(AI365/1200,MAX(1,'Loan Prepayment'!$B$7*12-AG365+1),AH365),AJ364)),AH365+AK365)) -> 0 | AK365: =IF(AH365<=0,0,AH365*AI365/1200) -> 0 | AL365: =MAX(0,AJ365-AK365) -> 0 | AM365: =IF(AH365<=0,0,MIN(MAX(0,AH365-AL365),SUMIFS('Loan Prepayment'!$B$12:$B$31,'Loan Prepayment'!$A$12:$A$31,AG365)+IF(AND(AG365>='Loan Prepayment'!$B$9,AG365<='Loan Prepayment'!$E$16),'Loan Prepayment'!$B$8,0))) -> 0 | AN365: =MAX(0,AH365-AL365-AM365) -> 0
A366: =A365+1 -> 365 | B366: =H365 -> 0 | C366: ='Loan Prepayment'!$B$6 -> 7.5 | D366: =IF(B366<=0,0,MIN(-PMT('Loan Prepayment'!$B$6/1200,'Loan Prepayment'!$B$7*12,'Loan Prepayment'!$B$5),B366+E366)) -> 0 | E366: =IF(B366<=0,0,B366*C366/1200) -> 0 | F366: =MAX(0,D366-E366) -> 0 | G366: 0 | H366: =MAX(0,B366-F366-G366) -> 0 | I366: =I365+1 -> 365 | J366: =P365 -> 0 | K366: ='Loan Prepayment'!$B$6 -> 7.5 | L366: =IF(J366<=0,0,MIN(IF(AND('Loan Prepayment'!$E$15="Reduce EMI",O365>0),-PMT(K366/1200,MAX(1,'Loan Prepayment'!$B$7*12-I366+1),J366),L365),J366+M366)) -> 0 | M366: =IF(J366<=0,0,J366*K366/1200) -> 0 | N366: =MAX(0,L366-M366) -> 0 | O366: =IF(J366<=0,0,MIN(MAX(0,J366-N366),SUMIFS('Loan Prepayment'!$B$12:$B$31,'Loan Prepayment'!$A$12:$A$31,I366)+0)) -> 0 | P366: =MAX(0,J366-N366-O366) -> 0 | Q366: =Q365+1 -> 365 | R366: =X365 -> 0 | S366: ='Loan Prepayment'!$B$6 -> 7.5 | T366: =IF(R366<=0,0,MIN(IF(AND('Loan Prepayment'!$E$15="Reduce EMI",W365>0),-PMT(S366/1200,MAX(1,'Loan Prepayment'!$B$7*12-Q366+1),R366),T365),R366+U366)) -> 0 | U366: =IF(R366<=0,0,R366*S366/1200) -> 0 | V366: =MAX(0,T366-U366) -> 0 | W366: =IF(R366<=0,0,MIN(MAX(0,R366-V366),0+IF(AND(Q366>='Loan Prepayment'!$B$9,Q366<='Loan Prepayment'!$E$16),'Loan Prepayment'!$B$8,0))) -> 0 | X366: =MAX(0,R366-V366-W366) -> 0 | Y366: =Y365+1 -> 365 | Z366: =AF365 -> 0 | AA366: =IF(Y366>='Loan Prepayment'!$E$11,'Loan Prepayment'!$E$12,'Loan Prepayment'!$B$6) -> 6.5 | AB366: =IF(Z366<=0,0,MIN(IF(Y366='Loan Prepayment'!$E$11,IF('Loan Prepayment'!$E$13="Keep tenure, recalculate EMI",-PMT(AA366/1200,MAX(1,'Loan Prepayment'!$B$7*12-Y366+1),Z366),AB365),AB365),Z366+AC366)) -> 0 | AC366: =IF(Z366<=0,0,Z366*AA366/1200) -> 0 | AD366: =MAX(0,AB366-AC366) -> 0 | AE366: =IF(Z366<=0,0,MIN(MAX(0,Z366-AD366),0)) -> 0 | AF366: =MAX(0,Z366-AD366-AE366) -> 0 | AG366: =AG365+1 -> 365 | AH366: =AN365 -> 0 | AI366: =IF(AG366>='Loan Prepayment'!$E$11,'Loan Prepayment'!$E$12,'Loan Prepayment'!$B$6) -> 6.5 | AJ366: =IF(AH366<=0,0,MIN(IF(AG366='Loan Prepayment'!$E$11,IF('Loan Prepayment'!$E$13="Keep tenure, recalculate EMI",-PMT(AI366/1200,MAX(1,'Loan Prepayment'!$B$7*12-AG366+1),AH366),IF(AND('Loan Prepayment'!$E$15="Reduce EMI",AM365>0),-PMT(AI365/1200,MAX(1,'Loan Prepayment'!$B$7*12-AG366+1),AH366),AJ365)),IF(AND('Loan Prepayment'!$E$15="Reduce EMI",AM365>0),-PMT(AI366/1200,MAX(1,'Loan Prepayment'!$B$7*12-AG366+1),AH366),AJ365)),AH366+AK366)) -> 0 | AK366: =IF(AH366<=0,0,AH366*AI366/1200) -> 0 | AL366: =MAX(0,AJ366-AK366) -> 0 | AM366: =IF(AH366<=0,0,MIN(MAX(0,AH366-AL366),SUMIFS('Loan Prepayment'!$B$12:$B$31,'Loan Prepayment'!$A$12:$A$31,AG366)+IF(AND(AG366>='Loan Prepayment'!$B$9,AG366<='Loan Prepayment'!$E$16),'Loan Prepayment'!$B$8,0))) -> 0 | AN366: =MAX(0,AH366-AL366-AM366) -> 0
A367: =A366+1 -> 366 | B367: =H366 -> 0 | C367: ='Loan Prepayment'!$B$6 -> 7.5 | D367: =IF(B367<=0,0,MIN(-PMT('Loan Prepayment'!$B$6/1200,'Loan Prepayment'!$B$7*12,'Loan Prepayment'!$B$5),B367+E367)) -> 0 | E367: =IF(B367<=0,0,B367*C367/1200) -> 0 | F367: =MAX(0,D367-E367) -> 0 | G367: 0 | H367: =MAX(0,B367-F367-G367) -> 0 | I367: =I366+1 -> 366 | J367: =P366 -> 0 | K367: ='Loan Prepayment'!$B$6 -> 7.5 | L367: =IF(J367<=0,0,MIN(IF(AND('Loan Prepayment'!$E$15="Reduce EMI",O366>0),-PMT(K367/1200,MAX(1,'Loan Prepayment'!$B$7*12-I367+1),J367),L366),J367+M367)) -> 0 | M367: =IF(J367<=0,0,J367*K367/1200) -> 0 | N367: =MAX(0,L367-M367) -> 0 | O367: =IF(J367<=0,0,MIN(MAX(0,J367-N367),SUMIFS('Loan Prepayment'!$B$12:$B$31,'Loan Prepayment'!$A$12:$A$31,I367)+0)) -> 0 | P367: =MAX(0,J367-N367-O367) -> 0 | Q367: =Q366+1 -> 366 | R367: =X366 -> 0 | S367: ='Loan Prepayment'!$B$6 -> 7.5 | T367: =IF(R367<=0,0,MIN(IF(AND('Loan Prepayment'!$E$15="Reduce EMI",W366>0),-PMT(S367/1200,MAX(1,'Loan Prepayment'!$B$7*12-Q367+1),R367),T366),R367+U367)) -> 0 | U367: =IF(R367<=0,0,R367*S367/1200) -> 0 | V367: =MAX(0,T367-U367) -> 0 | W367: =IF(R367<=0,0,MIN(MAX(0,R367-V367),0+IF(AND(Q367>='Loan Prepayment'!$B$9,Q367<='Loan Prepayment'!$E$16),'Loan Prepayment'!$B$8,0))) -> 0 | X367: =MAX(0,R367-V367-W367) -> 0 | Y367: =Y366+1 -> 366 | Z367: =AF366 -> 0 | AA367: =IF(Y367>='Loan Prepayment'!$E$11,'Loan Prepayment'!$E$12,'Loan Prepayment'!$B$6) -> 6.5 | AB367: =IF(Z367<=0,0,MIN(IF(Y367='Loan Prepayment'!$E$11,IF('Loan Prepayment'!$E$13="Keep tenure, recalculate EMI",-PMT(AA367/1200,MAX(1,'Loan Prepayment'!$B$7*12-Y367+1),Z367),AB366),AB366),Z367+AC367)) -> 0 | AC367: =IF(Z367<=0,0,Z367*AA367/1200) -> 0 | AD367: =MAX(0,AB367-AC367) -> 0 | AE367: =IF(Z367<=0,0,MIN(MAX(0,Z367-AD367),0)) -> 0 | AF367: =MAX(0,Z367-AD367-AE367) -> 0 | AG367: =AG366+1 -> 366 | AH367: =AN366 -> 0 | AI367: =IF(AG367>='Loan Prepayment'!$E$11,'Loan Prepayment'!$E$12,'Loan Prepayment'!$B$6) -> 6.5 | AJ367: =IF(AH367<=0,0,MIN(IF(AG367='Loan Prepayment'!$E$11,IF('Loan Prepayment'!$E$13="Keep tenure, recalculate EMI",-PMT(AI367/1200,MAX(1,'Loan Prepayment'!$B$7*12-AG367+1),AH367),IF(AND('Loan Prepayment'!$E$15="Reduce EMI",AM366>0),-PMT(AI366/1200,MAX(1,'Loan Prepayment'!$B$7*12-AG367+1),AH367),AJ366)),IF(AND('Loan Prepayment'!$E$15="Reduce EMI",AM366>0),-PMT(AI367/1200,MAX(1,'Loan Prepayment'!$B$7*12-AG367+1),AH367),AJ366)),AH367+AK367)) -> 0 | AK367: =IF(AH367<=0,0,AH367*AI367/1200) -> 0 | AL367: =MAX(0,AJ367-AK367) -> 0 | AM367: =IF(AH367<=0,0,MIN(MAX(0,AH367-AL367),SUMIFS('Loan Prepayment'!$B$12:$B$31,'Loan Prepayment'!$A$12:$A$31,AG367)+IF(AND(AG367>='Loan Prepayment'!$B$9,AG367<='Loan Prepayment'!$E$16),'Loan Prepayment'!$B$8,0))) -> 0 | AN367: =MAX(0,AH367-AL367-AM367) -> 0
A368: =A367+1 -> 367 | B368: =H367 -> 0 | C368: ='Loan Prepayment'!$B$6 -> 7.5 | D368: =IF(B368<=0,0,MIN(-PMT('Loan Prepayment'!$B$6/1200,'Loan Prepayment'!$B$7*12,'Loan Prepayment'!$B$5),B368+E368)) -> 0 | E368: =IF(B368<=0,0,B368*C368/1200) -> 0 | F368: =MAX(0,D368-E368) -> 0 | G368: 0 | H368: =MAX(0,B368-F368-G368) -> 0 | I368: =I367+1 -> 367 | J368: =P367 -> 0 | K368: ='Loan Prepayment'!$B$6 -> 7.5 | L368: =IF(J368<=0,0,MIN(IF(AND('Loan Prepayment'!$E$15="Reduce EMI",O367>0),-PMT(K368/1200,MAX(1,'Loan Prepayment'!$B$7*12-I368+1),J368),L367),J368+M368)) -> 0 | M368: =IF(J368<=0,0,J368*K368/1200) -> 0 | N368: =MAX(0,L368-M368) -> 0 | O368: =IF(J368<=0,0,MIN(MAX(0,J368-N368),SUMIFS('Loan Prepayment'!$B$12:$B$31,'Loan Prepayment'!$A$12:$A$31,I368)+0)) -> 0 | P368: =MAX(0,J368-N368-O368) -> 0 | Q368: =Q367+1 -> 367 | R368: =X367 -> 0 | S368: ='Loan Prepayment'!$B$6 -> 7.5 | T368: =IF(R368<=0,0,MIN(IF(AND('Loan Prepayment'!$E$15="Reduce EMI",W367>0),-PMT(S368/1200,MAX(1,'Loan Prepayment'!$B$7*12-Q368+1),R368),T367),R368+U368)) -> 0 | U368: =IF(R368<=0,0,R368*S368/1200) -> 0 | V368: =MAX(0,T368-U368) -> 0 | W368: =IF(R368<=0,0,MIN(MAX(0,R368-V368),0+IF(AND(Q368>='Loan Prepayment'!$B$9,Q368<='Loan Prepayment'!$E$16),'Loan Prepayment'!$B$8,0))) -> 0 | X368: =MAX(0,R368-V368-W368) -> 0 | Y368: =Y367+1 -> 367 | Z368: =AF367 -> 0 | AA368: =IF(Y368>='Loan Prepayment'!$E$11,'Loan Prepayment'!$E$12,'Loan Prepayment'!$B$6) -> 6.5 | AB368: =IF(Z368<=0,0,MIN(IF(Y368='Loan Prepayment'!$E$11,IF('Loan Prepayment'!$E$13="Keep tenure, recalculate EMI",-PMT(AA368/1200,MAX(1,'Loan Prepayment'!$B$7*12-Y368+1),Z368),AB367),AB367),Z368+AC368)) -> 0 | AC368: =IF(Z368<=0,0,Z368*AA368/1200) -> 0 | AD368: =MAX(0,AB368-AC368) -> 0 | AE368: =IF(Z368<=0,0,MIN(MAX(0,Z368-AD368),0)) -> 0 | AF368: =MAX(0,Z368-AD368-AE368) -> 0 | AG368: =AG367+1 -> 367 | AH368: =AN367 -> 0 | AI368: =IF(AG368>='Loan Prepayment'!$E$11,'Loan Prepayment'!$E$12,'Loan Prepayment'!$B$6) -> 6.5 | AJ368: =IF(AH368<=0,0,MIN(IF(AG368='Loan Prepayment'!$E$11,IF('Loan Prepayment'!$E$13="Keep tenure, recalculate EMI",-PMT(AI368/1200,MAX(1,'Loan Prepayment'!$B$7*12-AG368+1),AH368),IF(AND('Loan Prepayment'!$E$15="Reduce EMI",AM367>0),-PMT(AI367/1200,MAX(1,'Loan Prepayment'!$B$7*12-AG368+1),AH368),AJ367)),IF(AND('Loan Prepayment'!$E$15="Reduce EMI",AM367>0),-PMT(AI368/1200,MAX(1,'Loan Prepayment'!$B$7*12-AG368+1),AH368),AJ367)),AH368+AK368)) -> 0 | AK368: =IF(AH368<=0,0,AH368*AI368/1200) -> 0 | AL368: =MAX(0,AJ368-AK368) -> 0 | AM368: =IF(AH368<=0,0,MIN(MAX(0,AH368-AL368),SUMIFS('Loan Prepayment'!$B$12:$B$31,'Loan Prepayment'!$A$12:$A$31,AG368)+IF(AND(AG368>='Loan Prepayment'!$B$9,AG368<='Loan Prepayment'!$E$16),'Loan Prepayment'!$B$8,0))) -> 0 | AN368: =MAX(0,AH368-AL368-AM368) -> 0
A369: =A368+1 -> 368 | B369: =H368 -> 0 | C369: ='Loan Prepayment'!$B$6 -> 7.5 | D369: =IF(B369<=0,0,MIN(-PMT('Loan Prepayment'!$B$6/1200,'Loan Prepayment'!$B$7*12,'Loan Prepayment'!$B$5),B369+E369)) -> 0 | E369: =IF(B369<=0,0,B369*C369/1200) -> 0 | F369: =MAX(0,D369-E369) -> 0 | G369: 0 | H369: =MAX(0,B369-F369-G369) -> 0 | I369: =I368+1 -> 368 | J369: =P368 -> 0 | K369: ='Loan Prepayment'!$B$6 -> 7.5 | L369: =IF(J369<=0,0,MIN(IF(AND('Loan Prepayment'!$E$15="Reduce EMI",O368>0),-PMT(K369/1200,MAX(1,'Loan Prepayment'!$B$7*12-I369+1),J369),L368),J369+M369)) -> 0 | M369: =IF(J369<=0,0,J369*K369/1200) -> 0 | N369: =MAX(0,L369-M369) -> 0 | O369: =IF(J369<=0,0,MIN(MAX(0,J369-N369),SUMIFS('Loan Prepayment'!$B$12:$B$31,'Loan Prepayment'!$A$12:$A$31,I369)+0)) -> 0 | P369: =MAX(0,J369-N369-O369) -> 0 | Q369: =Q368+1 -> 368 | R369: =X368 -> 0 | S369: ='Loan Prepayment'!$B$6 -> 7.5 | T369: =IF(R369<=0,0,MIN(IF(AND('Loan Prepayment'!$E$15="Reduce EMI",W368>0),-PMT(S369/1200,MAX(1,'Loan Prepayment'!$B$7*12-Q369+1),R369),T368),R369+U369)) -> 0 | U369: =IF(R369<=0,0,R369*S369/1200) -> 0 | V369: =MAX(0,T369-U369) -> 0 | W369: =IF(R369<=0,0,MIN(MAX(0,R369-V369),0+IF(AND(Q369>='Loan Prepayment'!$B$9,Q369<='Loan Prepayment'!$E$16),'Loan Prepayment'!$B$8,0))) -> 0 | X369: =MAX(0,R369-V369-W369) -> 0 | Y369: =Y368+1 -> 368 | Z369: =AF368 -> 0 | AA369: =IF(Y369>='Loan Prepayment'!$E$11,'Loan Prepayment'!$E$12,'Loan Prepayment'!$B$6) -> 6.5 | AB369: =IF(Z369<=0,0,MIN(IF(Y369='Loan Prepayment'!$E$11,IF('Loan Prepayment'!$E$13="Keep tenure, recalculate EMI",-PMT(AA369/1200,MAX(1,'Loan Prepayment'!$B$7*12-Y369+1),Z369),AB368),AB368),Z369+AC369)) -> 0 | AC369: =IF(Z369<=0,0,Z369*AA369/1200) -> 0 | AD369: =MAX(0,AB369-AC369) -> 0 | AE369: =IF(Z369<=0,0,MIN(MAX(0,Z369-AD369),0)) -> 0 | AF369: =MAX(0,Z369-AD369-AE369) -> 0 | AG369: =AG368+1 -> 368 | AH369: =AN368 -> 0 | AI369: =IF(AG369>='Loan Prepayment'!$E$11,'Loan Prepayment'!$E$12,'Loan Prepayment'!$B$6) -> 6.5 | AJ369: =IF(AH369<=0,0,MIN(IF(AG369='Loan Prepayment'!$E$11,IF('Loan Prepayment'!$E$13="Keep tenure, recalculate EMI",-PMT(AI369/1200,MAX(1,'Loan Prepayment'!$B$7*12-AG369+1),AH369),IF(AND('Loan Prepayment'!$E$15="Reduce EMI",AM368>0),-PMT(AI368/1200,MAX(1,'Loan Prepayment'!$B$7*12-AG369+1),AH369),AJ368)),IF(AND('Loan Prepayment'!$E$15="Reduce EMI",AM368>0),-PMT(AI369/1200,MAX(1,'Loan Prepayment'!$B$7*12-AG369+1),AH369),AJ368)),AH369+AK369)) -> 0 | AK369: =IF(AH369<=0,0,AH369*AI369/1200) -> 0 | AL369: =MAX(0,AJ369-AK369) -> 0 | AM369: =IF(AH369<=0,0,MIN(MAX(0,AH369-AL369),SUMIFS('Loan Prepayment'!$B$12:$B$31,'Loan Prepayment'!$A$12:$A$31,AG369)+IF(AND(AG369>='Loan Prepayment'!$B$9,AG369<='Loan Prepayment'!$E$16),'Loan Prepayment'!$B$8,0))) -> 0 | AN369: =MAX(0,AH369-AL369-AM369) -> 0
A370: =A369+1 -> 369 | B370: =H369 -> 0 | C370: ='Loan Prepayment'!$B$6 -> 7.5 | D370: =IF(B370<=0,0,MIN(-PMT('Loan Prepayment'!$B$6/1200,'Loan Prepayment'!$B$7*12,'Loan Prepayment'!$B$5),B370+E370)) -> 0 | E370: =IF(B370<=0,0,B370*C370/1200) -> 0 | F370: =MAX(0,D370-E370) -> 0 | G370: 0 | H370: =MAX(0,B370-F370-G370) -> 0 | I370: =I369+1 -> 369 | J370: =P369 -> 0 | K370: ='Loan Prepayment'!$B$6 -> 7.5 | L370: =IF(J370<=0,0,MIN(IF(AND('Loan Prepayment'!$E$15="Reduce EMI",O369>0),-PMT(K370/1200,MAX(1,'Loan Prepayment'!$B$7*12-I370+1),J370),L369),J370+M370)) -> 0 | M370: =IF(J370<=0,0,J370*K370/1200) -> 0 | N370: =MAX(0,L370-M370) -> 0 | O370: =IF(J370<=0,0,MIN(MAX(0,J370-N370),SUMIFS('Loan Prepayment'!$B$12:$B$31,'Loan Prepayment'!$A$12:$A$31,I370)+0)) -> 0 | P370: =MAX(0,J370-N370-O370) -> 0 | Q370: =Q369+1 -> 369 | R370: =X369 -> 0 | S370: ='Loan Prepayment'!$B$6 -> 7.5 | T370: =IF(R370<=0,0,MIN(IF(AND('Loan Prepayment'!$E$15="Reduce EMI",W369>0),-PMT(S370/1200,MAX(1,'Loan Prepayment'!$B$7*12-Q370+1),R370),T369),R370+U370)) -> 0 | U370: =IF(R370<=0,0,R370*S370/1200) -> 0 | V370: =MAX(0,T370-U370) -> 0 | W370: =IF(R370<=0,0,MIN(MAX(0,R370-V370),0+IF(AND(Q370>='Loan Prepayment'!$B$9,Q370<='Loan Prepayment'!$E$16),'Loan Prepayment'!$B$8,0))) -> 0 | X370: =MAX(0,R370-V370-W370) -> 0 | Y370: =Y369+1 -> 369 | Z370: =AF369 -> 0 | AA370: =IF(Y370>='Loan Prepayment'!$E$11,'Loan Prepayment'!$E$12,'Loan Prepayment'!$B$6) -> 6.5 | AB370: =IF(Z370<=0,0,MIN(IF(Y370='Loan Prepayment'!$E$11,IF('Loan Prepayment'!$E$13="Keep tenure, recalculate EMI",-PMT(AA370/1200,MAX(1,'Loan Prepayment'!$B$7*12-Y370+1),Z370),AB369),AB369),Z370+AC370)) -> 0 | AC370: =IF(Z370<=0,0,Z370*AA370/1200) -> 0 | AD370: =MAX(0,AB370-AC370) -> 0 | AE370: =IF(Z370<=0,0,MIN(MAX(0,Z370-AD370),0)) -> 0 | AF370: =MAX(0,Z370-AD370-AE370) -> 0 | AG370: =AG369+1 -> 369 | AH370: =AN369 -> 0 | AI370: =IF(AG370>='Loan Prepayment'!$E$11,'Loan Prepayment'!$E$12,'Loan Prepayment'!$B$6) -> 6.5 | AJ370: =IF(AH370<=0,0,MIN(IF(AG370='Loan Prepayment'!$E$11,IF('Loan Prepayment'!$E$13="Keep tenure, recalculate EMI",-PMT(AI370/1200,MAX(1,'Loan Prepayment'!$B$7*12-AG370+1),AH370),IF(AND('Loan Prepayment'!$E$15="Reduce EMI",AM369>0),-PMT(AI369/1200,MAX(1,'Loan Prepayment'!$B$7*12-AG370+1),AH370),AJ369)),IF(AND('Loan Prepayment'!$E$15="Reduce EMI",AM369>0),-PMT(AI370/1200,MAX(1,'Loan Prepayment'!$B$7*12-AG370+1),AH370),AJ369)),AH370+AK370)) -> 0 | AK370: =IF(AH370<=0,0,AH370*AI370/1200) -> 0 | AL370: =MAX(0,AJ370-AK370) -> 0 | AM370: =IF(AH370<=0,0,MIN(MAX(0,AH370-AL370),SUMIFS('Loan Prepayment'!$B$12:$B$31,'Loan Prepayment'!$A$12:$A$31,AG370)+IF(AND(AG370>='Loan Prepayment'!$B$9,AG370<='Loan Prepayment'!$E$16),'Loan Prepayment'!$B$8,0))) -> 0 | AN370: =MAX(0,AH370-AL370-AM370) -> 0
A371: =A370+1 -> 370 | B371: =H370 -> 0 | C371: ='Loan Prepayment'!$B$6 -> 7.5 | D371: =IF(B371<=0,0,MIN(-PMT('Loan Prepayment'!$B$6/1200,'Loan Prepayment'!$B$7*12,'Loan Prepayment'!$B$5),B371+E371)) -> 0 | E371: =IF(B371<=0,0,B371*C371/1200) -> 0 | F371: =MAX(0,D371-E371) -> 0 | G371: 0 | H371: =MAX(0,B371-F371-G371) -> 0 | I371: =I370+1 -> 370 | J371: =P370 -> 0 | K371: ='Loan Prepayment'!$B$6 -> 7.5 | L371: =IF(J371<=0,0,MIN(IF(AND('Loan Prepayment'!$E$15="Reduce EMI",O370>0),-PMT(K371/1200,MAX(1,'Loan Prepayment'!$B$7*12-I371+1),J371),L370),J371+M371)) -> 0 | M371: =IF(J371<=0,0,J371*K371/1200) -> 0 | N371: =MAX(0,L371-M371) -> 0 | O371: =IF(J371<=0,0,MIN(MAX(0,J371-N371),SUMIFS('Loan Prepayment'!$B$12:$B$31,'Loan Prepayment'!$A$12:$A$31,I371)+0)) -> 0 | P371: =MAX(0,J371-N371-O371) -> 0 | Q371: =Q370+1 -> 370 | R371: =X370 -> 0 | S371: ='Loan Prepayment'!$B$6 -> 7.5 | T371: =IF(R371<=0,0,MIN(IF(AND('Loan Prepayment'!$E$15="Reduce EMI",W370>0),-PMT(S371/1200,MAX(1,'Loan Prepayment'!$B$7*12-Q371+1),R371),T370),R371+U371)) -> 0 | U371: =IF(R371<=0,0,R371*S371/1200) -> 0 | V371: =MAX(0,T371-U371) -> 0 | W371: =IF(R371<=0,0,MIN(MAX(0,R371-V371),0+IF(AND(Q371>='Loan Prepayment'!$B$9,Q371<='Loan Prepayment'!$E$16),'Loan Prepayment'!$B$8,0))) -> 0 | X371: =MAX(0,R371-V371-W371) -> 0 | Y371: =Y370+1 -> 370 | Z371: =AF370 -> 0 | AA371: =IF(Y371>='Loan Prepayment'!$E$11,'Loan Prepayment'!$E$12,'Loan Prepayment'!$B$6) -> 6.5 | AB371: =IF(Z371<=0,0,MIN(IF(Y371='Loan Prepayment'!$E$11,IF('Loan Prepayment'!$E$13="Keep tenure, recalculate EMI",-PMT(AA371/1200,MAX(1,'Loan Prepayment'!$B$7*12-Y371+1),Z371),AB370),AB370),Z371+AC371)) -> 0 | AC371: =IF(Z371<=0,0,Z371*AA371/1200) -> 0 | AD371: =MAX(0,AB371-AC371) -> 0 | AE371: =IF(Z371<=0,0,MIN(MAX(0,Z371-AD371),0)) -> 0 | AF371: =MAX(0,Z371-AD371-AE371) -> 0 | AG371: =AG370+1 -> 370 | AH371: =AN370 -> 0 | AI371: =IF(AG371>='Loan Prepayment'!$E$11,'Loan Prepayment'!$E$12,'Loan Prepayment'!$B$6) -> 6.5 | AJ371: =IF(AH371<=0,0,MIN(IF(AG371='Loan Prepayment'!$E$11,IF('Loan Prepayment'!$E$13="Keep tenure, recalculate EMI",-PMT(AI371/1200,MAX(1,'Loan Prepayment'!$B$7*12-AG371+1),AH371),IF(AND('Loan Prepayment'!$E$15="Reduce EMI",AM370>0),-PMT(AI370/1200,MAX(1,'Loan Prepayment'!$B$7*12-AG371+1),AH371),AJ370)),IF(AND('Loan Prepayment'!$E$15="Reduce EMI",AM370>0),-PMT(AI371/1200,MAX(1,'Loan Prepayment'!$B$7*12-AG371+1),AH371),AJ370)),AH371+AK371)) -> 0 | AK371: =IF(AH371<=0,0,AH371*AI371/1200) -> 0 | AL371: =MAX(0,AJ371-AK371) -> 0 | AM371: =IF(AH371<=0,0,MIN(MAX(0,AH371-AL371),SUMIFS('Loan Prepayment'!$B$12:$B$31,'Loan Prepayment'!$A$12:$A$31,AG371)+IF(AND(AG371>='Loan Prepayment'!$B$9,AG371<='Loan Prepayment'!$E$16),'Loan Prepayment'!$B$8,0))) -> 0 | AN371: =MAX(0,AH371-AL371-AM371) -> 0
A372: =A371+1 -> 371 | B372: =H371 -> 0 | C372: ='Loan Prepayment'!$B$6 -> 7.5 | D372: =IF(B372<=0,0,MIN(-PMT('Loan Prepayment'!$B$6/1200,'Loan Prepayment'!$B$7*12,'Loan Prepayment'!$B$5),B372+E372)) -> 0 | E372: =IF(B372<=0,0,B372*C372/1200) -> 0 | F372: =MAX(0,D372-E372) -> 0 | G372: 0 | H372: =MAX(0,B372-F372-G372) -> 0 | I372: =I371+1 -> 371 | J372: =P371 -> 0 | K372: ='Loan Prepayment'!$B$6 -> 7.5 | L372: =IF(J372<=0,0,MIN(IF(AND('Loan Prepayment'!$E$15="Reduce EMI",O371>0),-PMT(K372/1200,MAX(1,'Loan Prepayment'!$B$7*12-I372+1),J372),L371),J372+M372)) -> 0 | M372: =IF(J372<=0,0,J372*K372/1200) -> 0 | N372: =MAX(0,L372-M372) -> 0 | O372: =IF(J372<=0,0,MIN(MAX(0,J372-N372),SUMIFS('Loan Prepayment'!$B$12:$B$31,'Loan Prepayment'!$A$12:$A$31,I372)+0)) -> 0 | P372: =MAX(0,J372-N372-O372) -> 0 | Q372: =Q371+1 -> 371 | R372: =X371 -> 0 | S372: ='Loan Prepayment'!$B$6 -> 7.5 | T372: =IF(R372<=0,0,MIN(IF(AND('Loan Prepayment'!$E$15="Reduce EMI",W371>0),-PMT(S372/1200,MAX(1,'Loan Prepayment'!$B$7*12-Q372+1),R372),T371),R372+U372)) -> 0 | U372: =IF(R372<=0,0,R372*S372/1200) -> 0 | V372: =MAX(0,T372-U372) -> 0 | W372: =IF(R372<=0,0,MIN(MAX(0,R372-V372),0+IF(AND(Q372>='Loan Prepayment'!$B$9,Q372<='Loan Prepayment'!$E$16),'Loan Prepayment'!$B$8,0))) -> 0 | X372: =MAX(0,R372-V372-W372) -> 0 | Y372: =Y371+1 -> 371 | Z372: =AF371 -> 0 | AA372: =IF(Y372>='Loan Prepayment'!$E$11,'Loan Prepayment'!$E$12,'Loan Prepayment'!$B$6) -> 6.5 | AB372: =IF(Z372<=0,0,MIN(IF(Y372='Loan Prepayment'!$E$11,IF('Loan Prepayment'!$E$13="Keep tenure, recalculate EMI",-PMT(AA372/1200,MAX(1,'Loan Prepayment'!$B$7*12-Y372+1),Z372),AB371),AB371),Z372+AC372)) -> 0 | AC372: =IF(Z372<=0,0,Z372*AA372/1200) -> 0 | AD372: =MAX(0,AB372-AC372) -> 0 | AE372: =IF(Z372<=0,0,MIN(MAX(0,Z372-AD372),0)) -> 0 | AF372: =MAX(0,Z372-AD372-AE372) -> 0 | AG372: =AG371+1 -> 371 | AH372: =AN371 -> 0 | AI372: =IF(AG372>='Loan Prepayment'!$E$11,'Loan Prepayment'!$E$12,'Loan Prepayment'!$B$6) -> 6.5 | AJ372: =IF(AH372<=0,0,MIN(IF(AG372='Loan Prepayment'!$E$11,IF('Loan Prepayment'!$E$13="Keep tenure, recalculate EMI",-PMT(AI372/1200,MAX(1,'Loan Prepayment'!$B$7*12-AG372+1),AH372),IF(AND('Loan Prepayment'!$E$15="Reduce EMI",AM371>0),-PMT(AI371/1200,MAX(1,'Loan Prepayment'!$B$7*12-AG372+1),AH372),AJ371)),IF(AND('Loan Prepayment'!$E$15="Reduce EMI",AM371>0),-PMT(AI372/1200,MAX(1,'Loan Prepayment'!$B$7*12-AG372+1),AH372),AJ371)),AH372+AK372)) -> 0 | AK372: =IF(AH372<=0,0,AH372*AI372/1200) -> 0 | AL372: =MAX(0,AJ372-AK372) -> 0 | AM372: =IF(AH372<=0,0,MIN(MAX(0,AH372-AL372),SUMIFS('Loan Prepayment'!$B$12:$B$31,'Loan Prepayment'!$A$12:$A$31,AG372)+IF(AND(AG372>='Loan Prepayment'!$B$9,AG372<='Loan Prepayment'!$E$16),'Loan Prepayment'!$B$8,0))) -> 0 | AN372: =MAX(0,AH372-AL372-AM372) -> 0
A373: =A372+1 -> 372 | B373: =H372 -> 0 | C373: ='Loan Prepayment'!$B$6 -> 7.5 | D373: =IF(B373<=0,0,MIN(-PMT('Loan Prepayment'!$B$6/1200,'Loan Prepayment'!$B$7*12,'Loan Prepayment'!$B$5),B373+E373)) -> 0 | E373: =IF(B373<=0,0,B373*C373/1200) -> 0 | F373: =MAX(0,D373-E373) -> 0 | G373: 0 | H373: =MAX(0,B373-F373-G373) -> 0 | I373: =I372+1 -> 372 | J373: =P372 -> 0 | K373: ='Loan Prepayment'!$B$6 -> 7.5 | L373: =IF(J373<=0,0,MIN(IF(AND('Loan Prepayment'!$E$15="Reduce EMI",O372>0),-PMT(K373/1200,MAX(1,'Loan Prepayment'!$B$7*12-I373+1),J373),L372),J373+M373)) -> 0 | M373: =IF(J373<=0,0,J373*K373/1200) -> 0 | N373: =MAX(0,L373-M373) -> 0 | O373: =IF(J373<=0,0,MIN(MAX(0,J373-N373),SUMIFS('Loan Prepayment'!$B$12:$B$31,'Loan Prepayment'!$A$12:$A$31,I373)+0)) -> 0 | P373: =MAX(0,J373-N373-O373) -> 0 | Q373: =Q372+1 -> 372 | R373: =X372 -> 0 | S373: ='Loan Prepayment'!$B$6 -> 7.5 | T373: =IF(R373<=0,0,MIN(IF(AND('Loan Prepayment'!$E$15="Reduce EMI",W372>0),-PMT(S373/1200,MAX(1,'Loan Prepayment'!$B$7*12-Q373+1),R373),T372),R373+U373)) -> 0 | U373: =IF(R373<=0,0,R373*S373/1200) -> 0 | V373: =MAX(0,T373-U373) -> 0 | W373: =IF(R373<=0,0,MIN(MAX(0,R373-V373),0+IF(AND(Q373>='Loan Prepayment'!$B$9,Q373<='Loan Prepayment'!$E$16),'Loan Prepayment'!$B$8,0))) -> 0 | X373: =MAX(0,R373-V373-W373) -> 0 | Y373: =Y372+1 -> 372 | Z373: =AF372 -> 0 | AA373: =IF(Y373>='Loan Prepayment'!$E$11,'Loan Prepayment'!$E$12,'Loan Prepayment'!$B$6) -> 6.5 | AB373: =IF(Z373<=0,0,MIN(IF(Y373='Loan Prepayment'!$E$11,IF('Loan Prepayment'!$E$13="Keep tenure, recalculate EMI",-PMT(AA373/1200,MAX(1,'Loan Prepayment'!$B$7*12-Y373+1),Z373),AB372),AB372),Z373+AC373)) -> 0 | AC373: =IF(Z373<=0,0,Z373*AA373/1200) -> 0 | AD373: =MAX(0,AB373-AC373) -> 0 | AE373: =IF(Z373<=0,0,MIN(MAX(0,Z373-AD373),0)) -> 0 | AF373: =MAX(0,Z373-AD373-AE373) -> 0 | AG373: =AG372+1 -> 372 | AH373: =AN372 -> 0 | AI373: =IF(AG373>='Loan Prepayment'!$E$11,'Loan Prepayment'!$E$12,'Loan Prepayment'!$B$6) -> 6.5 | AJ373: =IF(AH373<=0,0,MIN(IF(AG373='Loan Prepayment'!$E$11,IF('Loan Prepayment'!$E$13="Keep tenure, recalculate EMI",-PMT(AI373/1200,MAX(1,'Loan Prepayment'!$B$7*12-AG373+1),AH373),IF(AND('Loan Prepayment'!$E$15="Reduce EMI",AM372>0),-PMT(AI372/1200,MAX(1,'Loan Prepayment'!$B$7*12-AG373+1),AH373),AJ372)),IF(AND('Loan Prepayment'!$E$15="Reduce EMI",AM372>0),-PMT(AI373/1200,MAX(1,'Loan Prepayment'!$B$7*12-AG373+1),AH373),AJ372)),AH373+AK373)) -> 0 | AK373: =IF(AH373<=0,0,AH373*AI373/1200) -> 0 | AL373: =MAX(0,AJ373-AK373) -> 0 | AM373: =IF(AH373<=0,0,MIN(MAX(0,AH373-AL373),SUMIFS('Loan Prepayment'!$B$12:$B$31,'Loan Prepayment'!$A$12:$A$31,AG373)+IF(AND(AG373>='Loan Prepayment'!$B$9,AG373<='Loan Prepayment'!$E$16),'Loan Prepayment'!$B$8,0))) -> 0 | AN373: =MAX(0,AH373-AL373-AM373) -> 0
... A481: =A480+1 -> 480 | B481: =H480 -> 0 | C481: ='Loan Prepayment'!$B$6 -> 7.5 | D481: =IF(B481<=0,0,MIN(-PMT('Loan Prepayment'!$B$6/1200,'Loan Prepayment'!$B$7*12,'Loan Prepayment'!$B$5),B481+E481)) -> 0 | E481: =IF(B481<=0,0,B481*C481/1200) -> 0 | F481: =MAX(0,D481-E481) -> 0 | G481: 0 | H481: =MAX(0,B481-F481-G481) -> 0 | I481: =I480+1 -> 480 | J481: =P480 -> 0 | K481: ='Loan Prepayment'!$B$6 -> 7.5 | L481: =IF(J481<=0,0,MIN(IF(AND('Loan Prepayment'!$E$15="Reduce EMI",O480>0),-PMT(K481/1200,MAX(1,'Loan Prepayment'!$B$7*12-I481+1),J481),L480),J481+M481)) -> 0 | M481: =IF(J481<=0,0,J481*K481/1200) -> 0 | N481: =MAX(0,L481-M481) -> 0 | O481: =IF(J481<=0,0,MIN(MAX(0,J481-N481),SUMIFS('Loan Prepayment'!$B$12:$B$31,'Loan Prepayment'!$A$12:$A$31,I481)+0)) -> 0 | P481: =MAX(0,J481-N481-O481) -> 0 | Q481: =Q480+1 -> 480 | R481: =X480 -> 0 | S481: ='Loan Prepayment'!$B$6 -> 7.5 | T481: =IF(R481<=0,0,MIN(IF(AND('Loan Prepayment'!$E$15="Reduce EMI",W480>0),-PMT(S481/1200,MAX(1,'Loan Prepayment'!$B$7*12-Q481+1),R481),T480),R481+U481)) -> 0 | U481: =IF(R481<=0,0,R481*S481/1200) -> 0 | V481: =MAX(0,T481-U481) -> 0 | W481: =IF(R481<=0,0,MIN(MAX(0,R481-V481),0+IF(AND(Q481>='Loan Prepayment'!$B$9,Q481<='Loan Prepayment'!$E$16),'Loan Prepayment'!$B$8,0))) -> 0 | X481: =MAX(0,R481-V481-W481) -> 0 | Y481: =Y480+1 -> 480 | Z481: =AF480 -> 0 | AA481: =IF(Y481>='Loan Prepayment'!$E$11,'Loan Prepayment'!$E$12,'Loan Prepayment'!$B$6) -> 6.5 | AB481: =IF(Z481<=0,0,MIN(IF(Y481='Loan Prepayment'!$E$11,IF('Loan Prepayment'!$E$13="Keep tenure, recalculate EMI",-PMT(AA481/1200,MAX(1,'Loan Prepayment'!$B$7*12-Y481+1),Z481),AB480),AB480),Z481+AC481)) -> 0 | AC481: =IF(Z481<=0,0,Z481*AA481/1200) -> 0 | AD481: =MAX(0,AB481-AC481) -> 0 | AE481: =IF(Z481<=0,0,MIN(MAX(0,Z481-AD481),0)) -> 0 | AF481: =MAX(0,Z481-AD481-AE481) -> 0 | AG481: =AG480+1 -> 480 | AH481: =AN480 -> 0 | AI481: =IF(AG481>='Loan Prepayment'!$E$11,'Loan Prepayment'!$E$12,'Loan Prepayment'!$B$6) -> 6.5 | AJ481: =IF(AH481<=0,0,MIN(IF(AG481='Loan Prepayment'!$E$11,IF('Loan Prepayment'!$E$13="Keep tenure, recalculate EMI",-PMT(AI481/1200,MAX(1,'Loan Prepayment'!$B$7*12-AG481+1),AH481),IF(AND('Loan Prepayment'!$E$15="Reduce EMI",AM480>0),-PMT(AI480/1200,MAX(1,'Loan Prepayment'!$B$7*12-AG481+1),AH481),AJ480)),IF(AND('Loan Prepayment'!$E$15="Reduce EMI",AM480>0),-PMT(AI481/1200,MAX(1,'Loan Prepayment'!$B$7*12-AG481+1),AH481),AJ480)),AH481+AK481)) -> 0 | AK481: =IF(AH481<=0,0,AH481*AI481/1200) -> 0 | AL481: =MAX(0,AJ481-AK481) -> 0 | AM481: =IF(AH481<=0,0,MIN(MAX(0,AH481-AL481),SUMIFS('Loan Prepayment'!$B$12:$B$31,'Loan Prepayment'!$A$12:$A$31,AG481)+IF(AND(AG481>='Loan Prepayment'!$B$9,AG481<='Loan Prepayment'!$E$16),'Loan Prepayment'!$B$8,0))) -> 0 | AN481: =MAX(0,AH481-AL481-AM481) -> 0

Sheet Step-Up SIP Goal
A1: STEP-UP SIP GOAL PLANNER
A2: Estimate the starting monthly SIP and annual increase needed to fund a future goal after inflation and simplified long-term capital-gains tax.
A4: GOAL & INVESTMENT INPUTS | D4: GOAL FUNDING SUMMARY | H4: HOW TO READ THE RESULT
A5: Goal Type | B5: Retirement | D5: Inflation-Adjusted Goal | E5: =$B$6*(1+$B$8/100)^$B$7 -> 32071355 | H5: 1. Goal cost is entered in today’s rupees; inflation converts it into the future amount required.
A6: Goal Cost Today (₹) | B6: 10000000 | D6: Future Value of Current Corpus | E6: =$B$9*(1+$B$10/1200)^($B$7*12) -> 0 | H6: 2. Required starting SIP increases annually by the selected step-up percentage.
A7: Years to Goal | B7: 20 | D7: Required Starting Monthly SIP | E7: =IF($N$52<=$B$13,$N$51,$N$53) -> 17720.679 | H7: 3. Return, inflation and tax are assumptions—not guaranteed outcomes.
A8: Inflation (% p.a.) | B8: ='Common Assumptions'!$B$5 -> 6 | D8: First-Year Contribution | E8: =$E$7*12 -> 212648.15 | H8: 4. Tax assumes one final redemption and qualifying gains above the selected exemption.
A9: Current Invested Corpus (₹) | B9: 0 | D9: Final-Year Monthly SIP | E9: =$E$7*(1+$B$11/100)^($B$7-1) -> 108378.06 | H9: 5. Current corpus is treated as invested today and as part of the tax cost basis.
A10: Expected Return (% p.a.) | B10: ='Common Assumptions'!$B$6 -> 12 | D10: Total Contributions | E10: =$B$9+SUM($D$18:INDEX($D$18:$D$47,$B$7)) -> 12179423 | H10: 6. Use a lower return or higher inflation for a more conservative plan.
A11: Annual SIP Step-Up (%) | B11: ='Common Assumptions'!$B$15 -> 10 | D11: Projected Pre-Tax Corpus | E11: {=INDEX($F$18:$F$47,$B$7)} -> 34895202
A12: LTCG Tax Rate (%) | B12: ='Common Assumptions'!$B$12 -> 12.5 | D12: Estimated LTCG Tax | E12: =MAX(0,($E$11-$E$10-$B$13)*$B$12/100) -> 2823847.5
A13: LTCG Exemption (₹) | B13: ='Common Assumptions'!$B$13 -> 125000 | D13: Projected Post-Tax Corpus | E13: =$E$11-$E$12 -> 32071355
D14: Funding Surplus / (Gap) | E14: =IF(ABS($E$13-$E$5)<1,0,$E$13-$E$5) -> 0
A15: Tax note: Instalments held 12 months or less are not treated as long-term; this model treats all gains as long-term.
A16: YEARLY STEP-UP SIP PROJECTION
A17: Year | B17: Opening Corpus | C17: Monthly SIP | D17: Annual Contribution | E17: Investment Growth | F17: Closing Pre-Tax Corpus | G17: Cumulative Contributions | H17: Estimated Tax | I17: Post-Tax Corpus | J17: Funding % | K17: Inflation-Adjusted Goal | L17: Funding Gap | M17: Year | N17: Step-Up Multiple | O17: Future Value Factor | P17: Contribution Factor
A18: 1 | B18: =IF(A18<=$B$7,$B$9,"") -> 0 | C18: =IF(A18<=$B$7,$E$7*(1+$B$11/100)^(A18-1),"") -> 17720.679 | D18: =IF(A18<=$B$7,C18*12,"") -> 212648.15 | E18: =IF(A18<=$B$7,F18-B18-D18,"") -> 12094.417 | F18: =IF(A18<=$B$7,IF($B$10=0,B18+C18*12,B18*(1+$B$10/1200)^12+C18*(((1+$B$10/1200)^12-1)/($B$10/1200))),"") -> 224742.56 | G18: =IF(A18<=$B$7,$B$9+SUM($D$18:D18),"") -> 212648.15 | H18: =IF(A18<=$B$7,MAX(0,(F18-G18-$B$13)*$B$12/100),"") -> 0 | I18: =IF(A18<=$B$7,F18-H18,"") -> 224742.56 | J18: =IF(A18<=$B$7,I18/($B$6*(1+$B$8/100)^A18),"") -> 0.021202129 | K18: =IF(A18<=$B$7,$B$6*(1+$B$8/100)^A18,"") -> 10600000 | L18: =IF(A18<=$B$7,IF(ABS(I18-K18)<1,0,I18-K18),"") -> -10375257 | M18: 1 | N18: =IF($M18<=$B$7,(1+$B$11/100)^($M18-1),0) -> 1 | O18: =IF($M18<=$B$7,$N18*IF($B$10=0,12,((1+$B$10/1200)^12-1)/($B$10/1200))*(1+$B$10/1200)^(12*($B$7-$M18)),0) -> 122.59654 | P18: =IF($M18<=$B$7,12*$N18,0) -> 12
A19: =A18+1 -> 2 | B19: =IF(A19<=$B$7,F18,"") -> 224742.56 | C19: =IF(A19<=$B$7,$E$7*(1+$B$11/100)^(A19-1),"") -> 19492.747 | D19: =IF(A19<=$B$7,C19*12,"") -> 233912.96 | E19: =IF(A19<=$B$7,F19-B19-D19,"") -> 41806.841 | F19: =IF(A19<=$B$7,IF($B$10=0,B19+C19*12,B19*(1+$B$10/1200)^12+C19*(((1+$B$10/1200)^12-1)/($B$10/1200))),"") -> 500462.37 | G19: =IF(A19<=$B$7,$B$9+SUM($D$18:D19),"") -> 446561.11 | H19: =IF(A19<=$B$7,MAX(0,(F19-G19-$B$13)*$B$12/100),"") -> 0 | I19: =IF(A19<=$B$7,F19-H19,"") -> 500462.37 | J19: =IF(A19<=$B$7,I19/($B$6*(1+$B$8/100)^A19),"") -> 0.044540973 | K19: =IF(A19<=$B$7,$B$6*(1+$B$8/100)^A19,"") -> 11236000 | L19: =IF(A19<=$B$7,IF(ABS(I19-K19)<1,0,I19-K19),"") -> -10735538 | M19: 2 | N19: =IF($M19<=$B$7,(1+$B$11/100)^($M19-1),0) -> 1.1 | O19: =IF($M19<=$B$7,$N19*IF($B$10=0,12,((1+$B$10/1200)^12-1)/($B$10/1200))*(1+$B$10/1200)^(12*($B$7-$M19)),0) -> 119.67802 | P19: =IF($M19<=$B$7,12*$N19,0) -> 13.2
A20: =A19+1 -> 3 | B20: =IF(A20<=$B$7,F19,"") -> 500462.37 | C20: =IF(A20<=$B$7,$E$7*(1+$B$11/100)^(A20-1),"") -> 21442.022 | D20: =IF(A20<=$B$7,C20*12,"") -> 257304.26 | E20: =IF(A20<=$B$7,F20-B20-D20,"") -> 78105.399 | F20: =IF(A20<=$B$7,IF($B$10=0,B20+C20*12,B20*(1+$B$10/1200)^12+C20*(((1+$B$10/1200)^12-1)/($B$10/1200))),"") -> 835872.03 | G20: =IF(A20<=$B$7,$B$9+SUM($D$18:D20),"") -> 703865.37 | H20: =IF(A20<=$B$7,MAX(0,(F20-G20-$B$13)*$B$12/100),"") -> 875.83211 | I20: =IF(A20<=$B$7,F20-H20,"") -> 834996.19 | J20: =IF(A20<=$B$7,I20/($B$6*(1+$B$8/100)^A20),"") -> 0.07010789 | K20: =IF(A20<=$B$7,$B$6*(1+$B$8/100)^A20,"") -> 11910160 | L20: =IF(A20<=$B$7,IF(ABS(I20-K20)<1,0,I20-K20),"") -> -11075164 | M20: 3 | N20: =IF($M20<=$B$7,(1+$B$11/100)^($M20-1),0) -> 1.21 | O20: =IF($M20<=$B$7,$N20*IF($B$10=0,12,((1+$B$10/1200)^12-1)/($B$10/1200))*(1+$B$10/1200)^(12*($B$7-$M20)),0) -> 116.82898 | P20: =IF($M20<=$B$7,12*$N20,0) -> 14.52
A21: =A20+1 -> 4 | B21: =IF(A21<=$B$7,F20,"") -> 835872.03 | C21: =IF(A21<=$B$7,$E$7*(1+$B$11/100)^(A21-1),"") -> 23586.224 | D21: =IF(A21<=$B$7,C21*12,"") -> 283034.68 | E21: =IF(A21<=$B$7,F21-B21-D21,"") -> 122107.16 | F21: =IF(A21<=$B$7,IF($B$10=0,B21+C21*12,B21*(1+$B$10/1200)^12+C21*(((1+$B$10/1200)^12-1)/($B$10/1200))),"") -> 1241013.9 | G21: =IF(A21<=$B$7,$B$9+SUM($D$18:D21),"") -> 986900.05 | H21: =IF(A21<=$B$7,MAX(0,(F21-G21-$B$13)*$B$12/100),"") -> 16139.228 | I21: =IF(A21<=$B$7,F21-H21,"") -> 1224874.6 | J21: =IF(A21<=$B$7,I21/($B$6*(1+$B$8/100)^A21),"") -> 0.097021544 | K21: =IF(A21<=$B$7,$B$6*(1+$B$8/100)^A21,"") -> 12624770 | L21: =IF(A21<=$B$7,IF(ABS(I21-K21)<1,0,I21-K21),"") -> -11399895 | M21: 4 | N21: =IF($M21<=$B$7,(1+$B$11/100)^($M21-1),0) -> 1.331 | O21: =IF($M21<=$B$7,$N21*IF($B$10=0,12,((1+$B$10/1200)^12-1)/($B$10/1200))*(1+$B$10/1200)^(12*($B$7-$M21)),0) -> 114.04777 | P21: =IF($M21<=$B$7,12*$N21,0) -> 15.972
A22: =A21+1 -> 5 | B22: =IF(A22<=$B$7,F21,"") -> 1241013.9 | C22: =IF(A22<=$B$7,$E$7*(1+$B$11/100)^(A22-1),"") -> 25944.846 | D22: =IF(A22<=$B$7,C22*12,"") -> 311338.15 | E22: =IF(A22<=$B$7,F22-B22-D22,"") -> 175099.06 | F22: =IF(A22<=$B$7,IF($B$10=0,B22+C22*12,B22*(1+$B$10/1200)^12+C22*(((1+$B$10/1200)^12-1)/($B$10/1200))),"") -> 1727451.1 | G22: =IF(A22<=$B$7,$B$9+SUM($D$18:D22),"") -> 1298238.2 | H22: =IF(A22<=$B$7,MAX(0,(F22-G22-$B$13)*$B$12/100),"") -> 38026.61 | I22: =IF(A22<=$B$7,F22-H22,"") -> 1689424.5 | J22: =IF(A22<=$B$7,I22/($B$6*(1+$B$8/100)^A22),"") -> 0.12624362 | K22: =IF(A22<=$B$7,$B$6*(1+$B$8/100)^A22,"") -> 13382256 | L22: =IF(A22<=$B$7,IF(ABS(I22-K22)<1,0,I22-K22),"") -> -11692831 | M22: 5 | N22: =IF($M22<=$B$7,(1+$B$11/100)^($M22-1),0) -> 1.4641 | O22: =IF($M22<=$B$7,$N22*IF($B$10=0,12,((1+$B$10/1200)^12-1)/($B$10/1200))*(1+$B$10/1200)^(12*($B$7-$M22)),0) -> 111.33277 | P22: =IF($M22<=$B$7,12*$N22,0) -> 17.5692
A23: =A22+1 -> 6 | B23: =IF(A23<=$B$7,F22,"") -> 1727451.1 | C23: =IF(A23<=$B$7,$E$7*(1+$B$11/100)^(A23-1),"") -> 28539.331 | D23: =IF(A23<=$B$7,C23*12,"") -> 342471.97 | E23: =IF(A23<=$B$7,F23-B23-D23,"") -> 238562.21 | F23: =IF(A23<=$B$7,IF($B$10=0,B23+C23*12,B23*(1+$B$10/1200)^12+C23*(((1+$B$10/1200)^12-1)/($B$10/1200))),"") -> 2308485.3 | G23: =IF(A23<=$B$7,$B$9+SUM($D$18:D23),"") -> 1640710.2 | H23: =IF(A23<=$B$7,MAX(0,(F23-G23-$B$13)*$B$12/100),"") -> 67846.887 | I23: =IF(A23<=$B$7,F23-H23,"") -> 2240638.4 | J23: =IF(A23<=$B$7,I23/($B$6*(1+$B$8/100)^A23),"") -> 0.15795616 | K23: =IF(A23<=$B$7,$B$6*(1+$B$8/100)^A23,"") -> 14185191 | L23: =IF(A23<=$B$7,IF(ABS(I23-K23)<1,0,I23-K23),"") -> -11944553 | M23: 6 | N23: =IF($M23<=$B$7,(1+$B$11/100)^($M23-1),0) -> 1.61051 | O23: =IF($M23<=$B$7,$N23*IF($B$10=0,12,((1+$B$10/1200)^12-1)/($B$10/1200))*(1+$B$10/1200)^(12*($B$7-$M23)),0) -> 108.68239 | P23: =IF($M23<=$B$7,12*$N23,0) -> 19.32612
A24: =A23+1 -> 7 | B24: =IF(A24<=$B$7,F23,"") -> 2308485.3 | C24: =IF(A24<=$B$7,$E$7*(1+$B$11/100)^(A24-1),"") -> 31393.264 | D24: =IF(A24<=$B$7,C24*12,"") -> 376719.16 | E24: =IF(A24<=$B$7,F24-B24-D24,"") -> 314199.71 | F24: =IF(A24<=$B$7,IF($B$10=0,B24+C24*12,B24*(1+$B$10/1200)^12+C24*(((1+$B$10/1200)^12-1)/($B$10/1200))),"") -> 2999404.1 | G24: =IF(A24<=$B$7,$B$9+SUM($D$18:D24),"") -> 2017429.3 | H24: =IF(A24<=$B$7,MAX(0,(F24-G24-$B$13)*$B$12/100),"") -> 107121.85 | I24: =IF(A24<=$B$7,F24-H24,"") -> 2892282.3 | J24: =IF(A24<=$B$7,I24/($B$6*(1+$B$8/100)^A24),"") -> 0.19235329 | K24: =IF(A24<=$B$7,$B$6*(1+$B$8/100)^A24,"") -> 15036303 | L24: =IF(A24<=$B$7,IF(ABS(I24-K24)<1,0,I24-K24),"") -> -12144020 | M24: 7 | N24: =IF($M24<=$B$7,(1+$B$11/100)^($M24-1),0) -> 1.771561 | O24: =IF($M24<=$B$7,$N24*IF($B$10=0,12,((1+$B$10/1200)^12-1)/($B$10/1200))*(1+$B$10/1200)^(12*($B$7-$M24)),0) -> 106.09512 | P24: =IF($M24<=$B$7,12*$N24,0) -> 21.258732
A25: =A24+1 -> 8 | B25: =IF(A25<=$B$7,F24,"") -> 2999404.1 | C25: =IF(A25<=$B$7,$E$7*(1+$B$11/100)^(A25-1),"") -> 34532.59 | D25: =IF(A25<=$B$7,C25*12,"") -> 414391.08 | E25: =IF(A25<=$B$7,F25-B25-D25,"") -> 403968.12 | F25: =IF(A25<=$B$7,IF($B$10=0,B25+C25*12,B25*(1+$B$10/1200)^12+C25*(((1+$B$10/1200)^12-1)/($B$10/1200))),"") -> 3817763.3 | G25: =IF(A25<=$B$7,$B$9+SUM($D$18:D25),"") -> 2431820.4 | H25: =IF(A25<=$B$7,MAX(0,(F25-G25-$B$13)*$B$12/100),"") -> 157617.87 | I25: =IF(A25<=$B$7,F25-H25,"") -> 3660145.5 | J25: =IF(A25<=$B$7,I25/($B$6*(1+$B$8/100)^A25),"") -> 0.22964206 | K25: =IF(A25<=$B$7,$B$6*(1+$B$8/100)^A25,"") -> 15938481 | L25: =IF(A25<=$B$7,IF(ABS(I25-K25)<1,0,I25-K25),"") -> -12278335 | M25: 8 | N25: =IF($M25<=$B$7,(1+$B$11/100)^($M25-1),0) -> 1.9487171 | O25: =IF($M25<=$B$7,$N25*IF($B$10=0,12,((1+$B$10/1200)^12-1)/($B$10/1200))*(1+$B$10/1200)^(12*($B$7-$M25)),0) -> 103.56943 | P25: =IF($M25<=$B$7,12*$N25,0) -> 23.384605
A26: =A25+1 -> 9 | B26: =IF(A26<=$B$7,F25,"") -> 3817763.3 | C26: =IF(A26<=$B$7,$E$7*(1+$B$11/100)^(A26-1),"") -> 37985.849 | D26: =IF(A26<=$B$7,C26*12,"") -> 455830.19 | E26: =IF(A26<=$B$7,F26-B26-D26,"") -> 510113.41 | F26: =IF(A26<=$B$7,IF($B$10=0,B26+C26*12,B26*(1+$B$10/1200)^12+C26*(((1+$B$10/1200)^12-1)/($B$10/1200))),"") -> 4783706.9 | G26: =IF(A26<=$B$7,$B$9+SUM($D$18:D26),"") -> 2887650.6 | H26: =IF(A26<=$B$7,MAX(0,(F26-G26-$B$13)*$B$12/100),"") -> 221382.04 | I26: =IF(A26<=$B$7,F26-H26,"") -> 4562324.9 | J26: =IF(A26<=$B$7,I26/($B$6*(1+$B$8/100)^A26),"") -> 0.27004331 | K26: =IF(A26<=$B$7,$B$6*(1+$B$8/100)^A26,"") -> 16894790 | L26: =IF(A26<=$B$7,IF(ABS(I26-K26)<1,0,I26-K26),"") -> -12332465 | M26: 9 | N26: =IF($M26<=$B$7,(1+$B$11/100)^($M26-1),0) -> 2.1435888 | O26: =IF($M26<=$B$7,$N26*IF($B$10=0,12,((1+$B$10/1200)^12-1)/($B$10/1200))*(1+$B$10/1200)^(12*($B$7-$M26)),0) -> 101.10387 | P26: =IF($M26<=$B$7,12*$N26,0) -> 25.723066
A27: =A26+1 -> 10 | B27: =IF(A27<=$B$7,F26,"") -> 4783706.9 | C27: =IF(A27<=$B$7,$E$7*(1+$B$11/100)^(A27-1),"") -> 41784.434 | D27: =IF(A27<=$B$7,C27*12,"") -> 501413.21 | E27: =IF(A27<=$B$7,F27-B27-D27,"") -> 635211.78 | F27: =IF(A27<=$B$7,IF($B$10=0,B27+C27*12,B27*(1+$B$10/1200)^12+C27*(((1+$B$10/1200)^12-1)/($B$10/1200))),"") -> 5920331.9 | G27: =IF(A27<=$B$7,$B$9+SUM($D$18:D27),"") -> 3389063.8 | H27: =IF(A27<=$B$7,MAX(0,(F27-G27-$B$13)*$B$12/100),"") -> 300783.51 | I27: =IF(A27<=$B$7,F27-H27,"") -> 5619548.4 | J27: =IF(A27<=$B$7,I27/($B$6*(1+$B$8/100)^A27),"") -> 0.31379265 | K27: =IF(A27<=$B$7,$B$6*(1+$B$8/100)^A27,"") -> 17908477 | L27: =IF(A27<=$B$7,IF(ABS(I27-K27)<1,0,I27-K27),"") -> -12288929 | M27: 10 | N27: =IF($M27<=$B$7,(1+$B$11/100)^($M27-1),0) -> 2.3579477 | O27: =IF($M27<=$B$7,$N27*IF($B$10=0,12,((1+$B$10/1200)^12-1)/($B$10/1200))*(1+$B$10/1200)^(12*($B$7-$M27)),0) -> 98.69701 | P27: =IF($M27<=$B$7,12*$N27,0) -> 28.295372
A28: =A27+1 -> 11 | B28: =IF(A28<=$B$7,F27,"") -> 5920331.9 | C28: =IF(A28<=$B$7,$E$7*(1+$B$11/100)^(A28-1),"") -> 45962.877 | D28: =IF(A28<=$B$7,C28*12,"") -> 551554.53 | E28: =IF(A28<=$B$7,F28-B28-D28,"") -> 782216.08 | F28: =IF(A28<=$B$7,IF($B$10=0,B28+C28*12,B28*(1+$B$10/1200)^12+C28*(((1+$B$10/1200)^12-1)/($B$10/1200))),"") -> 7254102.5 | G28: =IF(A28<=$B$7,$B$9+SUM($D$18:D28),"") -> 3940618.3 | H28: =IF(A28<=$B$7,MAX(0,(F28-G28-$B$13)*$B$12/100),"") -> 398560.52 | I28: =IF(A28<=$B$7,F28-H28,"") -> 6855542 | J28: =IF(A28<=$B$7,I28/($B$6*(1+$B$8/100)^A28),"") -> 0.3611414 | K28: =IF(A28<=$B$7,$B$6*(1+$B$8/100)^A28,"") -> 18982986 | L28: =IF(A28<=$B$7,IF(ABS(I28-K28)<1,0,I28-K28),"") -> -12127444 | M28: 11 | N28: =IF($M28<=$B$7,(1+$B$11/100)^($M28-1),0) -> 2.5937425 | O28: =IF($M28<=$B$7,$N28*IF($B$10=0,12,((1+$B$10/1200)^12-1)/($B$10/1200))*(1+$B$10/1200)^(12*($B$7-$M28)),0) -> 96.347443 | P28: =IF($M28<=$B$7,12*$N28,0) -> 31.12491
A29: =A28+1 -> 12 | B29: =IF(A29<=$B$7,F28,"") -> 7254102.5 | C29: =IF(A29<=$B$7,$E$7*(1+$B$11/100)^(A29-1),"") -> 50559.165 | D29: =IF(A29<=$B$7,C29*12,"") -> 606709.98 | E29: =IF(A29<=$B$7,F29-B29-D29,"") -> 954508.55 | F29: =IF(A29<=$B$7,IF($B$10=0,B29+C29*12,B29*(1+$B$10/1200)^12+C29*(((1+$B$10/1200)^12-1)/($B$10/1200))),"") -> 8815321.1 | G29: =IF(A29<=$B$7,$B$9+SUM($D$18:D29),"") -> 4547328.3 | H29: =IF(A29<=$B$7,MAX(0,(F29-G29-$B$13)*$B$12/100),"") -> 517874.09 | I29: =IF(A29<=$B$7,F29-H29,"") -> 8297447 | J29: =IF(A29<=$B$7,I29/($B$6*(1+$B$8/100)^A29),"") -> 0.41235769 | K29: =IF(A29<=$B$7,$B$6*(1+$B$8/100)^A29,"") -> 20121965 | L29: =IF(A29<=$B$7,IF(ABS(I29-K29)<1,0,I29-K29),"") -> -11824518 | M29: 12 | N29: =IF($M29<=$B$7,(1+$B$11/100)^($M29-1),0) -> 2.8531167 | O29: =IF($M29<=$B$7,$N29*IF($B$10=0,12,((1+$B$10/1200)^12-1)/($B$10/1200))*(1+$B$10/1200)^(12*($B$7-$M29)),0) -> 94.05381 | P29: =IF($M29<=$B$7,12*$N29,0) -> 34.2374
A30: =A29+1 -> 13 | B30: =IF(A30<=$B$7,F29,"") -> 8815321.1 | C30: =IF(A30<=$B$7,$E$7*(1+$B$11/100)^(A30-1),"") -> 55615.082 | D30: =IF(A30<=$B$7,C30*12,"") -> 667380.98 | E30: =IF(A30<=$B$7,F30-B30-D30,"") -> 1155960.8 | F30: =IF(A30<=$B$7,IF($B$10=0,B30+C30*12,B30*(1+$B$10/1200)^12+C30*(((1+$B$10/1200)^12-1)/($B$10/1200))),"") -> 10638663 | G30: =IF(A30<=$B$7,$B$9+SUM($D$18:D30),"") -> 5214709.3 | H30: =IF(A30<=$B$7,MAX(0,(F30-G30-$B$13)*$B$12/100),"") -> 662369.19 | I30: =IF(A30<=$B$7,F30-H30,"") -> 9976293.7 | J30: =IF(A30<=$B$7,I30/($B$6*(1+$B$8/100)^A30),"") -> 0.46772758 | K30: =IF(A30<=$B$7,$B$6*(1+$B$8/100)^A30,"") -> 21329283 | L30: =IF(A30<=$B$7,IF(ABS(I30-K30)<1,0,I30-K30),"") -> -11352989 | M30: 13 | N30: =IF($M30<=$B$7,(1+$B$11/100)^($M30-1),0) -> 3.1384284 | O30: =IF($M30<=$B$7,$N30*IF($B$10=0,12,((1+$B$10/1200)^12-1)/($B$10/1200))*(1+$B$10/1200)^(12*($B$7-$M30)),0) -> 91.814779 | P30: =IF($M30<=$B$7,12*$N30,0) -> 37.661141
... A47: =A46+1 -> 30 | B47: =IF(A47<=$B$7,F46,"") | C47: =IF(A47<=$B$7,$E$7*(1+$B$11/100)^(A47-1),"") | D47: =IF(A47<=$B$7,C47*12,"") | E47: =IF(A47<=$B$7,F47-B47-D47,"") | F47: =IF(A47<=$B$7,IF($B$10=0,B47+C47*12,B47*(1+$B$10/1200)^12+C47*(((1+$B$10/1200)^12-1)/($B$10/1200))),"") | G47: =IF(A47<=$B$7,$B$9+SUM($D$18:D47),"") | H47: =IF(A47<=$B$7,MAX(0,(F47-G47-$B$13)*$B$12/100),"") | I47: =IF(A47<=$B$7,F47-H47,"") | J47: =IF(A47<=$B$7,I47/($B$6*(1+$B$8/100)^A47),"") | K47: =IF(A47<=$B$7,$B$6*(1+$B$8/100)^A47,"") | L47: =IF(A47<=$B$7,IF(ABS(I47-K47)<1,0,I47-K47),"") | M47: 30 | N47: =IF($M47<=$B$7,(1+$B$11/100)^($M47-1),0) -> 0 | O47: =IF($M47<=$B$7,$N47*IF($B$10=0,12,((1+$B$10/1200)^12-1)/($B$10/1200))*(1+$B$10/1200)^(12*($B$7-$M47)),0) -> 0 | P47: =IF($M47<=$B$7,12*$N47,0) -> 0
M49: FV per ₹1 starting monthly SIP | N49: =SUM(O18:O47) -> 1969.1798
M50: Contribution per ₹1 starting monthly SIP | N50: =SUM(P18:P47) -> 687.29999
M51: Required SIP before tax | N51: =MAX(0,($E$5-$E$6)/$N$49) -> 16286.657
M52: Gain at before-tax SIP | N52: =$E$6+$N$49*$N$51-$B$9-$N$50*$N$51 -> 20877536
M53: Required SIP after tax | N53: =MAX(0,($E$5-$E$6+($B$12/100)*($E$6-$B$9-$B$13))/($N$49-($B$12/100)*($N$49-$N$50))) -> 17720.679

Sheet Prepay vs Invest
A1: PREPAY LOAN VS INVEST — DECISION CALCULATOR
A2: Compare the certainty of loan-interest savings with the higher but uncertain potential of investing the same surplus.
A4: YOUR INPUTS | D4: DECISION SUMMARY | H4: COACH'S READ
A5: Outstanding Loan (₹) | B5: 10000000 | D5: Normal Monthly EMI | E5: =-PMT($B$6/1200,$B$7*12,$B$5) -> 80559.319 | H5: 1. Prepayment earns a certain return close to the loan rate: every rupee of interest avoided is guaranteed.
A6: Loan Interest (% p.a.) | B6: ='Common Assumptions'!$B$7 -> 7.5 | D6: Net Investment Return Assumption | E6: =($B$13-$B$14)/100 -> 0.115
A7: Remaining Tenure (years) | B7: 20 | D7: Invest Surplus: Post-Tax Wealth | E7: {=INDEX('PVI Engine'!$L$2:$L$361,$B$7*12)} -> 12322162 | H7: 2. Investing can create more wealth, but returns arrive unevenly and may fall below the assumption.
A8: One-Time Surplus (₹) | B8: 500000 | D8: Prepay — Reduce Tenure: Liquid Wealth | E8: {=INDEX('PVI Engine'!$W$2:$W$361,$B$7*12)} -> 8289116.7
A9: Lump Sum Applied in Month | B9: 12 | D9: Prepay — Reduce EMI: Liquid Wealth | E9: {=INDEX('PVI Engine'!$AH$2:$AH$361,$B$7*12)} -> 10096414 | H9: 3. Keep an emergency fund before either choice; prepayments are difficult to reverse when cash is needed.
A10: Monthly Surplus (₹) | B10: 10000 | D10: Interest Saved — Reduce Tenure | E10: =SUM('PVI Engine'!$C$2:INDEX('PVI Engine'!$C$2:$C$361,$B$7*12))-SUM('PVI Engine'!$N$2:INDEX('PVI Engine'!$N$2:$N$361,$B$7*12)) -> 3233552.4
A11: Monthly Surplus Starts in Month | B11: 1 | D11: Interest Saved — Reduce EMI | E11: =SUM('PVI Engine'!$C$2:INDEX('PVI Engine'!$C$2:$C$361,$B$7*12))-SUM('PVI Engine'!$Y$2:INDEX('PVI Engine'!$Y$2:$Y$361,$B$7*12)) -> 1488572 | H11: 4. Compare the modeled wealth difference with market risk, liquidity, and the certainty of interest saved; a small edge may not be decisive.
A12: Monthly Surplus Ends in Month | B12: 240 | D12: Loan-Free Month — Reduce Tenure | E12: =IFERROR(MATCH(0,'PVI Engine'!$Q$2:INDEX('PVI Engine'!$Q$2:$Q$361,$B$7*12),0),$B$7*12) -> 173
A13: Expected Gross Investment Return (% p.a.) | B13: ='Common Assumptions'!$B$6 -> 12 | D13: Expected Wealth Edge vs Best Prepay | E13: =E7-MAX(E8,E9) -> 2225747.9 | H13: 5. Reduce tenure usually saves more interest; reduce EMI improves monthly breathing room.
A14: Investment Expense Ratio (% p.a.) | B14: ='Common Assumptions'!$B$10 -> 0.5 | D14: Rule-of-Thumb Gross Return Hurdle | E14: =($B$6/(1-$B$15/100))+$B$14 -> 9.0714286
A15: LTCG Tax Rate (%) | B15: ='Common Assumptions'!$B$12 -> 12.5 | D15: Model Recommendation | E15: =IF($B$18<>"Yes","BUILD EMERGENCY FUND FIRST",IF(OR($B$20="Debt-free",$B$19="Low"),"LEAN TOWARD PREPAYMENT",IF(E13>0,"MODELED WEALTH FAVOURS INVESTING; WEIGH RISK AND LIQUIDITY","MODELED WEALTH FAVOURS PREPAYMENT"))) -> MODELED WEALTH FAVOURS INVESTING; WEIGH RISK AND LIQUIDITY | H15: 6. Review the decision yearly when rates, income, tax rules, or risk comfort change.
A16: LTCG Exemption (₹) | B16: ='Common Assumptions'!$B$13 -> 125000
A17: Inflation (% p.a.) | B17: ='Common Assumptions'!$B$5 -> 6 | D17: Invest wealth — real (today's rupees) | E17: =$E$7/(1+$B$17/100)^$B$7 -> 3842108.4
A18: Emergency Fund Ready? | B18: Yes | D18: Prepay reduce-tenure — real (today's rupees) | E18: =$E$8/(1+$B$17/100)^$B$7 -> 2584585.8
A19: Risk Comfort | B19: Medium | D19: Prepay reduce-EMI — real (today's rupees) | E19: =$E$9/(1+$B$17/100)^$B$7 -> 3148109.7
A20: Decision Preference | B20: Balanced | E20: Break-even return: not computed. As a simple reference, compare the net return assumption with the Rule-of-Thumb Hurdle above.
A23: YEAR-END COMPARISON
A24: Year | B24: Normal Loan Balance | C24: Invest Post-Tax Wealth | D24: Reduce-Tenure Balance | E24: Reduce-Tenure Wealth | F24: Reduce-EMI Balance | G24: Reduce-EMI Wealth | H24: Expected Leader
A25: 1 | B25: {=IF(A25<=$B$7,INDEX('PVI Engine'!$F$2:$F$361,A25*12),"")} -> 9775681.3 | C25: {=IF(A25<=$B$7,INDEX('PVI Engine'!$L$2:$L$361,A25*12),"")} -> 626531.47 | D25: {=IF(A25<=$B$7,INDEX('PVI Engine'!$Q$2:$Q$361,A25*12),"")} -> 9151469.1 | E25: {=IF(A25<=$B$7,INDEX('PVI Engine'!$W$2:$W$361,A25*12),"")} -> 0 | F25: {=IF(A25<=$B$7,INDEX('PVI Engine'!$AB$2:$AB$361,A25*12),"")} -> 9156941.8 | G25: {=IF(A25<=$B$7,INDEX('PVI Engine'!$AH$2:$AH$361,A25*12),"")} -> 5534.2556 | H25: =IF(A25>$B$7,"",IF(C25>=MAX(E25,G25),"Invest",IF(E25>=G25,"Prepay: Tenure","Prepay: EMI"))) -> Invest
A26: 2 | B26: {=IF(A26<=$B$7,INDEX('PVI Engine'!$F$2:$F$361,A26*12),"")} -> 9533948.1 | C26: {=IF(A26<=$B$7,INDEX('PVI Engine'!$L$2:$L$361,A26*12),"")} -> 829035.73 | D26: {=IF(A26<=$B$7,INDEX('PVI Engine'!$Q$2:$Q$361,A26*12),"")} -> 8737064.6 | E26: {=IF(A26<=$B$7,INDEX('PVI Engine'!$W$2:$W$361,A26*12),"")} -> 0 | F26: {=IF(A26<=$B$7,INDEX('PVI Engine'!$AB$2:$AB$361,A26*12),"")} -> 8811899.5 | G26: {=IF(A26<=$B$7,INDEX('PVI Engine'!$AH$2:$AH$361,A26*12),"")} -> 76388.371 | H26: =IF(A26>$B$7,"",IF(C26>=MAX(E26,G26),"Invest",IF(E26>=G26,"Prepay: Tenure","Prepay: EMI"))) -> Invest
A27: 3 | B27: {=IF(A27<=$B$7,INDEX('PVI Engine'!$F$2:$F$361,A27*12),"")} -> 9273448.6 | C27: {=IF(A27<=$B$7,INDEX('PVI Engine'!$L$2:$L$361,A27*12),"")} -> 1047208.6 | D27: {=IF(A27<=$B$7,INDEX('PVI Engine'!$Q$2:$Q$361,A27*12),"")} -> 8290488.8 | E27: {=IF(A27<=$B$7,INDEX('PVI Engine'!$W$2:$W$361,A27*12),"")} -> 0 | F27: {=IF(A27<=$B$7,INDEX('PVI Engine'!$AB$2:$AB$361,A27*12),"")} -> 8452666.9 | G27: {=IF(A27<=$B$7,INDEX('PVI Engine'!$AH$2:$AH$361,A27*12),"")} -> 168664.46 | H27: =IF(A27>$B$7,"",IF(C27>=MAX(E27,G27),"Invest",IF(E27>=G27,"Prepay: Tenure","Prepay: EMI"))) -> Invest
A28: 4 | B28: {=IF(A28<=$B$7,INDEX('PVI Engine'!$F$2:$F$361,A28*12),"")} -> 8992725.9 | C28: {=IF(A28<=$B$7,INDEX('PVI Engine'!$L$2:$L$361,A28*12),"")} -> 1284977.4 | D28: {=IF(A28<=$B$7,INDEX('PVI Engine'!$Q$2:$Q$361,A28*12),"")} -> 7809244.1 | E28: {=IF(A28<=$B$7,INDEX('PVI Engine'!$W$2:$W$361,A28*12),"")} -> 0 | F28: {=IF(A28<=$B$7,INDEX('PVI Engine'!$AB$2:$AB$361,A28*12),"")} -> 8078496.5 | G28: {=IF(A28<=$B$7,INDEX('PVI Engine'!$AH$2:$AH$361,A28*12),"")} -> 285320.76 | H28: =IF(A28>$B$7,"",IF(C28>=MAX(E28,G28),"Invest",IF(E28>=G28,"Prepay: Tenure","Prepay: EMI"))) -> Invest
A29: 5 | B29: {=IF(A29<=$B$7,INDEX('PVI Engine'!$F$2:$F$361,A29*12),"")} -> 8690209.8 | C29: {=IF(A29<=$B$7,INDEX('PVI Engine'!$L$2:$L$361,A29*12),"")} -> 1549759 | D29: {=IF(A29<=$B$7,INDEX('PVI Engine'!$Q$2:$Q$361,A29*12),"")} -> 7290639.2 | E29: {=IF(A29<=$B$7,INDEX('PVI Engine'!$W$2:$W$361,A29*12),"")} -> 0 | F29: {=IF(A29<=$B$7,INDEX('PVI Engine'!$AB$2:$AB$361,A29*12),"")} -> 7688633.2 | G29: {=IF(A29<=$B$7,INDEX('PVI Engine'!$AH$2:$AH$361,A29*12),"")} -> 429725.7 | H29: =IF(A29>$B$7,"",IF(C29>=MAX(E29,G29),"Invest",IF(E29>=G29,"Prepay: Tenure","Prepay: EMI"))) -> Invest
A30: 6 | B30: {=IF(A30<=$B$7,INDEX('PVI Engine'!$F$2:$F$361,A30*12),"")} -> 8364208.7 | C30: {=IF(A30<=$B$7,INDEX('PVI Engine'!$L$2:$L$361,A30*12),"")} -> 1844828.9 | D30: {=IF(A30<=$B$7,INDEX('PVI Engine'!$Q$2:$Q$361,A30*12),"")} -> 6731773.6 | E30: {=IF(A30<=$B$7,INDEX('PVI Engine'!$W$2:$W$361,A30*12),"")} -> 0 | F30: {=IF(A30<=$B$7,INDEX('PVI Engine'!$AB$2:$AB$361,A30*12),"")} -> 7282324.5 | G30: {=IF(A30<=$B$7,INDEX('PVI Engine'!$AH$2:$AH$361,A30*12),"")} -> 603643.04 | H30: =IF(A30>$B$7,"",IF(C30>=MAX(E30,G30),"Invest",IF(E30>=G30,"Prepay: Tenure","Prepay: EMI"))) -> Invest
A31: 7 | B31: {=IF(A31<=$B$7,INDEX('PVI Engine'!$F$2:$F$361,A31*12),"")} -> 8012899.3 | C31: {=IF(A31<=$B$7,INDEX('PVI Engine'!$L$2:$L$361,A31*12),"")} -> 2173859.9 | D31: {=IF(A31<=$B$7,INDEX('PVI Engine'!$Q$2:$Q$361,A31*12),"")} -> 6129521.9 | E31: {=IF(A31<=$B$7,INDEX('PVI Engine'!$W$2:$W$361,A31*12),"")} -> 0 | F31: {=IF(A31<=$B$7,INDEX('PVI Engine'!$AB$2:$AB$361,A31*12),"")} -> 6858832.8 | G31: {=IF(A31<=$B$7,INDEX('PVI Engine'!$AH$2:$AH$361,A31*12),"")} -> 805544.15 | H31: =IF(A31>$B$7,"",IF(C31>=MAX(E31,G31),"Invest",IF(E31>=G31,"Prepay: Tenure","Prepay: EMI"))) -> Invest
A32: 8 | B32: {=IF(A32<=$B$7,INDEX('PVI Engine'!$F$2:$F$361,A32*12),"")} -> 7634316.8 | C32: {=IF(A32<=$B$7,INDEX('PVI Engine'!$L$2:$L$361,A32*12),"")} -> 2540970.1 | D32: {=IF(A32<=$B$7,INDEX('PVI Engine'!$Q$2:$Q$361,A32*12),"")} -> 5480515.7 | E32: {=IF(A32<=$B$7,INDEX('PVI Engine'!$W$2:$W$361,A32*12),"")} -> 0 | F32: {=IF(A32<=$B$7,INDEX('PVI Engine'!$AB$2:$AB$361,A32*12),"")} -> 6417455.1 | G32: {=IF(A32<=$B$7,INDEX('PVI Engine'!$AH$2:$AH$361,A32*12),"")} -> 1045105.1 | H32: =IF(A32>$B$7,"",IF(C32>=MAX(E32,G32),"Invest",IF(E32>=G32,"Prepay: Tenure","Prepay: EMI"))) -> Invest
A33: 9 | B33: {=IF(A33<=$B$7,INDEX('PVI Engine'!$F$2:$F$361,A33*12),"")} -> 7226344 | C33: {=IF(A33<=$B$7,INDEX('PVI Engine'!$L$2:$L$361,A33*12),"")} -> 2950777 | D33: {=IF(A33<=$B$7,INDEX('PVI Engine'!$Q$2:$Q$361,A33*12),"")} -> 4781125.6 | E33: {=IF(A33<=$B$7,INDEX('PVI Engine'!$W$2:$W$361,A33*12),"")} -> 0 | F33: {=IF(A33<=$B$7,INDEX('PVI Engine'!$AB$2:$AB$361,A33*12),"")} -> 5957547.7 | G33: {=IF(A33<=$B$7,INDEX('PVI Engine'!$AH$2:$AH$361,A33*12),"")} -> 1327426.5 | H33: =IF(A33>$B$7,"",IF(C33>=MAX(E33,G33),"Invest",IF(E33>=G33,"Prepay: Tenure","Prepay: EMI"))) -> Invest
A34: 10 | B34: {=IF(A34<=$B$7,INDEX('PVI Engine'!$F$2:$F$361,A34*12),"")} -> 6786699.1 | C34: {=IF(A34<=$B$7,INDEX('PVI Engine'!$L$2:$L$361,A34*12),"")} -> 3408457.9 | D34: {=IF(A34<=$B$7,INDEX('PVI Engine'!$Q$2:$Q$361,A34*12),"")} -> 4027439.9 | E34: {=IF(A34<=$B$7,INDEX('PVI Engine'!$W$2:$W$361,A34*12),"")} -> 0 | F34: {=IF(A34<=$B$7,INDEX('PVI Engine'!$AB$2:$AB$361,A34*12),"")} -> 5478562.5 | G34: {=IF(A34<=$B$7,INDEX('PVI Engine'!$AH$2:$AH$361,A34*12),"")} -> 1658363.9 | H34: =IF(A34>$B$7,"",IF(C34>=MAX(E34,G34),"Invest",IF(E34>=G34,"Prepay: Tenure","Prepay: EMI"))) -> Invest
A35: 11 | B35: {=IF(A35<=$B$7,INDEX('PVI Engine'!$F$2:$F$361,A35*12),"")} -> 6312923.5 | C35: {=IF(A35<=$B$7,INDEX('PVI Engine'!$L$2:$L$361,A35*12),"")} -> 3919818 | D35: {=IF(A35<=$B$7,INDEX('PVI Engine'!$Q$2:$Q$361,A35*12),"")} -> 3215243.7 | E35: {=IF(A35<=$B$7,INDEX('PVI Engine'!$W$2:$W$361,A35*12),"")} -> 0 | F35: {=IF(A35<=$B$7,INDEX('PVI Engine'!$AB$2:$AB$361,A35*12),"")} -> 4980098.8 | G35: {=IF(A35<=$B$7,INDEX('PVI Engine'!$AH$2:$AH$361,A35*12),"")} -> 2044661.8 | H35: =IF(A35>$B$7,"",IF(C35>=MAX(E35,G35),"Invest",IF(E35>=G35,"Prepay: Tenure","Prepay: EMI"))) -> Invest
A36: 12 | B36: {=IF(A36<=$B$7,INDEX('PVI Engine'!$F$2:$F$361,A36*12),"")} -> 5802367.5 | C36: {=IF(A36<=$B$7,INDEX('PVI Engine'!$L$2:$L$361,A36*12),"")} -> 4491366.3 | D36: {=IF(A36<=$B$7,INDEX('PVI Engine'!$Q$2:$Q$361,A36*12),"")} -> 2339994.6 | E36: {=IF(A36<=$B$7,INDEX('PVI Engine'!$W$2:$W$361,A36*12),"")} -> 0 | F36: {=IF(A36<=$B$7,INDEX('PVI Engine'!$AB$2:$AB$361,A36*12),"")} -> 4461978.1 | G36: {=IF(A36<=$B$7,INDEX('PVI Engine'!$AH$2:$AH$361,A36*12),"")} -> 2494123.1 | H36: =IF(A36>$B$7,"",IF(C36>=MAX(E36,G36),"Invest",IF(E36>=G36,"Prepay: Tenure","Prepay: EMI"))) -> Invest
... A54: 30 | B54: {=IF(A54<=$B$7,INDEX('PVI Engine'!$F$2:$F$361,A54*12),"")} | C54: {=IF(A54<=$B$7,INDEX('PVI Engine'!$L$2:$L$361,A54*12),"")} | D54: {=IF(A54<=$B$7,INDEX('PVI Engine'!$Q$2:$Q$361,A54*12),"")} | E54: {=IF(A54<=$B$7,INDEX('PVI Engine'!$W$2:$W$361,A54*12),"")} | F54: {=IF(A54<=$B$7,INDEX('PVI Engine'!$AB$2:$AB$361,A54*12),"")} | G54: {=IF(A54<=$B$7,INDEX('PVI Engine'!$AH$2:$AH$361,A54*12),"")} | H54: =IF(A54>$B$7,"",IF(C54>=MAX(E54,G54),"Invest",IF(E54>=G54,"Prepay: Tenure","Prepay: EMI")))
A57: HOW TO USE THIS DECISION
A58: Question | B58: Finance-coach guidance
A59: What does prepayment earn? | B59: Approximately the loan interest rate, with certainty, before considering any eligible loan tax benefit.
A60: What must investing beat? | B60: The calculator shows a tax-adjusted gross-return hurdle. Treat it as a planning guide, not a precise forecast.
A61: When does prepayment fit best? | B61: When the emergency fund is ready, the loan rate is high, income is uncertain, risk comfort is low, or becoming debt-free has strong emotional value.
A62: When can investing fit better? | B62: When cash reserves are strong, the horizon is long, the investor can tolerate losses, and the expected post-tax return meaningfully exceeds the loan rate.
A63: Why compare reduce tenure and EMI? | B63: Reducing tenure normally maximizes interest savings; reducing EMI improves cash flow and may suit households with variable income.
A64: What is a sensible middle path? | B64: Split the surplus—for example, direct part to prepayment and invest the rest—especially when the modeled advantage is narrow.
A65: Important limitation | B65: Returns, inflation, expenses and tax are assumptions. The model excludes loan tax benefits, lender fees, penalties, cess, surcharge and tax-lot timing.
A66: What is One-Time Surplus? | B66: A single amount available only once—such as a bonus, maturity proceeds, or idle cash. The calculator compares using this same amount to prepay the loan versus investing it.
A67: What is Lump Sum Applied in Month? | B67: The loan month when the one-time surplus is deployed. Month 1 means immediately; month 12 means after 12 monthly EMIs. With the current inputs, ₹5,00,000 is applied in month 12 in both comparison paths.

Sheet Retirement SWP
A1: RETIREMENT CORPUS & SWP PLANNER
